Workbook

Sheet Guide
A1: Micron (MU) Cycle Valuation Model — Guide
A3: Purpose of This Model
A4: Cyclicals like memory cannot be valued on P/E. At the peak, earnings are highest so P/E looks lowest;
A5: at the trough, losses make P/E meaningless. This model offers three alternatives.
A7: ① P/B × ROE | B7: Assumes a sustainable ROE and solves for justified P/B. The standard memory-sector frame.
A8: (2) Normalized earnings | B8: Builds a normalized EPS on mid-cycle margins and applies a multiple.
A9: (3) Probability-weighted scenarios | B9: Assigns probabilities to bull, base and bear cases to produce an expected value.
A11: The Most Useful Way to Read This
A12: Rather than asking what the fair value is, it is more practical to back-solve what the current price already assumes.
A13: On the PB_ROE_Model tab, find the ROE in the sensitivity grid that corresponds to the current price.
A14: Then the only judgment left is whether you believe that ROE.
A16: Cell Colour Legend
A17: Blue text | B17: Hardcoded input or scenario lever
A18: Black text | B18: Formula (calculated automatically - do not edit)
A19: Green text | B19: Reference to another sheet
A20: Yellow fill | B20: [*] Edit here - key assumption input cells
A23: Tab Layout
A24: Assumptions | B24: [*] All inputs live here. Start on this tab.
A25: CurrentData | B25: Micron actuals as of 2026-07-28, with sources noted
A26: HistoricalCycle | B26: Results and valuation from FY2021 to date - context for where the cycle stands
A27: PB_ROE_Model | B27: Justified P/B = (ROE-g)/(COE-g), with an ROE by g sensitivity grid
A28: NormalizedEarnings | B28: Normalized revenue x margin gives normalized EPS, then a target multiple; margin by multiple grid
A29: Scenarios | B29: Probability-weighted expected value across bull, base and bear
A30: Consensus | B30: Full analyst estimates FY2025(A) to FY2029(E) - median, low, high and estimate counts
A31: ConsensusValuation | B31: [*] Forward P/E, P/B and EV/EBITDA by year, plus a consensus achievement (haircut) adjustment
A32: Disclaimer: This file is a template for learning valuation methodology. It is not investment advice, and every assumption must be independently verified by the user.
A33: Created 2026-07-28. Market data sources: Finviz, stockanalysis.com (Fiscal.ai)
A35: Key finding: On the FY2028 consensus BPS of $437.94, forward P/B is 1.91x - below the five-year average of 1.95x.
A36: That assumes consensus is realized in full, including a 70.7% FY2027 net margin. Stress it by lowering the achievement rate on the ConsensusValuation tab.
A39: Added 2026-07-31 — Mix-Based ROE Build-up (tabs 12-15)
A40: MixPath | B40: Wafer allocation to bit share to revenue mix. Anchored on TrendForce actuals with an [*] ASP premium lever.
A41: SegmentMargin | B41: Segment OPM to blended EBIT margin. [*] Cross-check 1 against consensus EBIT margin, deriving the achievement rate.
A42: ROE_Build | B42: Derives ROE via two-factor DuPont. [*] Cross-check 2 against consensus ROE.
A43: TerminalROE | B43: Applies a through-cycle adjustment. RIM_3Stage B10 reads this; manual entry retired.
A45: Note: The information hierarchy has been inverted. Previously terminal ROE was entered by hand and a price fell out. Now ROE is derived from wafer allocation and consensus becomes the thing being tested.
A46: Note: [*] Input cells - MixPath B6:E8 (wafer share, trade ratio, DRAM share) and B11 (premium case); SegmentMargin B6:E8 (segment OPM); TerminalROE B13 (smoothing efficiency).
A48: Added 2026-07-31 (second pass) — ASP Drivers and the Multiple Explanation Layer
A49: SegmentMargin rows 37-52 | B49: (17) ASP Drivers. Retires manual OPM entry and derives it from ASP indices: OPM = 1 - (1 - base OPM) / ASP index.
A50: Scenarios rows 32-63 | B50: (16) Derivation block. Adjusting only three indices - commodity spot ASP, HBM contract ASP and NAND ASP - derives premium, mix, revenue and margin.
A51: PB_Bridge | B51: (18) Splits P/B into three pieces - book value, explicit residual income and terminal. Includes a news routing table.
A53: Note: No adjustment-factor cell exists for P/B. Every news item routes through the table on PB_Bridge rows 57-69 into an existing input cell.

Sheet Tracker
A1: (9) Micron Tracker — What to Watch Before Updating the View
A2: Written 2026-07-29. Margin calls are setting prices right now, so valuation judgment is suspended until the indicators below confirm a regime change.
A4: Stage 1 — Has Forced Liquidation Ended (check daily over the next one to three weeks)
A5: Indicator | B5: How to check | C5: Liquidation ongoing | D5: Signal that liquidation has ended | E5: Log
A6: Circuit breakers and sidecars | B6: KRX disclosures and news | C6: Triggered two days running (Jul 28-29) | D6: No trigger for three sessions or more
A7: Trading value | B7: KRX and Nasdaq daily | C7: Inflated by forced selling | D7: Back to normal levels
A8: Retail net selling | B8: KRX flows by investor type | C8: KRW 1.4tn net selling on Jul 29 | D8: Turns to net buying or neutral
A9: Leveraged ETF assets under management | B9: Single-stock 2x ETF balances | C9: Declining since the late-June peak | D9: Decline stops and flattens
A10: Micron intraday range | B10: ATR(14) at 79.67, or 9.5% of the share price | C10: Above 7% of the share price | D10: Narrows below 4% of the share price
A11: Implied correlation | B11: S&P 500 three-month implied correlation | C11: At multi-decade lows, with AI treated as a dispersion story | D11: A rise means AI has become an aggregate story - warning sign
A13: Stage 2 — Panic or Re-rating (scheduled events)
A14: Date | B14: Event | C14: What to check | D14: Bullish signal | E14: Bearish signal | F14: Log
A15: August 2026 | B15: Capacity calendar of the top three | C15: Timing for Samsung P4/P5, SK hynix M15X and Yongin phase one, and Micron Idaho | D15: Schedules slip or capacity is prioritized to HBM | E15: Start-up pulled forward (SK hynix M15X already confirmed earlier)
A16: Late September to early October 2026 | B16: Micron FY26 Q4 results | C16: (1) direction of ASP to cloud providers (2) FY27 capex guidance (3) progress on HBM contracts | D16: ASP keeps rising with capex discipline | E16: Missing consensus for the same reason as SK hynix would confirm the cycle has turned
A17: October 2026 | B17: SK hynix Q3 results | C17: Whether the Q2 ASP slowdown was one-off | D17: Slowdown reverses and the bonus effect is confirmed as gone | E17: A second consecutive quarter of ASP slowdown
A18: November to December 2026 | B18: HBM4 annual contract price negotiation | C18: HBM has no spot market, so this negotiation is the only price signal | D18: Close to the Goldman forecast of +44-50% | E18: Below the consensus of +34%
A19: 9 December 2026 | B19: Micron CHIPS restriction lifts | C19: (1) buyback size (2) duration (3) whether restrictions remain in years three to five | D19: A specific, large program is announced | E19: No announcement or a small one, repeating the SK hynix pattern
A20: Year-end to early next year | B20: LTA terms disclosed | C20: Level of prepayments, penalties and floor prices | D20: Strong terms would validate the Nomura discount rate argument | E20: Weak terms would kill the case for a lower cost of equity
A22: Stage 3 — Micron-Specific Factors (how it differs from the Korean names)
A23: The drawdown is shallower | B23: Micron is down about 34% from its peak versus KOSPI at -44% and Samsung at -50%. Falling less in the same cycle means more room below.
A24: It has just broken the 200-day line | B24: Broke below the 200-day EMA and the $803.95 support on Jul 29, with no meaningful support beneath. The 200-day simple moving average sits near $506.
A25: Not unrelated to the Korean leveraged ETFs | B25: Peter Kim of KB Securities: forced liquidation is running across Korea, the US, Hong Kong and the UK. A single-stock 2x Micron ETF exists in the US too.
A26: The HBM weighting is different | B26: Micron revenue splits 53% commodity DRAM, 23% HBM and 24% NAND. Direct CXMT competition sits in the 53%.
A27: It has its own catalysts | B27: The CHIPS restriction lifting on Dec 9 and FY26 Q4 results in late September - dates the Korean names do not have.
A28: Volatility is high | B28: ATR(14) of 79.67 equals 9.5% of the share price, with a beta of 2.20. Position size is the risk.
A30: Stage 4 — Update Rules (set in advance)
A31: 1. When the stage 1 indicators show liquidation has ended, resume the valuation discussion. Until then, do not argue about price.
A32: 2. If ASP to cloud providers keeps rising at the late-September results, raise the ConsensusValuation achievement rate to 85-100%.
A33: 3. If Micron also misses consensus for the same reason as SK hynix, cut the achievement rate to 50-60% and reallocate scenario probabilities.
A34: 4. If the Dec 9 buyback announcement is absent or small, treat the case for a lower cost of equity as dead and apply 18% or more rather than 15%.
A35: 5. Under no circumstances put the target multiple and the achievement rate on the optimistic side at the same time. One of the two must use the historical median.
A36: 6. Decide on adding to the position only after stage 1 confirms liquidation has ended. Adding before that is a directional bet, not a valuation judgment.
A38: Note: Record the date checked and the observed value in the yellow log column. When conviction wavers later, the reasoning can be retraced.
A39: Note: This file is not investment advice. It is a tool for organizing the basis of a judgment.
A41: Added 2026-07-30 — New Events and Data to Track
A42: Date | B42: Event | C42: Item to check | D42: Bullish signal | E42: Bearish signal | F42: Log
A43: 2026-08-21 | B43: [*] Apple deadline to reply to the Senate letter | C43: Whether Apple formally commits not to adopt CXMT or YMTC memory, plus disclosures on IP transfer, component qualification status, and any request to prioritize Korean and US suppliers | D43: An Apple commitment not to adopt would give commodity DRAM, 53% of Micron revenue, a political shield | E43: Apple avoiding a firm answer would confirm CXMT qualification is progressing, opening the door globally
A44: Quarterly | B44: Microsoft Azure growth rate | C44: FY26 Q4 at +43%, the highest since early 2022, with roughly +45% guided for the next quarter | D44: Holding above 45% means memory demand is firm | E44: Slowing below 40%
A45: Quarterly | B45: Microsoft underlying capex | C45: Accounting changes - useful life from 15 to 25 years and finance to operating leases - cut the headline from $190B to $175B while actual investment plans are unchanged | D45: Confirming FY2027 capex rises year over year | E45: The shift to operating leases makes this harder to track - reading only the headline leads to the wrong conclusion
A46: Q4 2026 onward | B46: [*] Meta 2027 capex guidance | C46: Not yet provided. Compute is maximized through 2026-27, while chip and server spend from 2028 will depend on actual demand and supply chains. | D46: 2027 guidance issued and raised | E46: Continued reticence on spending from 2028 would weaken the terminal assumptions
A47: Ongoing | B47: SK hynix 2026 capex | C47: Raised to at least $31B, up 50% year over year, covering the pulled-forward M15X, Yongin phase one, P&T7 and M17 | D47: No further increase, with discipline reaffirmed | E47: A further increase would add FY2028-29 supply and impair terminal ROE
A49: One irony: the Senate letter worries about an influx of cheap Chinese memory, yet CXMT currently sells above Samsung and SK hynix. The political framing lags commercial reality.
A50: Note: Many signatories represent New York, Indiana and Idaho - states hosting $250B of Micron investment and roughly $4B from SK hynix. Security logic is reinforced by local economic interest, which gives it staying power.

Sheet Assumptions
A1: Assumptions and Inputs
A3: Item | B3: Value | C3: Unit | D3: Source / Note
A4: Market Data
A5: Current share price | B5: 900 | C5: USD | D5: User-specified, 2026-07-31. Updated from $739 (the Jul 30 low).
A6: Shares outstanding | B6: 1130 | C6: millions of shares | D6: stockanalysis.com, 2026-07-28
A7: Current BVPS (TTM) | B7: 89.22 | C7: USD | D7: stockanalysis.com - equity $100.72B / 1.13B shares
A8: Net cash | B8: 23750 | C8: USD millions | D8: Cash $26.02B less total debt $6.38B
A9: Market capitalization | B9: =B5*B6 -> 1017000 | C9: USD millions | D9: Price x shares outstanding
A10: Current P/B | B10: =B5/B7 -> 10.087424 | C10: x | D10: Price / BVPS (note: actual range 10.09-10.32x)
A12: Cost of Equity
A13: Risk-free rate (Rf) | B13: 0.043 | C13: % | D13: Approximate US 10-year yield - verify and update directly
A14: Beta (5Y) | B14: 2.14 | C14: - | D14: Finviz, 2026-07-28
A15: Equity risk premium (ERP) | B15: 0.05 | C15: % | D15: Typically 4.5-5.5%
A16: Cost of equity (COE) | B16: =B13+B14*B15 -> 0.15 | C16: % | D16: Rf + beta x ERP (CAPM)
A18: Earnings Data
A19: TTM revenue | B19: 90274 | C19: USD millions | D19: stockanalysis.com, TTM(May '26)
A20: TTM net income | B20: 50469 | C20: USD millions | D20: stockanalysis.com, TTM(May '26)
A21: TTM EPS | B21: 44.17 | C21: USD | D21: stockanalysis.com
A22: TTM net margin | B22: =B20/B19 -> 0.55906463 | C22: % | D22: Net income / revenue - an all-time high
A23: TTM ROE | B23: =B20/(B7*B6) -> 0.50059215 | C23: % | D23: Net income / total equity
A24: Next-year EPS consensus | B24: 154.67 | C24: USD | D24: Finviz "EPS next Y", 45-analyst consensus - needs verification
A25: BVPS one year forward | B25: =B7+B24-0.6 -> 243.29 | C25: USD | D25: Current BVPS plus next-year EPS less the $0.60 dividend. Buyback effects ignored.
A26: FY2028 consensus BPS | B26: =Consensus!F24 -> 437.94 | C26: USD | D26: Analyst consensus median (12 estimates)
A27: [*] Model Levers — Edit Here
A28: Sustainable ROE | B28: 0.3 | C28: % | D28: [*] Assumed through-cycle average ROE. Actual five-year range: -12% to 19%.
A29: Perpetual growth rate (g) | B29: 0.05 | C29: % | D29: [*] Must stay below the cost of equity (see B16)
A30: Normalized revenue | B30: 65000 | C30: USD millions | D30: [*] Assumed mid-cycle revenue. FY25 $37.4B, TTM $90.3B.
A31: Normalized net margin | B31: 0.2 | C31: % | D31: [*] Mid-cycle margin. Five-year range: -37.6% to 28.2%.
A32: Normalized target P/E | B32: 12 | C32: x | D32: [*] Multiple applied to normalized earnings. Semiconductors typically 12-18x.
A33: BVPS basis (1 = current, 2 = one year forward, 3 = FY2028) | B33: 3 | C33: - | D33: [*] 1 = current $89, 2 = one year forward, 3 = FY2028 consensus $438
A34: Selected BVPS | B34: =IF(B33=3,B26,IF(B33=2,B25,B7)) -> 437.94 | C34: USD | D34: Set automatically by the choice above
A36: Warning: If COE is less than or equal to g, the justified P/B formula breaks down. Keep g comfortably below COE.
A37: Note: The default is 3 (FY2028 consensus). Comparing against 1 (current BVPS) shows immediately how much the reference date flips the conclusion.

Sheet CurrentData
A1: Current Results and Valuation (as of 2026-07-28)
A3: Item | B3: Value | C3: Unit | D3: Note
A4: Share Price and Market Cap
A5: Share price | B5: 739 | C5: USD | D5: 2026-07-30, -9.94%, volume 67.69m shares
A6: 52-week high | B6: 1255 | C6: USD | D6: Finviz
A7: 52-week low | B7: 103.38 | C7: USD | D7: Finviz
A8: vs 52-week high | B8: =B5/B6-1 -> -0.41115538 | C8: % | D8: Current drawdown - prior cycles ran -50% to -73%
A9: Market capitalization | B9: 946490 | C9: USD millions | D9: Finviz
A10: Valuation Multiples
A11: P/E (TTM) | B11: 18.97 | C11: x | D11: Finviz - beware the illusion of a low P/E at the cycle peak
A12: Forward P/E | B12: 5.42 | C12: x | D12: 838.05 / EPS next Y 154.67
A13: P/B | B13: 9.39 | C13: x | D13: Extreme versus the five-year band of 1.26-2.53x
A14: P/S | B14: 10.48 | C14: x | D14: Five-year band 2.04-4.94x
A15: EV/EBITDA | B15: 13.56 | C15: x | D15: Five-year band 3.62-40.3x
A16: PEG | B16: 0.03 | C16: x | D16: Finviz
A17: Profitability (TTM)
A18: Revenue | B18: 90274 | C18: USD millions | D18: +167% year over year
A19: Net income | B19: 50469 | C19: USD millions | D19: Net margin 55.9% - more than half of revenue drops to net income
A20: Gross margin | B20: 0.7257 | C20: % | D20: Up sharply from 39.8% in FY25
A21: Operating margin | B21: 0.6567 | C21: % | D21: FY25 26.1%
A22: Net margin | B22: 0.5591 | C22: % | D22: [*] All-time high. Prior peak was 28.2% in FY22.
A23: ROE | B23: 0.6664 | C23: % | D23: [*] Five-year average was 7.8%
A24: ROIC | B24: 0.4738 | C24: % | D24: Finviz
A25: Balance Sheet
A26: Debt to equity | B26: 0.06 | C26: x | D26: Effectively debt-free - financial risk is low
A27: Current ratio | B27: 3.42 | C27: x | D27: Current assets / current liabilities - short-term liquidity is very strong
A28: Net cash | B28: 23750 | C28: USD millions | D28: Cash $26.0B less debt $6.4B
A29: Free cash flow | B29: 26172 | C29: USD millions | D29: Operating cash flow $51.4B less capex $25.3B
A30: Consensus
A31: Analyst target price | B31: 1491.95 | C31: USD | D31: 45-analyst average, consensus rating Strong Buy
A32: Upside to target price | B32: =B31/B5-1 -> 1.0188769 | C32: % | D32: Warning: target prices lag the share price (see notes)
A33: Next-year EPS consensus | B33: 154.67 | C33: USD | D33: Finviz 'EPS next Y'
A35: Sources: Finviz (2026-07-28), stockanalysis.com / Fiscal.ai (2026-07-28)

Sheet HistoricalCycle
A1: Historical Cycle — Results and Valuation Trend
A3: Annual results (fiscal year Sep-Aug, USD millions)
A4: Item | B4: FY2021 | C4: FY2022 | D4: FY2023 | E4: FY2024 | F4: FY2025 | G4: TTM 2026 | H4: 5Y average (FY21-25)
A5: Revenue | B5: 27705 | C5: 30758 | D5: 15540 | E5: 25111 | F5: 37378 | G5: 90274 | H5: =AVERAGE(B5:F5) -> 27298.4
A6: Net income | B6: 5861 | C6: 8687 | D6: -5833 | E6: 778 | F6: 8539 | G6: 50469 | H6: =AVERAGE(B6:F6) -> 3606.4
A7: EPS | B7: 5.14 | C7: 7.75 | D7: -5.34 | E7: 0.7 | F7: 7.59 | G7: 44.17 | H7: =AVERAGE(B7:F7) -> 3.168
A8: Gross margin | B8: 0.3762 | C8: 0.4518 | D8: -0.0911 | E8: 0.2235 | F8: 0.3979 | G8: 0.7257 | H8: =AVERAGE(B8:F8) -> 0.27166
A9: Operating margin | B9: 0.2268 | C9: 0.3154 | D9: -0.3697 | E9: 0.0519 | F9: 0.2614 | G9: 0.6563 | H9: =AVERAGE(B9:F9) -> 0.09716
A10: Net margin | B10: 0.2102 | C10: 0.2823 | D10: -0.3755 | E10: 0.0314 | F10: 0.2282 | G10: 0.5589 | H10: =AVERAGE(B10:F10) -> 0.07532
A11: ROE | B11: 0.1405 | C11: 0.1851 | D11: -0.1241 | E11: 0.0177 | F11: 0.1718 | G11: 0.6326 | H11: =AVERAGE(B11:F11) -> 0.0782
A13: Valuation multiples (at each fiscal year end)
A14: Item | B14: FY2021 | C14: FY2022 | D14: FY2023 | E14: FY2024 | F14: FY2025 | G14: TTM 2026 | H14: 5Y average (FY21-25)
A15: Year-end share price | B15: 73.99 | C15: 57.31 | D15: 69.94 | E15: 95.57 | F15: 122 | G15: 838.05 | H15: =AVERAGE(B15:F15) -> 83.762
A16: P/B | B16: 1.88 | C16: 1.26 | D16: 1.74 | E16: 2.35 | F16: 2.53 | G16: 9.39 | H16: =AVERAGE(B16:F16) -> 1.952
A17: P/S | B17: 2.99 | C17: 2.04 | D17: 4.94 | E17: 4.22 | F17: 3.66 | G17: 10.48 | H17: =AVERAGE(B17:F17) -> 3.57
A18: P/E | B18: 14.39 | C18: 7.39 | D18: Loss | E18: 136.53 | F18: 16.07 | G18: 18.97 | H18: =AVERAGE(B18:F18) -> 43.595
A19: EV/EBITDA | B19: 6.52 | C19: 3.62 | D19: 40.34 | E19: 12.32 | F19: 7.83 | G19: 13.56 | H19: =AVERAGE(B19:F19) -> 14.126
A20: Note: The five-year average P/E excludes the loss-making FY2023 (AVERAGE skips text).
A21: P/B stayed within a 1.26-2.53x band across FY21-FY25. The current 9.39x is roughly four to seven times that band.
A22: The TTM net margin of 55.9% is double the prior peak of 28.2% in FY22. Whether that margin holds is the whole valuation question.
A24: Historical maximum drawdowns — reference
A25: Cycle | B25: Drawdown (approx.) | C25: Note
A26: 2000-2002 dot-com and DRAM collapse | B26: -0.9 | C26: Took over ten years to recover
A27: 2007-2008 financial crisis | B27: -0.98 | C27: Roughly thirteen years to recover (the worst on record)
A28: 2014~2016 | B28: -0.73 | C28: Pure cycle with no macro shock
A29: 2018 | B29: -0.57 | C29: Occurred at a trailing P/E of 3-4x, amid a rush of target price upgrades
A30: 2021~2022 | B30: -0.51 | C30: Immediately after a record revenue print
A31: 2024~2025 | B31: -0.6 | C31: Immediately after the sold-out HBM announcement
A32: 2026 to date (ongoing) | B32: -0.33 | C32: Occurred before spot prices had even started falling
A34: Drawdowns are approximate and based on closing prices; figures vary by data source. Sources: Trefis, stockanalysis.com price history.
A35: Results data sources: stockanalysis.com / Fiscal.ai (retrieved 2026-07-28), Micron 10-K

Sheet PB_ROE_Model
A1: (1) P/B x ROE Model — Justified P/B = (ROE - g) / (COE - g)
A3: Inputs (linked automatically from the Assumptions tab)
A4: Current share price | B4: =Assumptions!B5 -> 900
A5: Applied BVPS | B5: =Assumptions!B34 -> 437.94
A6: BVPS basis | B6: =IF(Assumptions!B33=3,"FY2028 consensus BPS",IF(Assumptions!B33=2,"BVPS one year forward","Current BVPS (TTM)")) -> FY2028 consensus BPS
A7: Cost of equity (COE) | B7: =Assumptions!B16 -> 0.15
A8: Assumed sustainable ROE | B8: =Assumptions!B28 -> 0.3
A9: Perpetual growth rate g | B9: =Assumptions!B29 -> 0.05
A11: Base case result
A12: Justified P/B | B12: =IF(B7<=B9,"Error: g >= COE",(B8-B9)/(B7-B9)) -> 2.5
A13: Implied share price | B13: =IF(B7<=B9,"n/a",B12*B5) -> 1094.85
A14: vs current price | B14: =IF(B7<=B9,"n/a",B13/B4-1) -> 0.2165
A16: Sensitivity — implied price (rows: sustainable ROE / columns: perpetual growth g)
A17: ROE \ g | B17: 0.03 | C17: 0.04 | D17: 0.05 | E17: 0.06 | F17: 0.07 | G17: 0.08
A18: 0.1 | B18: =IF($B$7<=B$17,"n/a",($A18-B$17)/($B$7-B$17)*$B$5) -> 255.465 | C18: =IF($B$7<=C$17,"n/a",($A18-C$17)/($B$7-C$17)*$B$5) -> 238.87636 | D18: =IF($B$7<=D$17,"n/a",($A18-D$17)/($B$7-D$17)*$B$5) -> 218.97 | E18: =IF($B$7<=E$17,"n/a",($A18-E$17)/($B$7-E$17)*$B$5) -> 194.64 | F18: =IF($B$7<=F$17,"n/a",($A18-F$17)/($B$7-F$17)*$B$5) -> 164.2275 | G18: =IF($B$7<=G$17,"n/a",($A18-G$17)/($B$7-G$17)*$B$5) -> 125.12571
A19: 0.15 | B19: =IF($B$7<=B$17,"n/a",($A19-B$17)/($B$7-B$17)*$B$5) -> 437.94 | C19: =IF($B$7<=C$17,"n/a",($A19-C$17)/($B$7-C$17)*$B$5) -> 437.94 | D19: =IF($B$7<=D$17,"n/a",($A19-D$17)/($B$7-D$17)*$B$5) -> 437.94 | E19: =IF($B$7<=E$17,"n/a",($A19-E$17)/($B$7-E$17)*$B$5) -> 437.94 | F19: =IF($B$7<=F$17,"n/a",($A19-F$17)/($B$7-F$17)*$B$5) -> 437.94 | G19: =IF($B$7<=G$17,"n/a",($A19-G$17)/($B$7-G$17)*$B$5) -> 437.94
A20: 0.2 | B20: =IF($B$7<=B$17,"n/a",($A20-B$17)/($B$7-B$17)*$B$5) -> 620.415 | C20: =IF($B$7<=C$17,"n/a",($A20-C$17)/($B$7-C$17)*$B$5) -> 637.00364 | D20: =IF($B$7<=D$17,"n/a",($A20-D$17)/($B$7-D$17)*$B$5) -> 656.91 | E20: =IF($B$7<=E$17,"n/a",($A20-E$17)/($B$7-E$17)*$B$5) -> 681.24 | F20: =IF($B$7<=F$17,"n/a",($A20-F$17)/($B$7-F$17)*$B$5) -> 711.6525 | G20: =IF($B$7<=G$17,"n/a",($A20-G$17)/($B$7-G$17)*$B$5) -> 750.75429
A21: 0.25 | B21: =IF($B$7<=B$17,"n/a",($A21-B$17)/($B$7-B$17)*$B$5) -> 802.89 | C21: =IF($B$7<=C$17,"n/a",($A21-C$17)/($B$7-C$17)*$B$5) -> 836.06727 | D21: =IF($B$7<=D$17,"n/a",($A21-D$17)/($B$7-D$17)*$B$5) -> 875.88 | E21: =IF($B$7<=E$17,"n/a",($A21-E$17)/($B$7-E$17)*$B$5) -> 924.54 | F21: =IF($B$7<=F$17,"n/a",($A21-F$17)/($B$7-F$17)*$B$5) -> 985.365 | G21: =IF($B$7<=G$17,"n/a",($A21-G$17)/($B$7-G$17)*$B$5) -> 1063.5686
A22: 0.3 | B22: =IF($B$7<=B$17,"n/a",($A22-B$17)/($B$7-B$17)*$B$5) -> 985.365 | C22: =IF($B$7<=C$17,"n/a",($A22-C$17)/($B$7-C$17)*$B$5) -> 1035.1309 | D22: =IF($B$7<=D$17,"n/a",($A22-D$17)/($B$7-D$17)*$B$5) -> 1094.85 | E22: =IF($B$7<=E$17,"n/a",($A22-E$17)/($B$7-E$17)*$B$5) -> 1167.84 | F22: =IF($B$7<=F$17,"n/a",($A22-F$17)/($B$7-F$17)*$B$5) -> 1259.0775 | G22: =IF($B$7<=G$17,"n/a",($A22-G$17)/($B$7-G$17)*$B$5) -> 1376.3829
A23: 0.4 | B23: =IF($B$7<=B$17,"n/a",($A23-B$17)/($B$7-B$17)*$B$5) -> 1350.315 | C23: =IF($B$7<=C$17,"n/a",($A23-C$17)/($B$7-C$17)*$B$5) -> 1433.2582 | D23: =IF($B$7<=D$17,"n/a",($A23-D$17)/($B$7-D$17)*$B$5) -> 1532.79 | E23: =IF($B$7<=E$17,"n/a",($A23-E$17)/($B$7-E$17)*$B$5) -> 1654.44 | F23: =IF($B$7<=F$17,"n/a",($A23-F$17)/($B$7-F$17)*$B$5) -> 1806.5025 | G23: =IF($B$7<=G$17,"n/a",($A23-G$17)/($B$7-G$17)*$B$5) -> 2002.0114
A24: 0.5 | B24: =IF($B$7<=B$17,"n/a",($A24-B$17)/($B$7-B$17)*$B$5) -> 1715.265 | C24: =IF($B$7<=C$17,"n/a",($A24-C$17)/($B$7-C$17)*$B$5) -> 1831.3855 | D24: =IF($B$7<=D$17,"n/a",($A24-D$17)/($B$7-D$17)*$B$5) -> 1970.73 | E24: =IF($B$7<=E$17,"n/a",($A24-E$17)/($B$7-E$17)*$B$5) -> 2141.04 | F24: =IF($B$7<=F$17,"n/a",($A24-F$17)/($B$7-F$17)*$B$5) -> 2353.9275 | G24: =IF($B$7<=G$17,"n/a",($A24-G$17)/($B$7-G$17)*$B$5) -> 2627.64
A25: 0.6 | B25: =IF($B$7<=B$17,"n/a",($A25-B$17)/($B$7-B$17)*$B$5) -> 2080.215 | C25: =IF($B$7<=C$17,"n/a",($A25-C$17)/($B$7-C$17)*$B$5) -> 2229.5127 | D25: =IF($B$7<=D$17,"n/a",($A25-D$17)/($B$7-D$17)*$B$5) -> 2408.67 | E25: =IF($B$7<=E$17,"n/a",($A25-E$17)/($B$7-E$17)*$B$5) -> 2627.64 | F25: =IF($B$7<=F$17,"n/a",($A25-F$17)/($B$7-F$17)*$B$5) -> 2901.3525 | G25: =IF($B$7<=G$17,"n/a",($A25-G$17)/($B$7-G$17)*$B$5) -> 3253.2686
A26: 0.7 | B26: =IF($B$7<=B$17,"n/a",($A26-B$17)/($B$7-B$17)*$B$5) -> 2445.165 | C26: =IF($B$7<=C$17,"n/a",($A26-C$17)/($B$7-C$17)*$B$5) -> 2627.64 | D26: =IF($B$7<=D$17,"n/a",($A26-D$17)/($B$7-D$17)*$B$5) -> 2846.61 | E26: =IF($B$7<=E$17,"n/a",($A26-E$17)/($B$7-E$17)*$B$5) -> 3114.24 | F26: =IF($B$7<=F$17,"n/a",($A26-F$17)/($B$7-F$17)*$B$5) -> 3448.7775 | G26: =IF($B$7<=G$17,"n/a",($A26-G$17)/($B$7-G$17)*$B$5) -> 3878.8971
A28: Find the cell closest to the current price - that ROE is what the market is assuming.
A30: Back-solve — the sustainable ROE implied by the current price
A31: Formula: ROE = (price / BVPS) x (COE - g) + g
A32: Perpetual growth rate g | B32: Implied ROE | C32: Interpretation
A33: 0.03 | B33: =IF($B$7<=A33,"n/a",($B$4/$B$5)*($B$7-A33)+A33) -> 0.27660912 | C33: Conservative growth assumption
A34: 0.04 | B34: =IF($B$7<=A34,"n/a",($B$4/$B$5)*($B$7-A34)+A34) -> 0.26605836 | C34: Conservative to neutral
A35: 0.05 | B35: =IF($B$7<=A35,"n/a",($B$4/$B$5)*($B$7-A35)+A35) -> 0.2555076 | C35: In line with market growth
A36: 0.06 | B36: =IF($B$7<=A36,"n/a",($B$4/$B$5)*($B$7-A36)+A36) -> 0.24495684 | C36: Neutral to aggressive
A37: 0.07 | B37: =IF($B$7<=A37,"n/a",($B$4/$B$5)*($B$7-A37)+A37) -> 0.23440608 | C37: Aggressive growth assumption
A38: 0.08 | B38: =IF($B$7<=A38,"n/a",($B$4/$B$5)*($B$7-A38)+A38) -> 0.22385532 | C38: Very aggressive assumption
A40: Note: Micron actual ROE over the past five years ranged from -12.4% to 18.5%, averaging 7.8% (see HistoricalCycle).
A41: Note: Using current BVPS is harsh while equity is compounding fast. Set Assumptions B33 to 2 to view the one-year-forward BVPS basis alongside.
A42: Note: Toggle Assumptions B33 between 1 and 3. On the same ROE assumption, the implied price shifts by nearly fivefold depending on the BPS basis.
A43: Note: Consensus FY2028 ROE median is 44.9% with a low of 24.3%; FY2029 median is 29.6% (Consensus rows 27-29).

Sheet NormalizedEarnings
A1: (2) Normalized Earnings Model — Fair Value on Mid-Cycle Margins
A3: Why This Method Is Needed
A4: The current 55.9% net margin is an all-time high and double the prior peak of 28.2% in FY22. Applying a multiple to EPS built on
A5: that margin capitalizes peak-cycle earnings in perpetuity. Normalizing corrects for this.
A7: Calculation (inputs linked from the Assumptions tab)
A8: Normalized revenue (USD millions) | B8: =Assumptions!B30 -> 65000 | C8: [*] Edit on Assumptions B30
A9: Normalized net margin | B9: =Assumptions!B31 -> 0.2 | C9: [*] Edit on Assumptions B31
A10: Normalized net income | B10: =B8*B9 -> 13000 | C10: Revenue x margin
A11: Shares outstanding (millions) | B11: =Assumptions!B6 -> 1130
A12: Normalized EPS | B12: =B10/B11 -> 11.504425 | C12: Net income / shares outstanding
A13: Normalized target P/E | B13: =Assumptions!B32 -> 12 | C13: [*] Edit on Assumptions B32
A14: Business value per share | B14: =B12*B13 -> 138.0531 | C14: Normalized EPS x target multiple
A15: Plus net cash per share | B15: =Assumptions!B8/Assumptions!B6 -> 21.017699 | C15: Net cash $23.75B across 1.13B shares (value of the debt-free position)
A16: Implied share price (total) | B16: =B14+B15 -> 159.0708 | C16: Business value plus net cash
A17: Current share price | B17: =Assumptions!B5 -> 900 | C17: Finviz 2026-07-28
A18: vs current price | B18: =B16/B17-1 -> -0.82325467
A20: Reference: historical range (basis for the normalization assumptions)
A21: Item | B21: FY2021 | C21: FY2022 | D21: FY2023 | E21: FY2024 | F21: FY2025 | G21: TTM 2026 | H21: FY21-25 average
A22: Revenue (USD millions) | B22: =HistoricalCycle!B5 -> 27705 | C22: =HistoricalCycle!C5 -> 30758 | D22: =HistoricalCycle!D5 -> 15540 | E22: =HistoricalCycle!E5 -> 25111 | F22: =HistoricalCycle!F5 -> 37378 | G22: =HistoricalCycle!G5 -> 90274 | H22: =HistoricalCycle!H5 -> 27298.4
A23: Net margin | B23: =HistoricalCycle!B10 -> 0.2102 | C23: =HistoricalCycle!C10 -> 0.2823 | D23: =HistoricalCycle!D10 -> -0.3755 | E23: =HistoricalCycle!E10 -> 0.0314 | F23: =HistoricalCycle!F10 -> 0.2282 | G23: =HistoricalCycle!G10 -> 0.5589 | H23: =HistoricalCycle!H10 -> 0.07532
A24: Note: The FY21-25 average net margin is about 7.5%, including the large FY23 loss. Excluding loss years it is roughly 18.8%.
A26: Sensitivity — implied price (rows: normalized net margin / columns: target P/E, net cash per share included)
A27: Net margin \ P/E | B27: 8 | C27: 10 | D27: 12 | E27: 15 | F27: 18 | G27: 20 | H27: 25
A28: 0.05 | B28: =$B$8*$A28/$B$11*B$27+$B$15 -> 44.026549 | C28: =$B$8*$A28/$B$11*C$27+$B$15 -> 49.778761 | D28: =$B$8*$A28/$B$11*D$27+$B$15 -> 55.530973 | E28: =$B$8*$A28/$B$11*E$27+$B$15 -> 64.159292 | F28: =$B$8*$A28/$B$11*F$27+$B$15 -> 72.787611 | G28: =$B$8*$A28/$B$11*G$27+$B$15 -> 78.539823 | H28: =$B$8*$A28/$B$11*H$27+$B$15 -> 92.920354
A29: 0.1 | B29: =$B$8*$A29/$B$11*B$27+$B$15 -> 67.035398 | C29: =$B$8*$A29/$B$11*C$27+$B$15 -> 78.539823 | D29: =$B$8*$A29/$B$11*D$27+$B$15 -> 90.044248 | E29: =$B$8*$A29/$B$11*E$27+$B$15 -> 107.30088 | F29: =$B$8*$A29/$B$11*F$27+$B$15 -> 124.55752 | G29: =$B$8*$A29/$B$11*G$27+$B$15 -> 136.06195 | H29: =$B$8*$A29/$B$11*H$27+$B$15 -> 164.82301
A30: 0.15 | B30: =$B$8*$A30/$B$11*B$27+$B$15 -> 90.044248 | C30: =$B$8*$A30/$B$11*C$27+$B$15 -> 107.30088 | D30: =$B$8*$A30/$B$11*D$27+$B$15 -> 124.55752 | E30: =$B$8*$A30/$B$11*E$27+$B$15 -> 150.44248 | F30: =$B$8*$A30/$B$11*F$27+$B$15 -> 176.32743 | G30: =$B$8*$A30/$B$11*G$27+$B$15 -> 193.58407 | H30: =$B$8*$A30/$B$11*H$27+$B$15 -> 236.72566
A31: 0.2 | B31: =$B$8*$A31/$B$11*B$27+$B$15 -> 113.0531 | C31: =$B$8*$A31/$B$11*C$27+$B$15 -> 136.06195 | D31: =$B$8*$A31/$B$11*D$27+$B$15 -> 159.0708 | E31: =$B$8*$A31/$B$11*E$27+$B$15 -> 193.58407 | F31: =$B$8*$A31/$B$11*F$27+$B$15 -> 228.09735 | G31: =$B$8*$A31/$B$11*G$27+$B$15 -> 251.10619 | H31: =$B$8*$A31/$B$11*H$27+$B$15 -> 308.62832
A32: 0.25 | B32: =$B$8*$A32/$B$11*B$27+$B$15 -> 136.06195 | C32: =$B$8*$A32/$B$11*C$27+$B$15 -> 164.82301 | D32: =$B$8*$A32/$B$11*D$27+$B$15 -> 193.58407 | E32: =$B$8*$A32/$B$11*E$27+$B$15 -> 236.72566 | F32: =$B$8*$A32/$B$11*F$27+$B$15 -> 279.86726 | G32: =$B$8*$A32/$B$11*G$27+$B$15 -> 308.62832 | H32: =$B$8*$A32/$B$11*H$27+$B$15 -> 380.53097
A33: 0.3 | B33: =$B$8*$A33/$B$11*B$27+$B$15 -> 159.0708 | C33: =$B$8*$A33/$B$11*C$27+$B$15 -> 193.58407 | D33: =$B$8*$A33/$B$11*D$27+$B$15 -> 228.09735 | E33: =$B$8*$A33/$B$11*E$27+$B$15 -> 279.86726 | F33: =$B$8*$A33/$B$11*F$27+$B$15 -> 331.63717 | G33: =$B$8*$A33/$B$11*G$27+$B$15 -> 366.15044 | H33: =$B$8*$A33/$B$11*H$27+$B$15 -> 452.43363
A34: 0.4 | B34: =$B$8*$A34/$B$11*B$27+$B$15 -> 205.0885 | C34: =$B$8*$A34/$B$11*C$27+$B$15 -> 251.10619 | D34: =$B$8*$A34/$B$11*D$27+$B$15 -> 297.12389 | E34: =$B$8*$A34/$B$11*E$27+$B$15 -> 366.15044 | F34: =$B$8*$A34/$B$11*F$27+$B$15 -> 435.17699 | G34: =$B$8*$A34/$B$11*G$27+$B$15 -> 481.19469 | H34: =$B$8*$A34/$B$11*H$27+$B$15 -> 596.23894
A35: 0.5 | B35: =$B$8*$A35/$B$11*B$27+$B$15 -> 251.10619 | C35: =$B$8*$A35/$B$11*C$27+$B$15 -> 308.62832 | D35: =$B$8*$A35/$B$11*D$27+$B$15 -> 366.15044 | E35: =$B$8*$A35/$B$11*E$27+$B$15 -> 452.43363 | F35: =$B$8*$A35/$B$11*F$27+$B$15 -> 538.71681 | G35: =$B$8*$A35/$B$11*G$27+$B$15 -> 596.23894 | H35: =$B$8*$A35/$B$11*H$27+$B$15 -> 740.04425
A37: Note: The grid above holds normalized revenue (Assumptions B30) fixed. Changing the revenue assumption shifts the entire table.
A38: Note: This method tends to produce very low values. Understand the two reasons before using it:
A39: (1) It ignores the cash the company earns on the way to normalization - the Scenarios tab corrects for this.
A40: (2) If HBM has structurally raised margins, the normalized margin itself should be set above the historical level.

Sheet Scenarios
A1: (3) Probability-Weighted Scenario Value (valued two to three years forward)
A3: Scenario definitions — edit the blue cells freely (values below are illustrative defaults)
A4: Scenarios | B4: Core logic | C4: Normalized revenue ($m) | D4: Net margin | E4: EPS | F4: Target P/E | G4: Business value | H4: Cumulative FCF (per share) | I4: Implied price | J4: Probability
A5: Bull | B5: Spot +15%, HBM contract price +35% — repricing succeeds | C5: =F54 -> 339435.2 | D5: =J54 -> 0.64049288 | E5: =C5*D5/Assumptions!$B$6 -> 192.39454 | F5: 10 | G5: =E5*F5 -> 1923.9454 | H5: 250 | I5: =G5+H5 -> 2173.9454 | J5: 0.25
A6: Base | B6: TrendForce and consensus baseline (spot and contract both at 100%) | C6: =F55 -> 285117 | D6: =J55 -> 0.5996267 | E6: =C6*D6/Assumptions!$B$6 -> 151.29537 | F6: 9 | G6: =E6*F6 -> 1361.6583 | H6: 180 | I6: =G6+H6 -> 1541.6583 | J6: 0.5
A7: Bear | B7: Spot -65%, HBM contract price -40% — the 2026 surge unwinds | C7: =F56 -> 136325.83 | D7: =J56 -> 0.32090264 | E7: =C7*D7/Assumptions!$B$6 -> 38.714442 | F7: 8 | G7: =E7*F7 -> 309.71553 | H7: 90 | I7: =G7+H7 -> 399.71553 | J7: 0.25
A8: Probability total | J8: =SUM(J5:J7) -> 1
A9: =IF(ABS(J8-1)>0.001,"Warning: probabilities do not sum to 100% - adjust J5:J7","OK - probabilities sum to 100%") -> OK - probabilities sum to 100%
A10: Note: Cumulative FCF per share is the free cash the company accumulates before the valuation date. Cyclicals earn substantial cash on the way to normalization, so it must be added. Current FCF runs about $23 per share per year.
A12: Results
A13: Probability-weighted expected price | B13: =SUMPRODUCT(I5:I7,J5:J7)/J8 -> 1414.2444 | C13: Sum of each scenario price times its probability
A14: Current share price | B14: =Assumptions!B5 -> 900 | C14: Finviz 2026-07-28
A15: Expected return | B15: =B13/B14-1 -> 0.57138266 | C15: Expected price / current price - 1
A16: Upside in the bull case | B16: =I5/B14-1 -> 1.4154949
A17: Downside in the bear case | B17: =I7/B14-1 -> -0.55587163
A18: Payoff asymmetry | B18: =IFERROR(ABS(I5/B14-1)/ABS(I7/B14-1),"n/a") -> 2.546442 | C18: Above 1 means upside exceeds downside
A19: Probability implied by the current price (on the bull case) | B19: =IFERROR((B14-I7)/(I5-I7),"n/a") -> 0.28197275 | C19: The current price requires assigning roughly this probability to the bull case (a two-state bull/bear approximation)
A21: The Variables That Actually Decide the Scenario
A22: 1. Capacity calendar of the top three | B22: Timing of Samsung P4/P5 and SK hynix M15X coming online - the point where supply growth overtakes demand growth of roughly 36%
A23: 2. HBM4 annual contract price | B23: The negotiation outcome around year-end. HBM has no spot market, so this is the only price signal.
A24: 3. Customer inventory days | B24: When hyperscalers stop pre-buying. This leads the capex headlines.
A26: Note: The revenue, margin, multiple, cumulative FCF and probability figures above are illustrative defaults. Replace them with your own judgment.
A27: Note: This file is not investment advice. It is a template for learning valuation methodology.
A28: Note: Defaults were rescaled to the consensus level (bull = FY2028 consensus median, base = consensus low, bear = oversupply).
A29: Note: Cumulative FCF approximates three years of per-share cash flow across FY2026-2028 (consensus CFPS of $74, $160 and $201, less capex).
A32: (16) Derivation Block — Spot DRAM Price Drives the Scenarios (rewritten 2026-07-31)
A33: The driver is the commodity DRAM spot ASP. HBM is contracted and moves separately and more slowly. The ASP premium, revenue, mix and margins are all derived here rather than entered by hand.
A35: Baseline (TrendForce and consensus = 100%)
A36: FY2028 HBM bit share | B36: =MixPath!D19 -> 0.15217391 | C36: Physical layer, independent of price
A37: FY2028 DRAM revenue share | B37: =MixPath!D8 -> 0.8
A38: Base ASP premium (FY2026 actual) | B38: =MixPath!B15 -> 4.39 | C38: 4.39x, back-solved from Micron actuals
A39: Base commodity DRAM OPM | B39: =SegmentMargin!D6 -> 0.77777778 | C39: ⑬ FY2028
A40: Base HBM OPM | B40: =SegmentMargin!D7 -> 0.75 | C40: ⑬ FY2028
A41: Base NAND OPM | B41: =SegmentMargin!D8 -> 0.44444444 | C41: ⑬ FY2028
A42: Consensus FY2028 revenue ($m) | B42: =Consensus!F6 -> 285117 | C42: Embeds the TrendForce spot price assumption
A43: Effective tax rate | B43: =ROE_Build!B5 -> 0.145
A44: Shares outstanding (millions) | B44: =Assumptions!B6 -> 1130
A46: [*] Scenario definitions — adjust only the price indices
A47: Basis | B47: [*] Commodity spot ASP index | C47: [*] HBM contract ASP index | D47: [*] NAND ASP index | E47: Character
A48: Bull | B48: 1.15 | C48: 1.35 | D48: 1 | E48: Spot holds firm and HBM4 contract repricing succeeds (Goldman +44-50%)
A49: Base | B49: 1 | C49: 1 | D49: 1 | E49: TrendForce and consensus baseline, unchanged
A50: Bear | B50: 0.35 | C50: 0.6 | D50: 0.55 | E50: Spot -65% (unwinding the 2026 surge) with HBM contract prices renegotiated -40%
A52: Derived Results
A53: Basis | B53: Derived premium | C53: HBM revenue share | D53: Commodity revenue share | E53: Revenue index | F53: Revenue ($m) | G53: Commodity OPM | H53: HBM OPM | I53: Blended EBIT | J53: Net margin
A54: =A48 -> Bull | B54: =$B$38*$C$48/$B$48 -> 5.1534783 | C54: =(($B$36*$B$38*$C$48)/($B$36*$B$38+(1-$B$36))*$B$37)/E54 -> 0.39979088 | D54: =(((1-$B$36)*$B$48)/($B$36*$B$38+(1-$B$36))*$B$37)/E54 -> 0.43221417 | E54: =((($B$36*$B$38*$C$48)+((1-$B$36)*$B$48))/($B$36*$B$38+(1-$B$36))*$B$37)+((1-$B$37)*$D$48) -> 1.190512 | F54: =$B$42*E54 -> 339435.2 | G54: =1-(1-$B$39)/$B$48 -> 0.80676329 | H54: =1-(1-$B$40)/$C$48 -> 0.81481481 | I54: =D54*G54+C54*H54+(1-C54-D54)*(1-(1-$B$41)/$D$48) -> 0.74911448 | J54: =I54*(1-$B$43) -> 0.64049288
A55: =A49 -> Base | B55: =$B$38*$C$49/$B$49 -> 4.39 | C55: =(($B$36*$B$38*$C$49)/($B$36*$B$38+(1-$B$36))*$B$37)/E55 -> 0.35255987 | D55: =(((1-$B$36)*$B$49)/($B$36*$B$38+(1-$B$36))*$B$37)/E55 -> 0.44744013 | E55: =((($B$36*$B$38*$C$49)+((1-$B$36)*$B$49))/($B$36*$B$38+(1-$B$36))*$B$37)+((1-$B$37)*$D$49) -> 1 | F55: =$B$42*E55 -> 285117 | G55: =1-(1-$B$39)/$B$49 -> 0.77777778 | H55: =1-(1-$B$40)/$C$49 -> 0.75 | I55: =D55*G55+C55*H55+(1-C55-D55)*(1-(1-$B$41)/$D$49) -> 0.70131778 | J55: =I55*(1-$B$43) -> 0.5996267
A56: =A50 -> Bear | B56: =$B$38*$C$50/$B$50 -> 7.5257143 | C56: =(($B$36*$B$38*$C$50)/($B$36*$B$38+(1-$B$36))*$B$37)/E56 -> 0.44241423 | D56: =(((1-$B$36)*$B$50)/($B$36*$B$38+(1-$B$36))*$B$37)/E56 -> 0.32752762 | E56: =((($B$36*$B$38*$C$50)+((1-$B$36)*$B$50))/($B$36*$B$38+(1-$B$36))*$B$37)+((1-$B$37)*$D$50) -> 0.47813997 | F56: =$B$42*E56 -> 136325.83 | G56: =1-(1-$B$39)/$B$50 -> 0.36507937 | H56: =1-(1-$B$40)/$C$50 -> 0.58333333 | I56: =D56*G56+C56*H56+(1-C56-D56)*(1-(1-$B$41)/$D$50) -> 0.37532472 | J56: =I56*(1-$B$43) -> 0.32090264
A58: Note: OPM = 1 - (1 - base OPM) / ASP index. Under a fixed-cost structure unit cost is unchanged, so the ASP decline cuts straight into margin.
A59: Note: From a base OPM of 78%, spot must fall 65% to bring OPM down to 37%. A decline of 80% flips the segment into a loss, on the scale of FY2023.
A60: Note: [*] The derived premium in column B is an output. When spot falls, the contracted HBM price becomes relatively expensive, the premium rises, and the HBM revenue share expands automatically.
A61: Note: This is the mechanical substance of contracts providing downside support - in a downturn the HBM share grows and cushions the fall in blended margin.
A62: Note: The TrendForce DRAM revenue forecast of $903B for 2027 is a central estimate, not a ceiling. A spot index of 1.0 marks that baseline; the downside runs below it.
A63: Note: Target P/E, cumulative FCF and probability remain manual because they are judgment. To change a scenario, adjust only the price indices in rows 48-50.

Sheet Consensus
A1: Analyst Consensus Estimates (FY2025 actual to FY2029E)
A2: Fiscal year runs Sep-Aug. Units in USD millions (per-share figures in USD). Source: consensus screen supplied by the user, retrieved 2026-07-28.
A4: Income Statement — Median Estimates
A5: Item | B5: Basis | C5: FY2025(A) | D5: FY2026(E) | E5: FY2027(E) | F5: FY2028(E) | G5: FY2029(E) | H5: Note
A6: Revenue | B6: Median | C6: 37378 | D6: 129459 | E6: 246699 | F6: 285117 | G6: 289549 | H6: Surges through FY27, then flattens in FY28-29
B7: Estimate count | D7: 45 | E7: 46 | F7: 31 | G7: 5 | H7: Only five estimates for FY29 - low confidence
A8: Gross profit | B8: Median | C8: 15288 | D8: 103973 | E8: 215170 | F8: 230379 | G8: 180733
A9: Gross margin | B9: % | C9: 0.409 | D9: 0.805 | E9: 0.8607 | F9: 0.803 | G9: 0.672 | H9: An 86% gross margin in FY27 would be unprecedented in semiconductors
A10: EBIT | B10: Median | C10: 10846 | D10: 98022 | E10: 205831 | F10: 223740 | G10: 188829
A11: EBIT margin | B11: % | C11: 0.2902 | D11: 0.7589 | E11: 0.8233 | F11: 0.7799 | G11: 0.7021
A12: EBITDA | B12: Median | C12: 19198 | D12: 107951 | E12: 222099 | F12: 246363 | G12: 213073
A13: EBITDA margin | B13: % | C13: 0.5136 | D13: 0.8358 | E13: 0.8884 | F13: 0.8587 | G13: 0.7922
A14: Pretax income | B14: Median | C14: 10785 | D14: 98737 | E14: 208426 | F14: 219435 | G14: 220433
A15: Net income | B15: Median | C15: 9470 | D15: 84014 | E15: 176699 | F15: 189388 | G15: 160492
A16: Net margin | B16: % | C16: 0.2534 | D16: 0.6505 | E16: 0.7068 | F16: 0.6601 | G16: 0.5967 | H16: [*] A 70.7% net margin in FY27 is an extreme assumption
B17: Estimate count | D17: 39 | E17: 39 | F17: 26 | G17: 3
A18: EPS (adjusted) | B18: Median | C18: 8.29 | D18: 73.13 | E18: 154.66 | F18: 170.38 | G18: 141.59 | H18: [*] The core valuation input
B19: Estimate count | D19: 47 | E19: 47 | F19: 31 | G19: 4
A20: GAAP EPS | B20: Median | C20: 7.59 | D20: 72.27 | E20: 153.65 | F20: 176.84 | G20: 101.54
A22: Per-Share and Balance Sheet — Median Estimates
A23: Item | B23: Basis | C23: FY2025(A) | D23: FY2026(E) | E23: FY2027(E) | F23: FY2028(E) | G23: FY2029(E) | H23: Note
A24: BPS (book value per share) | B24: Median | C24: 48.4 | D24: 118.72 | E24: 259.02 | F24: 437.94 | G24: 643.7 | H24: [*] The denominator in every P/B calculation
B25: Estimate count | C25: - | D25: 16 | E25: 16 | F25: 12 | G25: 2 | H25: FY28 has 12 estimates
A26: NAVPS (net asset value per share) | B26: Median | C26: 48.4 | D26: 122.16 | E26: 291.95 | F26: 442.77 | G26: - | H26: Only one estimate - reference only
A27: ROE | B27: Median | C27: 0.1907 | D27: 0.844 | E27: 0.7384 | F27: 0.4486 | G27: 0.296 | H27: [*] Consensus itself already assumes normalization
A28: ROE low | B28: % | C28: - | D28: 0.424 | E28: 0.366 | F28: 0.243 | G28: 0.148 | H28: Approximates the bear case
A29: ROE high | B29: % | C29: - | D29: 0.9098 | E29: 1.1097 | F29: 0.8632 | G29: 0.701
A30: ROA | B30: Median | C30: 0.1244 | D30: 0.6521 | E30: 0.6883 | F30: 0.4467 | G30: 0.3865
A31: Net debt | B31: Median | C31: 4270 | D31: -40902 | E31: -143648 | F31: -265525 | G31: -318921 | H31: Negative means net cash. FY28 net cash of $266B.
A32: CAPEX | B32: Median | C32: 15857 | D32: 27701 | E32: 47089 | F32: 48000 | G32: 55461 | H32: Large capacity additions from FY27 - the seed of the next oversupply
A33: Cash flow per share (CFPS) | B33: Median | C33: 15.33 | D33: 74.49 | E33: 160.05 | F33: 201.29 | G33: 208.67
A35: Estimate Dispersion — How Much Confidence Does Consensus Deserve
A36: Item | B36: FY2026(E) | C36: FY2027(E) | D36: FY2028(E) | E36: FY2029(E) | F36: Note
A37: Revenue low | B37: 113900 | C37: 203043 | D37: 208018 | E37: 214242
A38: Revenue median | B38: 129459 | C38: 246699 | D38: 285117 | E38: 289549
A39: Revenue high | B39: 138764 | C39: 342515 | D39: 405709 | E39: 303053
A40: EPS low | B40: 60.9 | C40: 119.4 | D40: 136 | E40: 101.94
A41: EPS median | B41: 73.13 | C41: 154.66 | D41: 170.38 | E41: 141.59
A42: EPS high | B42: 80.16 | C42: 221.27 | D42: 254.85 | E42: 185.86
A43: BPS low | B43: 99.71 | C43: 197.12 | D43: 311.26 | E43: 643.7
A44: BPS median | B44: 118.72 | C44: 259.02 | D44: 437.94 | E44: 643.7
A45: BPS high | B45: 125.55 | C45: 295.34 | D45: 496.34 | E45: 643.7
A46: ="FY2028 revenue estimate range: high exceeds low by "&TEXT(D39/D37-1,"0%")&"; for EPS the spread is "&TEXT(D42/D40-1,"0%")&". This is why the consensus median alone should not be trusted." -> FY2028 revenue estimate range: high exceeds low by 95%; for EPS the spread is 87%. This is why the consensus median alone should not be trusted.
A47: Note: Estimate counts collapse from 45-47 for FY2026 to 26-31 for FY2028 and just 2-5 for FY2029. The further out you go, the more a handful of views drive the median.

Sheet ConsensusValuation
A1: (4) Consensus-Based Valuation by Year (through FY2028)
A3: Reference Data
A4: Current share price | B4: =Assumptions!B5 -> 900 | C4: Finviz 2026-07-28
A5: Shares outstanding (millions) | B5: =Assumptions!B6 -> 1130
A6: Market capitalization (USD millions) | B6: =B4*B5 -> 1017000 | C6: Price x shares outstanding
A8: Multiples from applying the current price to each year of consensus
A9: Item | B9: FY2025(A) | C9: FY2026(E) | D9: FY2027(E) | E9: FY2028(E) | F9: Note
A10: EPS (consensus median) | B10: =Consensus!C18 -> 8.29 | C10: =Consensus!D18 -> 73.13 | D10: =Consensus!E18 -> 154.66 | E10: =Consensus!F18 -> 170.38
A11: BPS (consensus median) | B11: =Consensus!C24 -> 48.4 | C11: =Consensus!D24 -> 118.72 | D11: =Consensus!E24 -> 259.02 | E11: =Consensus!F24 -> 437.94
A12: EBITDA | B12: =Consensus!C12 -> 19198 | C12: =Consensus!D12 -> 107951 | D12: =Consensus!E12 -> 222099 | E12: =Consensus!F12 -> 246363
A13: Net debt (negative = net cash) | B13: =Consensus!C31 -> 4270 | C13: =Consensus!D31 -> -40902 | D13: =Consensus!E31 -> -143648 | E13: =Consensus!F31 -> -265525
A14: → P/E | B14: =IFERROR($B$4/B10,"n/a") -> 108.56454 | C14: =IFERROR($B$4/C10,"n/a") -> 12.306851 | D14: =IFERROR($B$4/D10,"n/a") -> 5.8192163 | E14: =IFERROR($B$4/E10,"n/a") -> 5.2823101 | F14: Current price / EPS for each year
A15: → P/B | B15: =IFERROR($B$4/B11,"n/a") -> 18.595041 | C15: =IFERROR($B$4/C11,"n/a") -> 7.5808625 | D15: =IFERROR($B$4/D11,"n/a") -> 3.4746352 | E15: =IFERROR($B$4/E11,"n/a") -> 2.055076 | F15: Current price / BPS for each year [*] the forward P/B in question
A16: → EV/EBITDA | B16: =IFERROR(($B$6+B13)/B12,"n/a") -> 53.196687 | C16: =IFERROR(($B$6+C13)/C12,"n/a") -> 9.0420469 | D16: =IFERROR(($B$6+D13)/D12,"n/a") -> 3.9322644 | E16: =IFERROR(($B$6+E13)/E12,"n/a") -> 3.0502754 | F16: EV = market cap plus net debt (net cash is deducted)
A18: Taken at face value, consensus puts FY2028 P/B near 1.9x and P/E near 4.9x, which looks cheap. The section below tests that premise.
A20: [*] Consensus Achievement (Haircut) Adjustment — The Critical Input
A21: Memory consensus uses current DRAM prices as an input, so it structurally lags the cycle.
A22: Lower the achievement rate below and see how far the valuation holds. 100% means consensus in full.
A24: [*] Consensus achievement rate | B24: =AVERAGE(SegmentMargin!B21:D21) -> 0.87716314 | C24: Linked to the average SegmentMargin achievement rate for FY2026-28, replacing the prior arbitrary 60%. Overwrite with a number to set it manually.
A25: FY2025 actual BPS | B25: =Consensus!C24 -> 48.4 | C25: Starting point - a confirmed actual
A26: Cumulative EPS FY26-28 (consensus) | B26: =Consensus!D18+Consensus!E18+Consensus!F18 -> 398.17 | C26: Sum of earnings per share over three years
A27: Adjusted FY2028 EPS | B27: =Consensus!F18*B24 -> 149.45106 | C27: Consensus EPS x achievement rate
A28: Adjusted FY2028 BPS | B28: =B25+B26*B24 -> 397.66005 | C28: FY25 BPS plus cumulative EPS x achievement rate (dividends ignored)
A29: Adjusted P/E | B29: =IFERROR($B$4/B27,"n/a") -> 6.0220384
A30: Adjusted P/B | B30: =IFERROR($B$4/B28,"n/a") -> 2.2632397
A31: Note: The achievement rate comes from the EBIT margin ratio. Since revenue is held at consensus, it approximates the earnings ratio. It applies to cumulative EPS in B26, so the FY2026-28 average is used.
A32: Applying Target Multiples — Implied Price
A33: Target P/E | B33: 10 | C33: [*] Normal multiple for a cyclical. Adjust within an 8-15x range.
A34: Implied price, P/E method | B34: =B27*B33 -> 1494.5106 | C34: Adjusted FY28 EPS x target P/E
A35: Target P/B | B35: 2 | C35: [*] The five-year P/B band is 1.26-2.53x, averaging 1.95x
A36: Implied price, P/B method | B36: =B28*B35 -> 795.32009 | C36: Adjusted FY28 BPS x target P/B
A37: Average of the two methods | B37: =AVERAGE(B34,B36) -> 1144.9153
A38: Current share price | B38: =B4 -> 900
A39: vs current price | B39: =B37/B38-1 -> 0.27212814
A41: Sensitivity — implied price (rows: consensus achievement rate / columns: target P/B on FY2028 BPS)
A42: Achievement rate \ Target P/B | B42: 1 | C42: 1.5 | D42: 2 | E42: 2.5 | F42: 3 | G42: 3.5 | H42: 4
A43: 0.3 | B43: =($B$25+$B$26*$A43)*B$42 -> 167.851 | C43: =($B$25+$B$26*$A43)*C$42 -> 251.7765 | D43: =($B$25+$B$26*$A43)*D$42 -> 335.702 | E43: =($B$25+$B$26*$A43)*E$42 -> 419.6275 | F43: =($B$25+$B$26*$A43)*F$42 -> 503.553 | G43: =($B$25+$B$26*$A43)*G$42 -> 587.4785 | H43: =($B$25+$B$26*$A43)*H$42 -> 671.404
A44: 0.4 | B44: =($B$25+$B$26*$A44)*B$42 -> 207.668 | C44: =($B$25+$B$26*$A44)*C$42 -> 311.502 | D44: =($B$25+$B$26*$A44)*D$42 -> 415.336 | E44: =($B$25+$B$26*$A44)*E$42 -> 519.17 | F44: =($B$25+$B$26*$A44)*F$42 -> 623.004 | G44: =($B$25+$B$26*$A44)*G$42 -> 726.838 | H44: =($B$25+$B$26*$A44)*H$42 -> 830.672
A45: 0.5 | B45: =($B$25+$B$26*$A45)*B$42 -> 247.485 | C45: =($B$25+$B$26*$A45)*C$42 -> 371.2275 | D45: =($B$25+$B$26*$A45)*D$42 -> 494.97 | E45: =($B$25+$B$26*$A45)*E$42 -> 618.7125 | F45: =($B$25+$B$26*$A45)*F$42 -> 742.455 | G45: =($B$25+$B$26*$A45)*G$42 -> 866.1975 | H45: =($B$25+$B$26*$A45)*H$42 -> 989.94
A46: 0.6 | B46: =($B$25+$B$26*$A46)*B$42 -> 287.302 | C46: =($B$25+$B$26*$A46)*C$42 -> 430.953 | D46: =($B$25+$B$26*$A46)*D$42 -> 574.604 | E46: =($B$25+$B$26*$A46)*E$42 -> 718.255 | F46: =($B$25+$B$26*$A46)*F$42 -> 861.906 | G46: =($B$25+$B$26*$A46)*G$42 -> 1005.557 | H46: =($B$25+$B$26*$A46)*H$42 -> 1149.208
A47: 0.7 | B47: =($B$25+$B$26*$A47)*B$42 -> 327.119 | C47: =($B$25+$B$26*$A47)*C$42 -> 490.6785 | D47: =($B$25+$B$26*$A47)*D$42 -> 654.238 | E47: =($B$25+$B$26*$A47)*E$42 -> 817.7975 | F47: =($B$25+$B$26*$A47)*F$42 -> 981.357 | G47: =($B$25+$B$26*$A47)*G$42 -> 1144.9165 | H47: =($B$25+$B$26*$A47)*H$42 -> 1308.476
A48: 0.85 | B48: =($B$25+$B$26*$A48)*B$42 -> 386.8445 | C48: =($B$25+$B$26*$A48)*C$42 -> 580.26675 | D48: =($B$25+$B$26*$A48)*D$42 -> 773.689 | E48: =($B$25+$B$26*$A48)*E$42 -> 967.11125 | F48: =($B$25+$B$26*$A48)*F$42 -> 1160.5335 | G48: =($B$25+$B$26*$A48)*G$42 -> 1353.9558 | H48: =($B$25+$B$26*$A48)*H$42 -> 1547.378
A49: 1 | B49: =($B$25+$B$26*$A49)*B$42 -> 446.57 | C49: =($B$25+$B$26*$A49)*C$42 -> 669.855 | D49: =($B$25+$B$26*$A49)*D$42 -> 893.14 | E49: =($B$25+$B$26*$A49)*E$42 -> 1116.425 | F49: =($B$25+$B$26*$A49)*F$42 -> 1339.71 | G49: =($B$25+$B$26*$A49)*G$42 -> 1562.995 | H49: =($B$25+$B$26*$A49)*H$42 -> 1786.28
A51: ="Current price of "&TEXT($B$4,"$#,##0")&" - find the closest cell; that combination is the achievement rate and target multiple the market assumes." -> Current price of $900 - find the closest cell; that combination is the achievement rate and target multiple the market assumes.
A53: Break-even Back-solve — What Justifies the Current Price
A54: Achievement rate required at a 2.0x target P/B | B54: =IFERROR(($B$4/2-$B$25)/$B$26,"n/a") -> 1.0086144 | C54: Below this rate, the current price is expensive
A55: Achievement rate required at a 2.5x target P/B | B55: =IFERROR(($B$4/2.5-$B$25)/$B$26,"n/a") -> 0.7825803
A56: Target P/B required at a 100% achievement rate | B56: =IFERROR($B$4/($B$25+$B$26),"n/a") -> 2.0153615 | C56: Even with consensus fully realized, this multiple is still required
A57: Target P/B required at a 60% achievement rate | B57: =IFERROR($B$4/($B$25+$B$26*0.6),"n/a") -> 3.1325922
A59: Note: Consensus net margins of 70.7% in FY2027 and 66.0% in FY2028 are exceptionally rare in manufacturing history. Do not leave the achievement rate at 100% by default.
A60: Note: At the same time, consensus already embeds capex rising from $27.7B in FY2026 to $48.0B in FY2028. That build-out is what causes the next oversupply.

Sheet ResearchSummary
A1: (5) Cross-Check of Seven Sell-Side Reports (15 May to 24 June 2026)
A2: Covers Nomura (May 15, Jun 24), BofA (May 29), Goldman memory (May 31), Morgan Stanley (Jun 2), Goldman strategy (Jun 16) and SocGen (Jun 24). Documents supplied by the user.
A4: 1. Core Argument by House
A5: House | B5: Date | C5: Core argument | F5: Target multiple (Korean names) | G5: Micron-related comment
A6: Goldman memory | B6: 5/31 | C6: The durability of the upcycle is not in the price. DRAM supply falls short by 5.0%, 5.9% and 3.9% in 2026, 2027 and 2028, with the shortage persisting through 2028. | F6: SK hynix at 9.0x P/E (methodology switched from P/B to P/E), Samsung at 9.0x | G6: Target price of $484, from normalized FY26 EPS of $22 at 22x
A7: Nomura | B7: 5/15 | C7: AI demand has passed an inflection. Long-term agreements lower the risk premium and drive a re-rating, with 30% annual growth from 2027 to 2031. | F7: Samsung at 5.0x P/B (discount rate cut from 17% to 10%), SK hynix at 6.0x (21% to 12%) | G7: Samsung and SK hynix earnings will far exceed Micron’s (not rated)
A8: Nomura | B8: 6/24 | C8: Raised Q3 2026 DRAM by 24% and NAND by 25% quarter on quarter. HBM profitability converges to commodity levels in 2027. | F8: Samsung at 5.0x P/B (target KRW 670,000), SK hynix at 6.0x (target KRW 4,700,000) | G8: -
A9: BofA | B9: 5/29 | C9: Supply coverage stays above 110% through 2028 with no meaningful oversupply, and ASP volatility runs below historical levels. | F9: - | G9: Two-year-forward P/B of 3.28x sits far above the historical median of 1.54x - a valuation warning
A10: MS | B10: 6/2 | C10: Chipflation. The bottleneck moves from GPUs to memory as HBM cannibalizes commodity DRAM capacity, leaving PCs and smartphones 12-15% short. | F10: - | G10: Classified as a beneficiary with pricing power
A11: Goldman strategy | B11: 6/16 | C11: A post-modern cycle in a capital-intensive expansion phase, where EPS growth rather than valuation drives returns | F11: - | G11: Capex beneficiary theme
A12: SocGen | B12: 6/24 | C12: Korea carries cycle risk. Foreign outflows plus a surge in retail leveraged ETFs have amplified concentration risk. | F12: - | G12: The key risk for Korean investors is the semiconductor cycle turning
A14: 2. Applying Each House’s Methodology to Micron — Implied Price
A15: Warning: These mechanically apply target multiples set for Korean names to Micron. They are not the houses’ actual Micron views, with the exception of the Goldman US team.
A16: Methodology source | B16: Multiple applied | C16: Applied to | D16: Base | E16: Implied share price | F16: vs current price | G16: Character
A17: Nomura, SK hynix | B17: 6.0x P/B | C17: FY2027 consensus BPS | D17: =Consensus!E24 -> 259.02 | E17: =D17*6 -> 1554.12 | F17: =E17/Assumptions!$B$5-1 -> 0.7268 | G17: Most bullish
A18: Nomura, Samsung | B18: 5.0x P/B | C18: FY2027 consensus BPS | D18: =Consensus!E24 -> 259.02 | E18: =D18*5 -> 1295.1 | F18: =E18/Assumptions!$B$5-1 -> 0.439 | G18: Bull
A19: Goldman Korea team | B19: 9.0x P/E | C19: Average FY26-27 EPS | D19: =(Consensus!D18+Consensus!E18)/2 -> 113.895 | E19: =D19*9 -> 1025.055 | F19: =E19/Assumptions!$B$5-1 -> 0.13895 | G19: Bull
A20: Five-year average | B20: 1.95x P/B | C20: FY2028 consensus BPS | D20: =Consensus!F24 -> 437.94 | E20: =D20*1.95 -> 853.983 | F20: =E20/Assumptions!$B$5-1 -> -0.05113 | G20: Neutral
A21: BofA historical median | B21: 1.54x P/B | C21: FY2028 consensus BPS | D21: =Consensus!F24 -> 437.94 | E21: =D21*1.54 -> 674.4276 | F21: =E21/Assumptions!$B$5-1 -> -0.250636 | G21: Conservative
A22: Goldman US team (actual Micron view) | B22: 22.0x P/E | C22: Normalized EPS per Goldman | D22: =22 -> 22 | E22: =D22*22 -> 484 | F22: =E22/Assumptions!$B$5-1 -> -0.46222222 | G22: Most conservative
A23: Current share price | E23: =Assumptions!B5 -> 900
A24: ="Report methodologies span "&TEXT(MIN(E17:E22),"$#,##0")&" to "&TEXT(MAX(E17:E22),"$#,##0")&". The current price of "&TEXT(E23,"$#,##0")&" sits in the middle of that range." -> Report methodologies span $484 to $1,554. The current price of $900 sits in the middle of that range.
A26: 3. What Is Priced In and What Is Not
A27: Basis | B27: Item | C27: Report basis | F27: Check against the model | H27: Verdict
A28: Priced in | B28: The earnings explosion itself | C28: Consensus EPS of $73 in FY26 rising to $155 in FY27 | F28: Shares up 709% over 52 weeks. An FY27 P/E of 5.4x shows the earnings numbers are accepted. | H28: Priced in
A29: Priced in | B29: Shift to net cash and balance sheet strength | C29: Consensus FY28 net cash of $266B | F29: Debt to equity of 0.06 and a current ratio of 3.42, none of which shows up in the risk premium | H29: Priced in
A30: Not priced in | B30: Durability of earnings (the crux) | C30: Goldman: the durability of the upcycle is still not adequately valued by the market | F30: A P/E of 7.4x on average FY26-27 EPS, 18% below the Goldman target of 9x | H30: Not priced in
A31: Not priced in | B31: Lower risk premium from long-term agreements | C31: Nomura: prepayments, penalties and three-to-five-year commitments justify cutting the discount rate from 17% to 10% | F31: The model uses a 15% cost of equity on a 2.14 beta. No discount rate reduction is reflected. | H31: Not priced in
A32: Not priced in | B32: HBM ASP catch-up (2027) | C32: Goldman sees HBM ASP up 44-50% versus consensus at 34% | F32: Partly embedded in the 70.7% consensus FY27 net margin | H32: Partly
A33: Not priced in | B33: Structurally lower supply elasticity | C33: Goldman: capacity CAGR of 7-8% for 2026-30 versus 12% in 2017-18. BofA: most capex goes into cleanroom shells. | F33: The model does not treat supply explicitly and proxies it through the achievement rate lever | H33: Not priced in
A34: Not priced in | B34: Capacity to expand shareholder returns | C34: BofA: Micron dividend yield of 0.05% versus a historical median of 0.4% | F34: Payout is currently 1.2%. Normalizing the dividend would support the valuation. | H34: Not priced in
A35: Not priced in (bearish) | B35: Fallout from the 2027-28 capex surge | C35: Consensus capex of $27.7B in FY26 rising to $48.0B in FY28 and $55.5B in FY29 | F35: That build-out creates supply from FY2029, which the model does not capture beyond FY29 | H35: Not priced in
A36: Not priced in (bearish) | B36: China: CXMT and YMTC | C36: Nomura: 30% share domestically and 10% globally, with cleanroom expansion running faster than estimated | F36: A disruptor in commodity DRAM, though entry into leading-edge and HBM remains difficult | H36: Not priced in
A37: Not priced in (bearish) | B37: Power and datacenter construction delays | C37: Nomura calls this a meaningful bottleneck risk and suggests monitoring via satellite imagery | F37: Risk of demand being deferred. Consensus assumes on-time start-up. | H37: Not priced in
A38: Not priced in (bearish) | B38: Hyperscaler free cash flow margins at zero | C38: BofA: cloud FCF margins at zero in 2026-27, with capex at 95-100% of operating cash flow versus 35-50% historically | F38: If funding conditions deteriorate, capex is at risk of being cut | H38: Not priced in
A39: Not priced in (bearish) | B39: The sharp upward revision in BPS estimates themselves | C39: BofA on May 29: two-year-forward P/B of 3.28x. On the same basis today it is 1.91x. | F39: Warning: the share price rose while P/B fell, meaning BPS estimates were revised up roughly 2.6-3.2x | H39: Not priced in
A41: 4. Applying the Goldman Stress Scenario to Micron (cross-check)
A42: Goldman tested SK hynix under price declines of 20% in 2027 and 20% in 2028, and again at 30% and 30% for a cumulative fall of roughly 50%, and found operating margins holding in the mid-40s to mid-50s.
A43: Scenarios | B43: Assumed operating margin | C43: Adjusted FY28 revenue | D43: Estimated net income | E43: EPS | F43: At 9x P/E | G43: At 12x P/E
A44: Goldman scenario 1 (-20% / -20%) | B44: 0.55 | C44: =Consensus!F6*0.64 -> 182474.88 | D44: =C44*B44*0.85 -> 85307.006 | E44: =D44/Assumptions!$B$6 -> 75.492926 | F44: =E44*9 -> 679.43633 | G44: =E44*12 -> 905.91511
A45: Goldman scenario 2 (-30% / -30%) | B45: 0.45 | C45: =Consensus!F6*0.5 -> 142558.5 | D45: =C45*B45*0.85 -> 54528.626 | E45: =D45/Assumptions!$B$6 -> 48.255421 | F45: =E45*9 -> 434.29879 | G45: =E45*12 -> 579.06506
A46: Note: Assumes a 15% tax rate. The revenue adjustment approximates a price decline partly offset by volume growth.
A47: ="Even in the harshest Goldman scenario, applying 9x P/E gives "&TEXT(F45,"$#,##0")&" and 12x gives "&TEXT(G45,"$#,##0")&"." -> Even in the harshest Goldman scenario, applying 9x P/E gives $434 and 12x gives $579.
A49: 5. Overall Verdict
A50: 1. The market has accepted the earnings but rejected their durability. At 7.4x average FY26-27 EPS it sits below the Goldman target of 9x and the 8-9.6x implied by Nomura.
A51: 2. Six of seven houses agree the shortage persists through 2028. There is effectively no dissent, and that unanimity is itself a risk.
A52: 3. The most important item not priced in is a lower discount rate from long-term agreements. Nomura cut theirs from 17% to 10%. Lowering the model cost of equity from 15% to 10% raises the implied price substantially.
A53: 4. Conversely, neither the market nor the reports reflect the FY2029-30 supply created by $48B of FY2028 capex, CXMT in China, power bottlenecks, or hyperscaler free cash flow at zero.
A54: 5. Warning - the point deserving most caution: on May 29 BofA flagged a two-year-forward P/B of 3.28x as far above the 1.54x historical median. Two months later the same measure reads 1.91x. The share price rose while the multiple fell, which means BPS estimates were revised up sharply. Much of why the stock looks cheap is the denominator moving, and if those revisions reverse the multiple widens again.
A56: Sources: seven research pieces supplied by the user, dated 15 May to 24 June 2026. Share prices and estimates moved substantially between publication and the current date of 28 July, so mind the timing gap.

Sheet ChinaRisk
A1: (6) China Risk — CXMT Listing and Domestic Immersion DUV Production (2026-07-27)
A2: Warning: The seven research pieces above were all published between May 15 and Jun 24, before the Jul 27 events. Their China assessments are already stale.
A4: 1. What Happened (27 July 2026)
A5: CXMT lists on the Shanghai STAR Market | B5: Raised $8.6B, the largest Asian IPO of 2026. Up 466-472% on day one, market cap around $489B.
A6: Domestic immersion DUV enters production | B6: A Shanghai state-owned enterprise began producing immersion DUV tools. Roughly five units in 2026 and twenty in 2027.
A7: Delivery destinations | B7: SMIC, Hua Hong and CXMT - a memory maker is directly included
A8: Technical specification | B8: Rated for 28nm-class processes, with claims of reaching 7nm-class using multi-patterning
A9: Market reaction | B9: Over $1 trillion of market value erased. Micron -8%, SanDisk -15%, SK hynix ADR -8%.
A10: Regulatory status | B10: CXMT is designated a military company by the US Department of Defense. US legislators proposed additional immersion DUV restrictions in April.
A12: 2. CXMT Capacity — Conflict With the Goldman and Nomura Assumptions
A13: Item | B13: CXMT | C13: SK hynix | D13: Micron | E13: Samsung | F13: Note
A14: 2026 capacity additions (kwspm) | B14: 85 | C14: 60 | D14: 30 | E14: 15 | F14: CXMT alone equals 81% of the 105 kwspm added by the top three combined
A15: Total capacity at end-2026 (kwspm) | B15: 350 | C15: - | D15: 375 | E15: - | F15: Closes to within 25k of Micron
A16: Global DRAM share, 2027E | B16: 0.12 | C16: - | D16: - | E16: - | F16: CXMT target
A17: Global DRAM share, 2028E | B17: 0.17 | C17: - | D17: - | E17: - | F17: CXMT target
A19: Goldman (May 31) forecast undersupply through 2028 assuming top-three commodity DRAM capacity growth of 7-8% CAGR over 2026-30 and 15% supply growth. CXMT was not in that calculation.
A20: Nomura (Jun 24) judged there was no need for excessive concern at this stage, but the equipment bottleneck underpinning that view was shaken on Jul 27.
A22: 3. Micron Revenue Structure — Where the Exposure Sits
A23: Segment | B23: TTM revenue share | C23: TTM revenue ($m) | D23: CXMT threat level | E23: Rationale
A24: Commodity DRAM | B24: =MixPath!B26 -> 0.52981686 | C24: =B24*Assumptions!$B$19 -> 47828.687 | D24: High | E24: Over 98% of CXMT revenue is commodity DRAM, centred on DDR5 and LPDDR5X
A25: HBM | B25: =MixPath!B27 -> 0.23018314 | C25: =B25*Assumptions!$B$19 -> 20779.553 | D25: Low | E25: CXMT lists no HBM project in its IPO prospectus. HBM3E production is targeted for 2027, one to two generations behind.
A26: NAND | B26: =MixPath!B28 -> 0.24 | C26: =B26*Assumptions!$B$19 -> 21665.76 | D26: Medium | E26: YMTC is a separate threat, but CXMT is DRAM-only
A27: Note: DRAM is 76% of revenue (FY26 Q3) and HBM is over 30% of DRAM revenue, so commodity DRAM is roughly 53% of the total. More than half of Micron revenue sits in direct competition with CXMT.
A29: 4. Channel A — Sensitivity of Earnings to Impairment
A30: Commodity DRAM ASP decline scenario. Under a fixed-cost structure most of the revenue loss flows straight to profit (85% pass-through). [*] Revised 2026-07-31: the weight was changed from a fixed TTM 53% to the FY2028 value derived on MixPath.
A31: Commodity DRAM ASP decline | B31: FY28 revenue loss | C31: Adjusted net income | D31: Adjusted EPS | E31: At 6x P/E | F31: At 9x P/E | G31: At 12x P/E
A32: 0 | B32: =Consensus!F6*MixPath!$D$26*A32 -> 0 | C32: =Consensus!F15-B32*0.85 -> 189388 | D32: =C32/Assumptions!$B$6 -> 167.6 | E32: =D32*6 -> 1005.6 | F32: =D32*9 -> 1508.4 | G32: =D32*12 -> 2011.2
A33: 0.1 | B33: =Consensus!F6*MixPath!$D$26*A33 -> 16784.246 | C33: =Consensus!F15-B33*0.85 -> 175121.39 | D33: =C33/Assumptions!$B$6 -> 154.97468 | E33: =D33*6 -> 929.84809 | F33: =D33*9 -> 1394.7721 | G33: =D33*12 -> 1859.6962
A34: 0.2 | B34: =Consensus!F6*MixPath!$D$26*A34 -> 33568.492 | C34: =Consensus!F15-B34*0.85 -> 160854.78 | D34: =C34/Assumptions!$B$6 -> 142.34936 | E34: =D34*6 -> 854.09619 | F34: =D34*9 -> 1281.1443 | G34: =D34*12 -> 1708.1924
A35: 0.3 | B35: =Consensus!F6*MixPath!$D$26*A35 -> 50352.738 | C35: =Consensus!F15-B35*0.85 -> 146588.17 | D35: =C35/Assumptions!$B$6 -> 129.72405 | E35: =D35*6 -> 778.34428 | F35: =D35*9 -> 1167.5164 | G35: =D35*12 -> 1556.6886
A36: 0.4 | B36: =Consensus!F6*MixPath!$D$26*A36 -> 67136.984 | C36: =Consensus!F15-B36*0.85 -> 132321.56 | D36: =C36/Assumptions!$B$6 -> 117.09873 | E36: =D36*6 -> 702.59237 | F36: =D36*9 -> 1053.8886 | G36: =D36*12 -> 1405.1847
A37: 0.5 | B37: =Consensus!F6*MixPath!$D$26*A37 -> 83921.23 | C37: =Consensus!F15-B37*0.85 -> 118054.95 | D37: =C37/Assumptions!$B$6 -> 104.47341 | E37: =D37*6 -> 626.84047 | F37: =D37*9 -> 940.2607 | G37: =D37*12 -> 1253.6809
A38: Even with ASP down 30%, FY28 EPS is around $134, implying $1,200 at 9x. Through the earnings channel alone the damage is smaller than expected.
A39: Warning: The prior version applied the TTM commodity share of 53% to FY2028 revenue and overstated the CXMT threat. Mix shift makes the FY2028 commodity share lower - time is on Micron’s side.
A40: 5. Channel B — Impairment Through the Discount Rate [*] This Is the Real One
A41: Justified P/B = (ROE - g) / (COE - g). Holding FY2028 consensus BPS, a 30% sustainable ROE and 5% growth fixed, only the cost of equity varies.
A42: Scenarios | B42: COE | C42: Justified P/B | D42: Implied share price | E42: vs current price | F42: Interpretation
A43: Nomura argument (re-rating on long-term agreements) | B43: 0.1 | C43: =(Assumptions!$B$28-Assumptions!$B$29)/(B43-Assumptions!$B$29) -> 5 | D43: =C43*Consensus!F24 -> 2189.7 | E43: =D43/Assumptions!$B$5-1 -> 1.433 | F43: Argues for cutting the discount rate from 17% to 10%
A44: Current model default (CAPM) | B44: 0.15 | C44: =(Assumptions!$B$28-Assumptions!$B$29)/(B44-Assumptions!$B$29) -> 2.5 | D44: =C44*Consensus!F24 -> 1094.85 | E44: =D44/Assumptions!$B$5-1 -> 0.2165 | F44: Calculated on a beta of 2.14
A45: Reflecting China risk | B45: 0.18 | C45: =(Assumptions!$B$28-Assumptions!$B$29)/(B45-Assumptions!$B$29) -> 1.9230769 | D45: =C45*Consensus!F24 -> 842.19231 | E45: =D45/Assumptions!$B$5-1 -> -0.064230769 | F45: [*] The level implied by the current price
A46: China risk escalating | B46: 0.22 | C46: =(Assumptions!$B$28-Assumptions!$B$29)/(B46-Assumptions!$B$29) -> 1.4705882 | D46: =C46*Consensus!F24 -> 644.02941 | E46: =D46/Assumptions!$B$5-1 -> -0.28441176 | F46: If reclassified as a cyclical
A48: ="The current price of "&TEXT(Assumptions!B5,"$#,##0")&" implies a cost of equity near 18%. Nomura argues for 10%. That 8pp gap is the entire debate." -> The current price of $900 implies a cost of equity near 18%. Nomura argues for 10%. That 8pp gap is the entire debate.
A49: The Jul 27 events did not immediately change EPS estimates but pushed the cost of equity up. That is precisely the variable the bull case depended on - Goldman switching from P/B to P/E methodology and Nomura cutting the discount rate.
A51: 6. A Balanced View — Reasons Not to Overstate This
A52: DUV volumes are still negligible | B52: Five units in 2026 and twenty in 2027. ASML ships hundreds of immersion tools a year.
A53: 28nm-class is not leading-edge DRAM | B53: Leading DRAM nodes require layered multi-patterning, which carries heavy yield, cost and cycle-time penalties
A54: HBM barriers are a separate matter | B54: Requires TSV and hybrid bonding in back-end plus qualification with Nvidia and the hyperscalers. CXMT is one to two generations behind.
A55: DoD designation blocks US datacenters | B55: Supply into US datacenters is effectively closed on security grounds. Nomura makes this point as well.
A56: Existing long-term agreements still hold | B56: Contracts carrying prepayments, penalties and floor prices do not collapse quickly
A57: The point is not volume but the removal of a ceiling | B57: It is not immediate supply but a change in terminal assumptions, which is why it hits the multiple before it hits EPS
A59: Sources: Reuters and Tom’s Hardware (Chinese immersion DUV production, 2026-07-27/28), CXMT STAR listing coverage, SemiAnalysis (CXMT capacity), Benzinga and CNBC (market reaction)
A62: 7. [*] The Twist — CXMT Is a Price Taker, Not a Price Destroyer (confirmed July 2026)
A63: Apple negotiation | B63: CXMT quoted Apple a higher price than Samsung or SK hynix, on the view that there is no reason to sell cheaply
A64: Server DDR5 transacted prices | B64: On 64GB DDR5 RDIMM, CXMT prices slightly above Samsung at roughly $1,240. Samsung and SK hynix at CNY 18,595.91, with CXMT higher still.
A65: Response to Huawei | B65: Refused a discount request even from Huawei, a domestic customer
A66: Domestic pushback | B66: Chinese electronics makers petitioned MIIT that price increases at CXMT and YMTC are delaying product launches
A67: Why Apple is interested | B67: Distributors report CXMT pricing in line with Samsung, SK hynix and Micron. The only advantage is availability of volume.
A68: Expansion plans | B68: Two new fabs in Shanghai and Hefei. Once running, capacity passes 600k wafers per month - more than double current levels.
A70: 8. Why This Matters — Two Historical Patterns of Chinese Entry
A71: Pattern | B71: Precedent | C71: Results | D71: Applies to CXMT?
A72: A. Share first (dumping) | B72: Solar, LED, LCD, steel | C72: Prices collapse and industry-wide margins disappear | D72: Not observed so far
A73: B. Profit first (price taking) | B73: Industries where the oligopoly holds | C73: Share is lost but price is maintained | D73: [*] What CXMT is currently doing
A74: The 28 July analysis assumed pattern A by default. Observed behaviour is pattern B, which materially weakens the bear case.
A75: One decisive caveat: this is a shortage phase. Anyone prices high in a shortage. The real test comes once supply catches demand.
A77: 9. Channel C — Impairment Through Volume and Share Rather Than Price
A78: If CXMT accepts market prices, ASP holds and Micron loses only share. That is far gentler than the price channel.
A79: Commodity DRAM volume displaced | B79: FY28 revenue loss | C79: Adjusted net income | D79: Adjusted EPS | E79: At 6x P/E | F79: At 9x P/E | G79: At 12x P/E
A80: 0 | B80: =Consensus!F6*$B$24*A80 -> 0 | C80: =Consensus!F15-B80*0.7 -> 189388 | D80: =C80/Assumptions!$B$6 -> 167.6 | E80: =D80*6 -> 1005.6 | F80: =D80*9 -> 1508.4 | G80: =D80*12 -> 2011.2
A81: 0.05 | B81: =Consensus!F6*$B$24*A81 -> 7552.9897 | C81: =Consensus!F15-B81*0.7 -> 184100.91 | D81: =C81/Assumptions!$B$6 -> 162.92116 | E81: =D81*6 -> 977.52694 | F81: =D81*9 -> 1466.2904 | G81: =D81*12 -> 1955.0539
A82: 0.1 | B82: =Consensus!F6*$B$24*A82 -> 15105.979 | C82: =Consensus!F15-B82*0.7 -> 178813.81 | D82: =C82/Assumptions!$B$6 -> 158.24231 | E82: =D82*6 -> 949.45388 | F82: =D82*9 -> 1424.1808 | G82: =D82*12 -> 1898.9078
A83: 0.15 | B83: =Consensus!F6*$B$24*A83 -> 22658.969 | C83: =Consensus!F15-B83*0.7 -> 173526.72 | D83: =C83/Assumptions!$B$6 -> 153.56347 | E83: =D83*6 -> 921.38082 | F83: =D83*9 -> 1382.0712 | G83: =D83*12 -> 1842.7616
A84: 0.2 | B84: =Consensus!F6*$B$24*A84 -> 30211.959 | C84: =Consensus!F15-B84*0.7 -> 168239.63 | D84: =C84/Assumptions!$B$6 -> 148.88463 | E84: =D84*6 -> 893.30776 | F84: =D84*9 -> 1339.9616 | G84: =D84*12 -> 1786.6155
A85: 0.3 | B85: =Consensus!F6*$B$24*A85 -> 45317.938 | C85: =Consensus!F15-B85*0.7 -> 157665.44 | D85: =C85/Assumptions!$B$6 -> 139.52694 | E85: =D85*6 -> 837.16165 | F85: =D85*9 -> 1255.7425 | G85: =D85*12 -> 1674.3233
A86: Note: Unlike a price decline, lost volume also reduces variable cost, so pass-through is set at 70% here versus 85% in Channel A.
A88: 10. Revised Overall View
A89: 1. CXMT has behaved profit-first so far, quoting Apple a premium and refusing Huawei a discount. That suggests the memory oligopoly may widen to four players while remaining intact.
A90: 2. The impairment path therefore shifts from price (Channel A) to volume and share (Channel C). The damage to Micron earnings is smaller than initially presented.
A91: 3. The discount rate logic in Channel B nonetheless stands. If CXMT takes 12% share in 2027 and 17% in 2028, Micron’s terminal share assumption falls.
A92: 4. Warning - the most important caveat: this is a shortage phase. Price discipline during a shortage proves nothing. The real test is whether discipline holds once CXMT reaches 600k wafers per month, more than double today.
A93: 5. Political variable: Chinese electronics makers have petitioned MIIT over CXMT price increases. If Beijing pushes domestic-supply priority and price restraint, that discipline could break for policy reasons.
A94: 6. Conclusion: lower the probability on the price-collapse leg of the bear case. Share erosion combined with terminal multiple compression remains valid.
A96: Sources: Techworld, EBN and Economy Tribune (CXMT quoting Apple a premium), TechPowerUp, Tom’s Hardware and Notebookcheck (server DDR5 price comparison), wccftech (600k wpm expansion, Huawei discount refusal)

Sheet Buybacks
A1: (7) Shareholder Returns — Buyback Simulator After the CHIPS Restriction Lifts (2026-12-09)
A3: 1. Confirmed Facts
A4: Nature of the CHIPS restriction | B4: A standard condition for CHIPS award recipients, not specific to Micron. It runs five years from the award date, and for the first two years buybacks are permitted only within a specified limit for offsetting employee compensation dilution.
A5: Key dates | B5: Award date 9 Dec 2024. The first two years expire 9 Dec 2026; the full five-year period ends 9 Dec 2029.
A6: Company policy (Q3 FY26) | B6: Shareholder returns expand once the restriction lifts, returning 100% of excess cash to shareholders
A7: Primary instrument | B7: CFO Mark Murphy: the dividend was raised, but buybacks are the primary vehicle
A8: Recent execution | B8: $300m repurchased in FY26 Q1 and $350m in Q2, then paused in Q3
A9: Current dividend | B9: $0.15 quarterly (raised Jun 24), $0.60 annually, a 0.07% yield
A10: Competing uses of cash | B10: FY26 capex of $27B. Quarterly FY27 capex is guided above FY26 Q4, with more than half the increase in construction.
A12: 2. Analyst Estimates — The Dispersion Is Enormous
A13: Source | B13: Estimate | C13: Amount ($m) | D13: vs market cap | E13: Character
A14: UBS (Timothy Arcuri) | B14: Cumulative FCF of over $400B across 2027-2029, enough to repurchase more than 40% of shares by end-2028 | C14: 380000 | D14: =C14/(Assumptions!$B$5*Assumptions!$B$6) -> 0.37364798 | E14: Most bullish
A15: BofA | B15: Up to $31.7B of buybacks in FY2027 alone | C15: 31700 | D15: =C15/(Assumptions!$B$5*Assumptions!$B$6) -> 0.031170108 | E15: Conservative
A16: Consensus FY28 net cash | B16: Projected FY2028 net cash balance, approximating the ceiling on returns | C16: =Consensus!F31*-1 -> 265525 | D16: =C16/(Assumptions!$B$5*Assumptions!$B$6) -> 0.26108653 | E16: Neutral
A17: The UBS and BofA FY2027 estimates differ by more than tenfold. UBS assumes all free cash flow is deployed; BofA assumes capex constrains it.
A19: 3. Simulator — Edit the Yellow Cells
A20: [*] Total buyback amount ($m) | B20: 265525 | C20: Default is consensus FY28 net cash. Try UBS at 380,000 and BofA at 31,700 as well.
A21: [*] Average purchase price | B21: 900 | C21: Assumed average share price over the repurchase period
A22: Shares repurchased (millions) | B22: =B20/B21 -> 295.02778 | C22: Amount / price
A23: Share of count retired | B23: =B22/Assumptions!B6 -> 0.26108653 | C23: Against the current share count
A24: Shares outstanding after repurchase (millions) | B24: =Assumptions!B6-B22 -> 834.97222
A26: 4. FY2028 Metrics — Before and After the Buyback
A27: Item | B27: Before buyback (consensus) | C27: After buyback | D27: Change | E27: Interpretation
A28: Shares outstanding (millions) | B28: =Assumptions!B6 -> 1130 | C28: =B24 -> 834.97222 | D28: =IFERROR(C28/B28-1,"n/a") -> -0.26108653
A29: Net income ($m) | B29: =Consensus!F15 -> 189388 | C29: =B29 -> 189388 | D29: =IFERROR(C29/B29-1,"n/a") -> 0 | E29: Buybacks do not change net income
A30: Shareholders equity ($m) | B30: =Consensus!F24*Assumptions!B6 -> 494872.2 | C30: =B30-B20 -> 229347.2 | D30: =IFERROR(C30/B30-1,"n/a") -> -0.53655267 | E30: Equity falls by the amount repurchased
A31: EPS | B31: =B29/B28 -> 167.6 | C31: =C29/C28 -> 226.81952 | D31: =IFERROR(C31/B31-1,"n/a") -> 0.35333843 | E31: [*] Materially improved
A32: BPS | B32: =B30/B28 -> 437.94 | C32: =C30/C28 -> 274.67644 | D32: =IFERROR(C32/B32-1,"n/a") -> -0.37279892 | E32: [*] Actually worse, since repurchases occur above 1x book
A33: P/E | B33: =Assumptions!B5/B31 -> 5.3699284 | C33: =Assumptions!B5/C31 -> 3.9679124 | D33: =IFERROR(C33/B33-1,"n/a") -> -0.26108653 | E33: Looks cheaper
A34: P/B | B34: =Assumptions!B5/B32 -> 2.055076 | C34: =Assumptions!B5/C32 -> 3.2765824 | D34: =IFERROR(C34/B34-1,"n/a") -> 0.594385 | E34: Looks more expensive
A36: [*] Key point: buybacks lower P/E and raise P/B, because book value falls by the cash spent.
A37: So the claim that FY2028 forward P/B of 1.91x is cheap cannot coexist with the claim of a huge buyback funded by $265.5B of net cash. The two pillars of the bull case consume each other.
A38: The correct test is whether the repurchase price sits below intrinsic value. Below it creates value; above it destroys value.
A40: 5. Sensitivity — Post-Buyback FY2028 EPS (rows: amount / columns: average purchase price)
A41: Amount ($m) \ Price | B41: 600 | C41: 700 | D41: 800 | E41: 900 | F41: 1000 | G41: 1200
A42: 31700 | B42: =Consensus!$F$15/(Assumptions!$B$6-$A42/B$41) -> 175.82052 | C42: =Consensus!$F$15/(Assumptions!$B$6-$A42/C$41) -> 174.59713 | D42: =Consensus!$F$15/(Assumptions!$B$6-$A42/D$41) -> 173.6907 | E42: =Consensus!$F$15/(Assumptions!$B$6-$A42/E$41) -> 172.99219 | F42: =Consensus!$F$15/(Assumptions!$B$6-$A42/F$41) -> 172.4374 | G42: =Consensus!$F$15/(Assumptions!$B$6-$A42/G$41) -> 171.61187
A43: 100000 | B43: =Consensus!$F$15/(Assumptions!$B$6-$A43/B$41) -> 196.59654 | C43: =Consensus!$F$15/(Assumptions!$B$6-$A43/C$41) -> 191.8547 | D43: =Consensus!$F$15/(Assumptions!$B$6-$A43/D$41) -> 188.44577 | E43: =Consensus!$F$15/(Assumptions!$B$6-$A43/E$41) -> 185.87699 | F43: =Consensus!$F$15/(Assumptions!$B$6-$A43/F$41) -> 183.87184 | G43: =Consensus!$F$15/(Assumptions!$B$6-$A43/G$41) -> 180.94395
A44: 150000 | B44: =Consensus!$F$15/(Assumptions!$B$6-$A44/B$41) -> 215.21364 | C44: =Consensus!$F$15/(Assumptions!$B$6-$A44/C$41) -> 206.81997 | D44: =Consensus!$F$15/(Assumptions!$B$6-$A44/D$41) -> 200.94218 | E44: =Consensus!$F$15/(Assumptions!$B$6-$A44/E$41) -> 196.59654 | F44: =Consensus!$F$15/(Assumptions!$B$6-$A44/F$41) -> 193.25306 | G44: =Consensus!$F$15/(Assumptions!$B$6-$A44/G$41) -> 188.44577
A45: 200000 | B45: =Consensus!$F$15/(Assumptions!$B$6-$A45/B$41) -> 237.72552 | C45: =Consensus!$F$15/(Assumptions!$B$6-$A45/C$41) -> 224.31743 | D45: =Consensus!$F$15/(Assumptions!$B$6-$A45/D$41) -> 215.21364 | E45: =Consensus!$F$15/(Assumptions!$B$6-$A45/E$41) -> 208.62815 | F45: =Consensus!$F$15/(Assumptions!$B$6-$A45/F$41) -> 203.64301 | G45: =Consensus!$F$15/(Assumptions!$B$6-$A45/G$41) -> 196.59654
A46: 265525 | B46: =Consensus!$F$15/(Assumptions!$B$6-$A46/B$41) -> 275.49015 | C46: =Consensus!$F$15/(Assumptions!$B$6-$A46/C$41) -> 252.28907 | D46: =Consensus!$F$15/(Assumptions!$B$6-$A46/D$41) -> 237.30044 | E46: =Consensus!$F$15/(Assumptions!$B$6-$A46/E$41) -> 226.81952 | F46: =Consensus!$F$15/(Assumptions!$B$6-$A46/F$41) -> 219.07863 | G46: =Consensus!$F$15/(Assumptions!$B$6-$A46/G$41) -> 208.40973
A47: 380000 | B47: =Consensus!$F$15/(Assumptions!$B$6-$A47/B$41) -> 381.31812 | C47: =Consensus!$F$15/(Assumptions!$B$6-$A47/C$41) -> 322.55864 | D47: =Consensus!$F$15/(Assumptions!$B$6-$A47/D$41) -> 289.14198 | E47: =Consensus!$F$15/(Assumptions!$B$6-$A47/E$41) -> 267.58116 | F47: =Consensus!$F$15/(Assumptions!$B$6-$A47/F$41) -> 252.51733 | G47: =Consensus!$F$15/(Assumptions!$B$6-$A47/G$41) -> 232.8541
A48: Note: Consensus FY2028 net income is held fixed. In practice net income falls slightly by the interest income forgone on the cash spent.
A49: Note: Pre-buyback consensus EPS is $170.38. Under the UBS scenario ($380B at $900 per share) the result sits near the bottom right of the grid.
A51: 6. Caveats
A52: 1. The definition of excess cash has not been disclosed. If it means the balance after capex, the FY2027 capex surge to $47.1B sharply reduces actual capacity.
A53: 2. December 9 is the date the restriction lifts, not the date of an announcement. Size and duration will be disclosed around that time.
A54: 3. The UBS estimate of retiring 40% assumes the current share price. If the stock rises, the same dollars buy fewer shares and the retirement ratio falls.
A55: 4. The company is currently diluting rather than retiring - buyback yield of -0.62%, share count up 0.62% year over year, and a total shareholder yield of -0.55%.
A56: 5. Everything here assumes consensus FY2028 results are realized. Read it alongside the achievement rate lever on the ConsensusValuation tab.
A58: Sources: Micron Q3 FY2026 results and earnings call (2026-06-24), UBS (July 2026), BofA, Micron 10-Q (FY2026)
A60: 7. Scenario by Buyback Size — Recalculated Implied Price
A61: Logic: a buyback removes cash from the company and reduces the share count. Total value falls by the amount spent, and that value is divided among fewer shares.
A62: Adjusted price = (prior implied price x prior share count - amount spent) / (prior share count - amount spent / purchase price)
A64: [*] Assumed purchase price | B64: 739 | C64: Default is the current share price. A purchase price above intrinsic value destroys value.
A66: Scenarios | B66: Implied price before buyback | C66: BofA case ($31.7B) | D66: Change | E66: UBS case ($380B) | F66: Change | G66: Verdict
A67: Bull | B67: =Scenarios!I5 -> 2173.9454 | C67: =(B67*Assumptions!$B$6-$C$15)/(Assumptions!$B$6-$C$15/$B$64) -> 2230.5666 | D67: =C67/B67-1 -> 0.026045362 | E67: =(B67*Assumptions!$B$6-$C$14)/(Assumptions!$B$6-$C$14/$B$64) -> 3372.177 | F67: =E67/B67-1 -> 0.55117833 | G67: =IF(B67>$B$64,"Intrinsic value above purchase price - value created","Intrinsic value below purchase price - value destroyed") -> Intrinsic value above purchase price - value created
A68: Base | B68: =Scenarios!I6 -> 1541.6583 | C68: =(B68*Assumptions!$B$6-$C$15)/(Assumptions!$B$6-$C$15/$B$64) -> 1573.3302 | D68: =C68/B68-1 -> 0.020544058 | E68: =(B68*Assumptions!$B$6-$C$14)/(Assumptions!$B$6-$C$14/$B$64) -> 2211.9072 | F68: =E68/B68-1 -> 0.43475839 | G68: =IF(B68>$B$64,"Intrinsic value above purchase price - value created","Intrinsic value below purchase price - value destroyed") -> Intrinsic value above purchase price - value created
A69: Bear | B69: =Scenarios!I7 -> 399.71553 | C69: =(B69*Assumptions!$B$6-$C$15)/(Assumptions!$B$6-$C$15/$B$64) -> 386.32778 | D69: =C69/B69-1 -> -0.033493197 | E69: =(B69*Assumptions!$B$6-$C$14)/(Assumptions!$B$6-$C$14/$B$64) -> 116.40067 | F69: =E69/B69-1 -> -0.70879124 | G69: =IF(B69>$B$64,"Intrinsic value above purchase price - value created","Intrinsic value below purchase price - value destroyed") -> Intrinsic value below purchase price - value destroyed
A71: ="In the base case (implied price "&TEXT(B68,"$#,##0")&"), a purchase price of "&TEXT($B$64,"$#,##0")&" exceeds intrinsic value, so the buyback lowers per-share value." -> In the base case (implied price $1,542), a purchase price of $739 exceeds intrinsic value, so the buyback lowers per-share value.
A72: Buybacks are not magic. Value is created only by buying cheaply. What matters is the price paid, not the amount spent.
A73: Warning on consistency: in the bear case the company never generates the $380B UBS assumes. The UBS estimate itself presupposes bull-case free cash flow.
A74: Warning: a bear case combined with a large buyback is therefore not a real-world combination. It appears in the table only for arithmetic comparison.
A76: 8. Break-even Purchase Price — Below What Level Does Buying Create Value
A77: Scenarios | B77: Implied price before buyback equals the break-even price | C77: vs the current price of $838 | D77: Interpretation
A78: Bull | B78: =B67 -> 2173.9454 | C78: =B78/Assumptions!$B$5-1 -> 1.4154949 | D78: =IF(B78>Assumptions!$B$5,"Buying at the current price still creates value","Buying at the current price destroys value - the company should wait") -> Buying at the current price still creates value
A79: Base | B79: =B68 -> 1541.6583 | C79: =B79/Assumptions!$B$5-1 -> 0.71295369 | D79: =IF(B79>Assumptions!$B$5,"Buying at the current price still creates value","Buying at the current price destroys value - the company should wait") -> Buying at the current price still creates value
A80: Bear | B80: =B69 -> 399.71553 | C80: =B80/Assumptions!$B$5-1 -> -0.55587163 | D80: =IF(B80>Assumptions!$B$5,"Buying at the current price still creates value","Buying at the current price destroys value - the company should wait") -> Buying at the current price destroys value - the company should wait
A81: When management buys after December 9 matters more than how much. Executing a large repurchase at the peak destroys shareholder value.
A82: Note: Micron has repurchased stock at prior cycle peaks. Check the timing of execution at every earnings report.
A84: Warning — An Important Unverified Premise Behind the UBS Estimate
A85: The Micron agreement imposes restrictions over five years from the award date, and the dilution-offset limit is specified only for the first two years.
A86: The company has said it will expand shareholder returns from 9 Dec 2026, the second anniversary, but the disclosed language does not make clear what conditions remain in years three through five, to 9 Dec 2029.
A87: The UBS estimate of retiring 40% by 2028 rests on the restriction lifting fully in December 2026. If constraints remain in years three to five, it is overstated.
A88: How to verify: read the CHIPS-related notes in Micron’s 10-K and 10-Q, or the buyback clause in the original 8-K dated 2024-12-10.
A90: Reference — Major CHIPS direct-funding recipients (same conditions apply)
A91: Intel | B91: Up to $8.5B | C91: 2024
A92: TSMC | B92: $6.6B | C92: Finalized November 2024
A93: Micron | B93: Up to $6.1B | C93: Finalized 9 December 2024
A94: Samsung | B94: $4.745B | C94: Finalized December 2024
A95: Texas Instruments | B95: $1.61B | C95: Finalized December 2024
A96: SK hynix | B96: $1.2B (West Lafayette, Indiana) | C96: Updated April 2026
A97: GlobalFoundries | B97: $0.8B | C97: April 2026
A98: Note: Award dates differ by company, so restrictions lift at different times. Detailed terms are negotiated individually and are not identical across recipients.

Sheet PurchaseStrategy
A1: (8) Buyback Strategy — Drawdown-Band Tranche Simulator
A3: 1. Reference Values
A4: 52-week high | B4: =CurrentData!B6 -> 1255 | C4: Finviz
A5: Current share price | B5: =Assumptions!B5 -> 900
A6: Current drawdown | B6: =B5/B4-1 -> -0.28286853 | C6: Already down 33%, so the -30% band is effectively reached
A7: [*] Total buyback budget ($m) | B7: 31700 | C7: [*] BofA estimate. UBS assumes $380,000m.
A8: Shares outstanding (millions) | B8: =Assumptions!B6 -> 1130
A10: 2. Drawdown Bands and Allocation — edit the yellow cells
A11: Band | B11: Drawdown from peak | C11: Purchase price | D11: Allocation A (33/33/33) | E11: Allocation B (30/40/30) | F11: Shares bought, A | G11: Shares bought, B | H11: Probability of reaching
A12: Shallow correction | B12: -0.3 | C12: =$B$4*(1+B12) -> 878.5 | D12: 0.33333333 | E12: 0.3 | F12: =$B$7*D12/C12 -> 12.028078 | G12: =$B$7*E12/C12 -> 10.82527 | H12: 1
A13: Cycle average | B13: -0.5 | C13: =$B$4*(1+B13) -> 627.5 | D13: 0.33333333 | E13: 0.4 | F13: =$B$7*D13/C13 -> 16.839309 | G13: =$B$7*E13/C13 -> 20.207171 | H13: 0.5
A14: Extreme (bear case realized) | B14: -0.8 | C14: =$B$4*(1+B14) -> 251 | D14: 0.33333333 | E14: 0.3 | F14: =$B$7*D14/C14 -> 42.098274 | G14: =$B$7*E14/C14 -> 37.888446 | H14: 0.15
A15: Total | D15: =SUM(D12:D14) -> 1 | E15: =SUM(E12:E14) -> 1 | F15: =SUM(F12:F14) -> 70.965661 | G15: =SUM(G12:G14) -> 68.920888
A17: 3. [*] Key Point 1 — The Effective Average Price Is Harmonic, Not Arithmetic
A18: The same dollar amount buys more shares at lower prices, so the effective purchase price is well below the simple average.
A19: Method | B19: Arithmetic average price | C19: Effective (harmonic) average price | D19: Difference | E19: Total shares bought | F19: Share of count retired | G19: vs a lump sum at $838
A20: Allocation A (33/33/33) | B20: =SUMPRODUCT(D12:D14,C12:C14) -> 585.66667 | C20: =$B$7/F15 -> 446.69492 | D20: =C20/B20-1 -> -0.23728814 | E20: =F15 -> 70.965661 | F20: =E20/$B$8 -> 0.06280147 | G20: =E20/$E$22-1 -> 1.014798
A21: Allocation B (30/40/30) | B21: =SUMPRODUCT(E12:E14,C12:C14) -> 589.85 | C21: =$B$7/G15 -> 459.94764 | D21: =C21/B21-1 -> -0.22022948 | E21: =G15 -> 68.920888 | F21: =E21/$B$8 -> 0.060991936 | G21: =E21/$E$22-1 -> 0.95674445
A22: Lump sum at $838 | B22: =Assumptions!B5 -> 900 | C22: =Assumptions!B5 -> 900 | D22: =C22/B22-1 -> 0 | E22: =$B$7/Assumptions!B5 -> 35.222222 | F22: =E22/$B$8 -> 0.031170108 | G22: =E22/$E$22-1 -> 0
A24: Spreading the same budget across bands retires materially more shares. That is the math working in your favour.
A26: 4. Implied Price by Scenario — With Banded Purchases Applied
A27: Adjusted price = (prior implied price x prior share count - budget) / (prior share count - shares bought)
A28: Scenarios | B28: Before buyback | C28: Lump sum at $838 | D28: Allocation A applied | E28: Allocation B applied | F28: A vs lump sum | G28: A vs before buyback
A29: Bull | B29: =Scenarios!I5 -> 2173.9454 | C29: =(B29*$B$8-$B$7)/($B$8-$E$22) -> 2214.932 | D29: =(B29*$B$8-$B$7)/($B$8-$E$20) -> 2289.6881 | E29: =(B29*$B$8-$B$7)/($B$8-$E$21) -> 2285.2757 | F29: =D29/C29-1 -> 0.033750973 | G29: =D29/B29-1 -> 0.05324084
A30: Base | B30: =Scenarios!I6 -> 1541.6583 | C30: =(B30*$B$8-$B$7)/($B$8-$E$22) -> 1562.3024 | D30: =(B30*$B$8-$B$7)/($B$8-$E$20) -> 1615.0316 | E30: =(B30*$B$8-$B$7)/($B$8-$E$21) -> 1611.9193 | F30: =D30/C30-1 -> 0.033750973 | G30: =D30/B30-1 -> 0.047593724
A31: Bear | B31: =Scenarios!I7 -> 399.71553 | C31: =(B31*$B$8-$B$7)/($B$8-$E$22) -> 383.61991 | D31: =(B31*$B$8-$B$7)/($B$8-$E$20) -> 396.56746 | E31: =(B31*$B$8-$B$7)/($B$8-$E$21) -> 395.80324 | F31: =D31/C31-1 -> 0.033750973 | G31: =D31/B31-1 -> -0.0078757963
A33: 5. Warning — Key Point 2: The Math That Works Against You, Regime Consistency
A34: In a world where the share price falls 80% from the peak, intrinsic value has collapsed alongside it.
A35: Reaching the -80% band at $251 means the bear case has been realized, and intrinsic value is then the bear figure of $217, not the bull figure of $1,637.
A36: Buying cheaply at -80% may therefore be an illusion, because the reason the price got there is the value destruction itself.
A38: Band | B38: Purchase price | C38: Corresponding regime | D38: Intrinsic value in that regime | E38: Margin over purchase price | F38: Verdict
A39: -30% ($878) | B39: =C12 -> 878.5 | C39: Base to bull regime holds | D39: =Scenarios!I6 -> 1541.6583 | E39: =D39/B39-1 -> 0.75487572 | F39: =IF(D39>B39,"Value created","Value destroyed - looks cheap but is not") -> Value created
A40: -50% ($628) | B40: =C13 -> 627.5 | C40: Lower end of the base case | D40: =Scenarios!I6 -> 1541.6583 | E40: =D40/B40-1 -> 1.456826 | F40: =IF(D40>B40,"Value created","Value destroyed - looks cheap but is not") -> Value created
A41: -80% ($251) | B41: =C14 -> 251 | C41: Bear case realized | D41: =Scenarios!I7 -> 399.71553 | E41: =D41/B41-1 -> 0.59249217 | F41: =IF(D41>B41,"Value created","Value destroyed - looks cheap but is not") -> Value created
A43: The genuinely attractive zone is where price has fallen but intrinsic value has not. The -50% band is a candidate; -80% usually is not.
A45: 6. Applying Reach Probabilities — What Can Actually Be Deployed
A46: Band | B46: Planned allocation A | C46: Probability of reaching | D46: Expected deployment | E46: Expected shares bought | F46: Undeployed balance
A47: =A12 -> Shallow correction | B47: =$B$7*D12 -> 10566.667 | C47: =H12 -> 1 | D47: =B47*C47 -> 10566.667 | E47: =D47/C12 -> 12.028078 | F47: =B47-D47 -> 0
A48: Note (2026-07-31): The total budget in B7 (BofA $31.7B) may differ from the cumulative buyback assumption in ROE_Build B33:E33. Align them to run a single consistent scenario. | B48: =$B$7*D13 -> 10566.667 | C48: =H13 -> 0.5 | D48: =B48*C48 -> 5283.3333 | E48: =D48/C13 -> 8.4196547 | F48: =B48-D48 -> 5283.3333
A49: =A14 -> Extreme (bear case realized) | B49: =$B$7*D14 -> 10566.667 | C49: =H14 -> 0.15 | D49: =B49*C49 -> 1585 | E49: =D49/C14 -> 6.314741 | F49: =B49-D49 -> 8981.6667
A50: Total | B50: =SUM(B47:B49) -> 31700 | D50: =SUM(D47:D49) -> 17435 | E50: =SUM(E47:E49) -> 26.762474 | F50: =SUM(F47:F49) -> 14265
A51: ="Of the planned budget of "&TEXT(B50,"#,##0")&", the probability-weighted expected deployment is "&TEXT(D50,"#,##0")&" million. The remaining "&TEXT(F50,"#,##0")&" goes undeployed because those bands are never reached." -> Of the planned budget of 31,700, the probability-weighted expected deployment is 17,435 million. The remaining 14,265 goes undeployed because those bands are never reached.
A52: Note: The undeployed balance either stays in cash or is reallocated to the higher bands. Assuming the latter raises the effective purchase price.
A53: Note: The share price is already 33% below the peak, so the -30% band is effectively reached and its probability is set to 100%.
A55: 7. Conclusion
A56: 1. Banded purchases retire more shares for the same budget because the effective price is a harmonic mean. That is unambiguously favourable.
A57: 2. But the deeper the band, the more the reason for reaching it - impaired intrinsic value - comes with it. At -80% the shares are usually not cheap; the value is gone.
A58: 3. The practically useful zone is where price has fallen by roughly the cycle average while the structure remains intact - broadly the -40% to -60% band.
A59: 4. Whether the company actually executes with this discipline is a separate question. Micron has bought back stock at prior cycle peaks.
A60: 5. This tab evaluates the company’s buyback strategy. It is a different question from an individual investor’s own averaging-in plan.

Sheet RIM_3Stage
A1: (10) Three-Stage Residual Income Model (RIM) — Explicit Discount Rate by Period
A2: V0 = B0 + sum of RIt / cumulative discount factor + terminal value / cumulative discount factor. RIt = EPSt - rt x Bt-1
A4: 1. Inputs — Edit the Yellow Cells
A5: Current share price | B5: =Assumptions!B5 -> 900 | C5: To use the Finviz Jul 28 close of $820.53, edit Assumptions B5
A6: B0 - FY2025 actual BPS | B6: =Consensus!C24 -> 48.4 | C6: A confirmed actual. The starting point of the model.
A7: [*] Stage 1 discount rate (FY2026-28) | B7: =DiscountRate!D26 -> 0.12002167 | C7: Derived on the DiscountRate tab (CAPM build-up plus stage adjustment)
A8: [*] Stage 2 discount rate (FY2029) | B8: =DiscountRate!D27 -> 0.17000346 | C8: Derived on the DiscountRate tab
A9: [*] Terminal discount rate | B9: =DiscountRate!D28 -> 0.16000346 | C9: Derived on the DiscountRate tab. [*] Still dominates the result.
A10: [*] Terminal ROE | B10: =TerminalROE!B27 -> 0.25277673 | C10: [*] Derived on the TerminalROE tab; manual entry retired. Overwrite this cell with a number to set it directly.
A11: [*] Terminal growth rate g | B11: 0.04 | C11: [*] Must stay below the terminal discount rate
A12: =IF(B9<=B11,"Error: terminal discount rate is not above the growth rate","OK - terminal discount rate exceeds growth rate") -> OK - terminal discount rate exceeds growth rate
A14: 2. Residual Income and Present Value by Year
A15: Item | B15: FY2026(E) | C15: FY2027(E) | D15: FY2028(E) | E15: FY2029(E)
A16: Opening equity Bt-1 | B16: =$B$6 -> 48.4 | C16: =B23 -> 118.72 | D16: =C23 -> 259.02 | E16: =D23 -> 437.94
A17: EPS (consensus median) | B17: =Consensus!D18 -> 73.13 | C17: =Consensus!E18 -> 154.66 | D17: =Consensus!F18 -> 170.38 | E17: =Consensus!G18 -> 141.59
A18: Applied discount rate rt | B18: =$B$7 -> 0.12002167 | C18: =$B$7 -> 0.12002167 | D18: =$B$7 -> 0.12002167 | E18: =$B$8 -> 0.17000346
A19: Equity charge = Bt-1 x rt | B19: =B16*B18 -> 5.8090486 | C19: =C16*C18 -> 14.248972 | D19: =D16*D18 -> 31.088012 | E19: =E16*E18 -> 74.451313
A20: Residual income RIt | B20: =B17-B19 -> 67.320951 | C20: =C17-C19 -> 140.41103 | D20: =D17-D19 -> 139.29199 | E20: =E17-E19 -> 67.138687
A21: Cumulative discount factor | B21: =1/(1+B18) -> 0.89283987 | C21: =B21/(1+C18) -> 0.79716304 | D21: =C21/(1+D18) -> 0.71173894 | E21: =D21/(1+E18) -> 0.60832209
A22: PV of residual income | B22: =B20*B21 -> 60.10683 | C22: =C20*C21 -> 111.93048 | D22: =D20*D21 -> 99.139532 | E22: =E20*E21 -> 40.841946
A23: Closing equity BPS (consensus) | B23: =Consensus!D24 -> 118.72 | C23: =Consensus!E24 -> 259.02 | D23: =Consensus!F24 -> 437.94 | E23: =Consensus!G24 -> 643.7
A25: 3. Value Build-up (as of today)
A26: B0 (FY2025 actual book value) | B26: =B6 -> 48.4 | C26: Starting point
A27: Plus total PV of residual income | B27: =SUM(B22:E22) -> 312.01879 | C27: Four years, FY2026-2029
A28: Terminal residual income | B28: =($B$10-$B$9)*E23 -> 59.718158 | C28: (terminal ROE - terminal discount rate) x FY2029 BPS
A29: Terminal value | B29: =IF($B$9<=$B$11,"Error",B28/($B$9-$B$11)) -> 497.63698 | C29: Terminal RI / (terminal discount rate - g)
A30: Plus PV of terminal value | B30: =B29*E21 -> 302.72357 | C30: Applying the FY2029 discount factor
A31: Intrinsic value V0 (today) | B31: =B26+B27+B30 -> 663.14236 | C31: [*] The price that can be paid today
A32: Current share price | B32: =B5 -> 900
A33: Gap | B33: =B31/B32-1 -> -0.26317516 | C33: Positive means undervalued
A35: 4. [*] Guarding Against Timing Confusion — an FY2028 Value Is Not a Today Value
A36: The PB_ROE_Model tab multiplies FY2028 book value by a multiple, producing a value dated FY2028. That must not be compared directly with today’s share price.
A37: Implied price from PB_ROE_Model (dated FY2028) | B37: =PB_ROE_Model!B13 -> 1094.85 | C37: A value three years out
A38: Discounted to today (stage 1 rate, three years) | B38: =B37/(1+B7)^3 -> 779.24738 | C38: FY2028 value / (1 + r1)^3
A39: Price required in three years to justify buying today | B39: =B5*(1+B7)^3 -> 1264.5086 | C39: Buying today at the required return implies this price
A40: Annualized return if the PB model value is realized | B40: =(B37/B5)^(1/3)-1 -> 0.067506933 | C40: If this falls below the stage 1 discount rate, the case does not clear the hurdle
A41: =IF(B40<B7,"Warning: the annualized return ("&TEXT(B40,"0.0%")&") is below the required return ("&TEXT(B7,"0.0%")&") - the PB model value does not justify the current price","OK - the annualized return exceeds the required return") -> Warning: the annualized return (6.8%) is below the required return (12.0%) - the PB model value does not justify the current price
A43: 5. Sensitivity — Intrinsic Value V0 (rows: terminal ROE / columns: terminal discount rate)
A44: Terminal ROE \ Discount rate | B44: 0.12 | C44: 0.14 | D44: 0.16 | E44: 0.18 | F44: 0.2
A45: 0.1 | B45: =IF(B$44<=$B$11,"n/a",$B$26+$B$27+(($A45-B$44)*$E$23/(B$44-$B$11))*$E$21) -> 262.52456 | C45: =IF(C$44<=$B$11,"n/a",$B$26+$B$27+(($A45-C$44)*$E$23/(C$44-$B$11))*$E$21) -> 203.78802 | D45: =IF(D$44<=$B$11,"n/a",$B$26+$B$27+(($A45-D$44)*$E$23/(D$44-$B$11))*$E$21) -> 164.63033 | E45: =IF(E$44<=$B$11,"n/a",$B$26+$B$27+(($A45-E$44)*$E$23/(E$44-$B$11))*$E$21) -> 136.66055 | F45: =IF(F$44<=$B$11,"n/a",$B$26+$B$27+(($A45-F$44)*$E$23/(F$44-$B$11))*$E$21) -> 115.68321
A46: 0.15 | B46: =IF(B$44<=$B$11,"n/a",$B$26+$B$27+(($A46-B$44)*$E$23/(B$44-$B$11))*$E$21) -> 507.26014 | C46: =IF(C$44<=$B$11,"n/a",$B$26+$B$27+(($A46-C$44)*$E$23/(C$44-$B$11))*$E$21) -> 399.57648 | D46: =IF(D$44<=$B$11,"n/a",$B$26+$B$27+(($A46-D$44)*$E$23/(D$44-$B$11))*$E$21) -> 327.78738 | E46: =IF(E$44<=$B$11,"n/a",$B$26+$B$27+(($A46-E$44)*$E$23/(E$44-$B$11))*$E$21) -> 276.50945 | F46: =IF(F$44<=$B$11,"n/a",$B$26+$B$27+(($A46-F$44)*$E$23/(F$44-$B$11))*$E$21) -> 238.051
A47: 0.2 | B47: =IF(B$44<=$B$11,"n/a",$B$26+$B$27+(($A47-B$44)*$E$23/(B$44-$B$11))*$E$21) -> 751.99572 | C47: =IF(C$44<=$B$11,"n/a",$B$26+$B$27+(($A47-C$44)*$E$23/(C$44-$B$11))*$E$21) -> 595.36495 | D47: =IF(D$44<=$B$11,"n/a",$B$26+$B$27+(($A47-D$44)*$E$23/(D$44-$B$11))*$E$21) -> 490.94443 | E47: =IF(E$44<=$B$11,"n/a",$B$26+$B$27+(($A47-E$44)*$E$23/(E$44-$B$11))*$E$21) -> 416.35835 | F47: =IF(F$44<=$B$11,"n/a",$B$26+$B$27+(($A47-F$44)*$E$23/(F$44-$B$11))*$E$21) -> 360.41879
A48: 0.25 | B48: =IF(B$44<=$B$11,"n/a",$B$26+$B$27+(($A48-B$44)*$E$23/(B$44-$B$11))*$E$21) -> 996.7313 | C48: =IF(C$44<=$B$11,"n/a",$B$26+$B$27+(($A48-C$44)*$E$23/(C$44-$B$11))*$E$21) -> 791.15341 | D48: =IF(D$44<=$B$11,"n/a",$B$26+$B$27+(($A48-D$44)*$E$23/(D$44-$B$11))*$E$21) -> 654.10148 | E48: =IF(E$44<=$B$11,"n/a",$B$26+$B$27+(($A48-E$44)*$E$23/(E$44-$B$11))*$E$21) -> 556.20725 | F48: =IF(F$44<=$B$11,"n/a",$B$26+$B$27+(($A48-F$44)*$E$23/(F$44-$B$11))*$E$21) -> 482.78658
A49: 0.3 | B49: =IF(B$44<=$B$11,"n/a",$B$26+$B$27+(($A49-B$44)*$E$23/(B$44-$B$11))*$E$21) -> 1241.4669 | C49: =IF(C$44<=$B$11,"n/a",$B$26+$B$27+(($A49-C$44)*$E$23/(C$44-$B$11))*$E$21) -> 986.94187 | D49: =IF(D$44<=$B$11,"n/a",$B$26+$B$27+(($A49-D$44)*$E$23/(D$44-$B$11))*$E$21) -> 817.25854 | E49: =IF(E$44<=$B$11,"n/a",$B$26+$B$27+(($A49-E$44)*$E$23/(E$44-$B$11))*$E$21) -> 696.05616 | F49: =IF(F$44<=$B$11,"n/a",$B$26+$B$27+(($A49-F$44)*$E$23/(F$44-$B$11))*$E$21) -> 605.15437
A50: 0.4 | B50: =IF(B$44<=$B$11,"n/a",$B$26+$B$27+(($A50-B$44)*$E$23/(B$44-$B$11))*$E$21) -> 1730.938 | C50: =IF(C$44<=$B$11,"n/a",$B$26+$B$27+(($A50-C$44)*$E$23/(C$44-$B$11))*$E$21) -> 1378.5188 | D50: =IF(D$44<=$B$11,"n/a",$B$26+$B$27+(($A50-D$44)*$E$23/(D$44-$B$11))*$E$21) -> 1143.5726 | E50: =IF(E$44<=$B$11,"n/a",$B$26+$B$27+(($A50-E$44)*$E$23/(E$44-$B$11))*$E$21) -> 975.75396 | F50: =IF(F$44<=$B$11,"n/a",$B$26+$B$27+(($A50-F$44)*$E$23/(F$44-$B$11))*$E$21) -> 849.88995
A51: 0.5 | B51: =IF(B$44<=$B$11,"n/a",$B$26+$B$27+(($A51-B$44)*$E$23/(B$44-$B$11))*$E$21) -> 2220.4092 | C51: =IF(C$44<=$B$11,"n/a",$B$26+$B$27+(($A51-C$44)*$E$23/(C$44-$B$11))*$E$21) -> 1770.0957 | D51: =IF(D$44<=$B$11,"n/a",$B$26+$B$27+(($A51-D$44)*$E$23/(D$44-$B$11))*$E$21) -> 1469.8867 | E51: =IF(E$44<=$B$11,"n/a",$B$26+$B$27+(($A51-E$44)*$E$23/(E$44-$B$11))*$E$21) -> 1255.4518 | F51: =IF(F$44<=$B$11,"n/a",$B$26+$B$27+(($A51-F$44)*$E$23/(F$44-$B$11))*$E$21) -> 1094.6255
A53: The cell closest to the current price is the terminal ROE and discount rate combination the market assumes.
A54: Note: Micron actual ROE averaged 7.8% over five years with a peak of 18.5%. Consensus is 44.9% for FY2028 and 29.6% for FY2029.
A56: 6. Strengths and Limits of This Model
A57: Strength 1: Explicit discount rates by period reflect Micron’s actual risk shape - near-term visibility, far-term uncertainty.
A58: Strength 2: Everything is discounted to today, so mixing an FY2028 value with a present value cannot happen by construction.
A59: Strength 3: B0 is a confirmed actual (FY2025 BPS), so reliance on estimates is lower than in the P/B model.
A60: Limit 1: The terminal still dominates. Intrinsic value varies threefold between a terminal ROE of 15% and 30%.
A61: Limit 2: It takes consensus EPS and BPS as given. If the SK hynix ASP slowdown drags estimates down, this must be recalculated.
A62: Limit 3: Buyback effects are not reflected here (see the Buybacks tab). A large repurchase changes the BPS path.
A64: 7. Substituting Consensus Values for Terminal ROE (terminal discount rate from B9)
A65: Consensus ROE is calculated on average equity while the RIM terminal formula uses opening equity, so there is a small difference. Read this directionally.
A66: Source of terminal ROE | B66: ROE | C66: Terminal RI | D66: Terminal value | E66: Present value | F66: Intrinsic value V0 | G66: vs current price
A67: FY2026 consensus median | B67: =Consensus!D27 -> 0.844 | C67: =(B67-$B$9)*$E$23 -> 440.28858 | D67: =IF($B$9<=$B$11,"n/a",C67/($B$9-$B$11)) -> 3668.9658 | E67: =D67*$E$21 -> 2231.9129 | F67: =$B$26+$B$27+E67 -> 2592.3317 | G67: =F67/$B$5-1 -> 1.8803686
A68: FY2027 consensus median | B68: =Consensus!E27 -> 0.7384 | C68: =(B68-$B$9)*$E$23 -> 372.31386 | D68: =IF($B$9<=$B$11,"n/a",C68/($B$9-$B$11)) -> 3102.5261 | E68: =D68*$E$21 -> 1887.3352 | F68: =$B$26+$B$27+E68 -> 2247.754 | G68: =F68/$B$5-1 -> 1.4975044
A69: FY2028 consensus median | B69: =Consensus!F27 -> 0.4486 | C69: =(B69-$B$9)*$E$23 -> 185.7696 | D69: =IF($B$9<=$B$11,"n/a",C69/($B$9-$B$11)) -> 1548.0354 | E69: =D69*$E$21 -> 941.70411 | F69: =$B$26+$B$27+E69 -> 1302.1229 | G69: =F69/$B$5-1 -> 0.44680323
A70: FY2029 consensus median | B70: =Consensus!G27 -> 0.296 | C70: =(B70-$B$9)*$E$23 -> 87.540976 | D70: =IF($B$9<=$B$11,"n/a",C70/($B$9-$B$11)) -> 729.48712 | E70: =D70*$E$21 -> 443.76313 | F70: =$B$26+$B$27+E70 -> 804.18192 | G70: =F70/$B$5-1 -> -0.10646454
A71: FY2028 consensus low | B71: =Consensus!F28 -> 0.243 | C71: =(B71-$B$9)*$E$23 -> 53.424876 | D71: =IF($B$9<=$B$11,"n/a",C71/($B$9-$B$11)) -> 445.19448 | E71: =D71*$E$21 -> 270.82163 | F71: =$B$26+$B$27+E71 -> 631.24042 | G71: =F71/$B$5-1 -> -0.29862175
A72: FY2029 consensus low | B72: =Consensus!G28 -> 0.148 | C72: =(B72-$B$9)*$E$23 -> -7.7266244 | D72: =IF($B$9<=$B$11,"n/a",C72/($B$9-$B$11)) -> -64.386683 | E72: =D72*$E$21 -> -39.167841 | F72: =$B$26+$B$27+E72 -> 321.25095 | G72: =F72/$B$5-1 -> -0.6430545
A73: Five-year actual average | B73: =HistoricalCycle!H11 -> 0.0782 | C73: =(B73-$B$9)*$E$23 -> -52.656884 | D73: =IF($B$9<=$B$11,"n/a",C73/($B$9-$B$11)) -> -438.79473 | E73: =D73*$E$21 -> -266.92853 | F73: =$B$26+$B$27+E73 -> 93.490261 | G73: =F73/$B$5-1 -> -0.89612193
A74: Five-year actual peak (FY2022) | B74: =HistoricalCycle!C11 -> 0.1851 | C74: =(B74-$B$9)*$E$23 -> 16.154646 | D74: =IF($B$9<=$B$11,"n/a",C74/($B$9-$B$11)) -> 134.61817 | E74: =D74*$E$21 -> 81.891206 | F74: =$B$26+$B$27+E74 -> 442.31 | G74: =F74/$B$5-1 -> -0.50854445
A76: ="Using the FY2029 consensus median of 29.6% as the terminal ROE gives an intrinsic value of "&TEXT(F70,"$#,##0")&", against a current price of "&TEXT(B5,"$#,##0")&" - almost identical." -> Using the FY2029 consensus median of 29.6% as the terminal ROE gives an intrinsic value of $804, against a current price of $900 - almost identical.
A77: In other words the market is pricing in the full consensus earnings path, a terminal ROE fixed at the final consensus year, and a 16% terminal discount rate.
A78: Capitalizing the FY2028 figure of 44.9% in perpetuity shows deep undervaluation, but consensus itself fades to 29.6% by FY2029. Citing consensus while ignoring that fade is inconsistent.
A79: Note: Using the five-year actual average of 7.8% turns terminal residual income negative and collapses intrinsic value. That is the numerical expression of memory historically failing to earn its cost of capital.
A81: 8. Estimate Counts — How Far Out Can Consensus Be Trusted
A82: Item | B82: FY2026 | C82: FY2027 | D82: FY2028 | E82: FY2029 | F82: Note
A83: Revenue estimate count | B83: =Consensus!D7 -> 45 | C83: =Consensus!E7 -> 46 | D83: =Consensus!F7 -> 31 | E83: =Consensus!G7 -> 5
A84: Net income estimate count | B84: =Consensus!D17 -> 39 | C84: =Consensus!E17 -> 39 | D84: =Consensus!F17 -> 26 | E84: =Consensus!G17 -> 3
A85: EPS estimate count | B85: =Consensus!D19 -> 47 | C85: =Consensus!E19 -> 47 | D85: =Consensus!F19 -> 31 | E85: =Consensus!G19 -> 4 | F85: Input to the RIM residual income calculation
A86: BPS estimate count | B86: =Consensus!D25 -> 16 | C86: =Consensus!E25 -> 16 | D86: =Consensus!F25 -> 12 | E86: =Consensus!G25 -> 2 | F86: [*] Terminal base equity - the most important one
A87: ROE estimate count | B87: - | C87: - | D87: - | E87: - | F87: FY26: 22, FY27: 21, FY28: 16, FY29: 3
A88: For FY2029 there are 5 revenue estimates, 3 for net income, 4 for EPS, 2 for BPS and 3 for ROE. That is effectively a minority view.
A89: Even FY2028 has only 12 BPS estimates and 16 for ROE. The denominator behind the 1.91x forward P/B rests on twelve analysts.
A91: 9. Version Excluding FY2029 — Ending the Explicit Forecast at FY2028
A92: If FY2029 data (2 BPS estimates, 3 for ROE) is not trustworthy, cut at FY2028 and use that equity as the terminal base.
A93: B0 (FY2025 actual) | B93: =B6 -> 48.4 | C93: Unchanged
A94: Plus PV of residual income (FY2026-28 only) | B94: =SUM(B22:D22) -> 271.17684 | C94: Excluding FY2029 lowers the total
A95: Terminal base equity (FY2028 BPS) | B95: =D23 -> 437.94 | C95: Falls from $643.70 to $437.94
A96: Applied discount factor (to FY2028) | B96: =D21 -> 0.71173894 | C96: Rises from 0.6084 to 0.7118
A97: [*] Terminal ROE | B97: 0.296 | C97: [*] Input cell. Default is the FY2029 consensus of 29.6%.
A98: Terminal RI | B98: =(B97-$B$9)*B95 -> 59.558327 | C98: (terminal ROE - terminal discount rate) x FY2028 BPS
A99: Terminal value | B99: =IF($B$9<=$B$11,"Error",B98/($B$9-$B$11)) -> 496.3051
A100: Plus PV of terminal value | B100: =B99*B96 -> 353.23966
A101: Intrinsic value V0 (truncated at FY2028) | B101: =B93+B94+B100 -> 672.81651 | C101: [*] Result
A102: vs current price | B102: =B101/$B$5-1 -> -0.2524261
A103: Reference: version including FY2029 | B103: =B31 -> 663.14236 | C103: Result from section 3
A104: Difference (truncated less full) | B104: =B101-B103 -> 9.6741515 | C104: Negative means truncation is the more conservative choice
A106: 10. Truncated Version Sensitivity — by Terminal ROE (discount rate from B9)
A107: Terminal ROE | B107: Source | C107: Terminal RI | D107: Intrinsic value V0 (truncated at FY2028) | E107: vs current price | F107: Difference versus the version including FY2029
A108: 0.449 | B108: FY2028 consensus median (16 estimates) | C108: =(A108-$B$9)*$D$23 -> 126.56315 | D108: =IF($B$9<=$B$11,"n/a",$B$93+$B$94+(C108/($B$9-$B$11))*$D$21) -> 1070.2212 | E108: =D108/$B$5-1 -> 0.1891347 | F108: =D108-($B$26+$B$27+((A108-$B$9)*$E$23/($B$9-$B$11))*$E$21) -> -233.20689
A109: 0.36 | B109: The level implied by the current price | C109: =(A109-$B$9)*$D$23 -> 87.586487 | D109: =IF($B$9<=$B$11,"n/a",$B$93+$B$94+(C109/($B$9-$B$11))*$D$21) -> 839.05116 | E109: =D109/$B$5-1 -> -0.06772093 | F109: =D109-($B$26+$B$27+((A109-$B$9)*$E$23/($B$9-$B$11))*$E$21) -> -173.96577
A110: 0.296 | B110: FY2029 consensus median (3 estimates) | C110: =(A110-$B$9)*$D$23 -> 59.558327 | D110: =IF($B$9<=$B$11,"n/a",$B$93+$B$94+(C110/($B$9-$B$11))*$D$21) -> 672.81651 | E110: =D110/$B$5-1 -> -0.2524261 | F110: =D110-($B$26+$B$27+((A110-$B$9)*$E$23/($B$9-$B$11))*$E$21) -> -131.36541
A111: 0.243 | B111: FY2028 consensus low | C111: =(A111-$B$9)*$D$23 -> 36.347507 | D111: =IF($B$9<=$B$11,"n/a",$B$93+$B$94+(C111/($B$9-$B$11))*$D$21) -> 535.15344 | E111: =D111/$B$5-1 -> -0.40538507 | F111: =D111-($B$26+$B$27+((A111-$B$9)*$E$23/($B$9-$B$11))*$E$21) -> -96.086987
A112: 0.185 | B112: Five-year actual peak (FY2022) | C112: =(A112-$B$9)*$D$23 -> 10.946987 | D112: =IF($B$9<=$B$11,"n/a",$B$93+$B$94+(C112/($B$9-$B$11))*$D$21) -> 384.50328 | E112: =D112/$B$5-1 -> -0.57277413 | F112: =D112-($B$26+$B$27+((A112-$B$9)*$E$23/($B$9-$B$11))*$E$21) -> -57.480411
...

Sheet TargetPriceCheck
A1: (11) Feasibility of Analyst Price Targets — Factor Decomposition
A3: 1. Back-solving What Each Target Requires
A4: Analyst | B4: Price target | C4: Date published | D4: FY27 P/B | E4: FY28 P/B | F4: Average FY26-27 P/E | G4: Required terminal ROE at 16% | H4: Required terminal ROE at 12% | I4: vs current price
A5: Cantor Fitzgerald | B5: 2000 | C5: 2026-06-29 | D5: =B5/Consensus!$E$24 -> 7.7214115 | E5: =B5/Consensus!$F$24 -> 4.5668356 | F5: =B5/((Consensus!$D$18+Consensus!$E$18)/2) -> 17.560033 | G5: =((B5-RIM_3Stage!$B$129)/RIM_3Stage!$B$128)*(0.16-0.04)/RIM_3Stage!$B$127+0.16 -> 0.80694083 | H5: =((B5-RIM_3Stage!$B$129)/RIM_3Stage!$B$128)*(0.12-0.04)/RIM_3Stage!$B$127+0.12 -> 0.55129389 | I5: =B5/Assumptions!$B$5-1 -> 1.2222222
A6: Barclays | B6: 2000 | C6: 2026-06-26 | D6: =B6/Consensus!$E$24 -> 7.7214115 | E6: =B6/Consensus!$F$24 -> 4.5668356 | F6: =B6/((Consensus!$D$18+Consensus!$E$18)/2) -> 17.560033 | G6: =((B6-RIM_3Stage!$B$129)/RIM_3Stage!$B$128)*(0.16-0.04)/RIM_3Stage!$B$127+0.16 -> 0.80694083 | H6: =((B6-RIM_3Stage!$B$129)/RIM_3Stage!$B$128)*(0.12-0.04)/RIM_3Stage!$B$127+0.12 -> 0.55129389 | I6: =B6/Assumptions!$B$5-1 -> 1.2222222
A7: Needham | B7: 1650 | C7: 2026-06-26 | D7: =B7/Consensus!$E$24 -> 6.3701645 | E7: =B7/Consensus!$F$24 -> 3.7676394 | F7: =B7/((Consensus!$D$18+Consensus!$E$18)/2) -> 14.487028 | G7: =((B7-RIM_3Stage!$B$129)/RIM_3Stage!$B$128)*(0.16-0.04)/RIM_3Stage!$B$127+0.16 -> 0.67219543 | H7: =((B7-RIM_3Stage!$B$129)/RIM_3Stage!$B$128)*(0.12-0.04)/RIM_3Stage!$B$127+0.12 -> 0.46146362 | I7: =B7/Assumptions!$B$5-1 -> 0.83333333
A8: UBS | B8: 1625 | C8: 2026-05-27 | D8: =B8/Consensus!$E$24 -> 6.2736468 | E8: =B8/Consensus!$F$24 -> 3.710554 | F8: =B8/((Consensus!$D$18+Consensus!$E$18)/2) -> 14.267527 | G8: =((B8-RIM_3Stage!$B$129)/RIM_3Stage!$B$128)*(0.16-0.04)/RIM_3Stage!$B$127+0.16 -> 0.66257076 | H8: =((B8-RIM_3Stage!$B$129)/RIM_3Stage!$B$128)*(0.12-0.04)/RIM_3Stage!$B$127+0.12 -> 0.45504717 | I8: =B8/Assumptions!$B$5-1 -> 0.80555556
A9: TD Cowen | B9: 1600 | C9: 2026-06-25 | D9: =B9/Consensus!$E$24 -> 6.1771292 | E9: =B9/Consensus!$F$24 -> 3.6534685 | F9: =B9/((Consensus!$D$18+Consensus!$E$18)/2) -> 14.048027 | G9: =((B9-RIM_3Stage!$B$129)/RIM_3Stage!$B$128)*(0.16-0.04)/RIM_3Stage!$B$127+0.16 -> 0.65294609 | H9: =((B9-RIM_3Stage!$B$129)/RIM_3Stage!$B$128)*(0.12-0.04)/RIM_3Stage!$B$127+0.12 -> 0.44863072 | I9: =B9/Assumptions!$B$5-1 -> 0.77777778
A10: Wells Fargo | B10: 1525 | C10: 2026-06-25 | D10: =B10/Consensus!$E$24 -> 5.8875762 | E10: =B10/Consensus!$F$24 -> 3.4822122 | F10: =B10/((Consensus!$D$18+Consensus!$E$18)/2) -> 13.389525 | G10: =((B10-RIM_3Stage!$B$129)/RIM_3Stage!$B$128)*(0.16-0.04)/RIM_3Stage!$B$127+0.16 -> 0.62407207 | H10: =((B10-RIM_3Stage!$B$129)/RIM_3Stage!$B$128)*(0.12-0.04)/RIM_3Stage!$B$127+0.12 -> 0.42938138 | I10: =B10/Assumptions!$B$5-1 -> 0.69444444
A11: Rosenblatt | B11: 1500 | C11: 2026-06-26 | D11: =B11/Consensus!$E$24 -> 5.7910586 | E11: =B11/Consensus!$F$24 -> 3.4251267 | F11: =B11/((Consensus!$D$18+Consensus!$E$18)/2) -> 13.170025 | G11: =((B11-RIM_3Stage!$B$129)/RIM_3Stage!$B$128)*(0.16-0.04)/RIM_3Stage!$B$127+0.16 -> 0.6144474 | H11: =((B11-RIM_3Stage!$B$129)/RIM_3Stage!$B$128)*(0.12-0.04)/RIM_3Stage!$B$127+0.12 -> 0.42296493 | I11: =B11/Assumptions!$B$5-1 -> 0.66666667
A12: Citigroup | B12: 1400 | C12: 2026-06-25 | D12: =B12/Consensus!$E$24 -> 5.404988 | E12: =B12/Consensus!$F$24 -> 3.1967849 | F12: =B12/((Consensus!$D$18+Consensus!$E$18)/2) -> 12.292023 | G12: =((B12-RIM_3Stage!$B$129)/RIM_3Stage!$B$128)*(0.16-0.04)/RIM_3Stage!$B$127+0.16 -> 0.57594871 | H12: =((B12-RIM_3Stage!$B$129)/RIM_3Stage!$B$128)*(0.12-0.04)/RIM_3Stage!$B$127+0.12 -> 0.39729914 | I12: =B12/Assumptions!$B$5-1 -> 0.55555556
A13: Wolfe Research | B13: 1250 | C13: 2026-06-11 | D13: =B13/Consensus!$E$24 -> 4.8258822 | E13: =B13/Consensus!$F$24 -> 2.8542723 | F13: =B13/((Consensus!$D$18+Consensus!$E$18)/2) -> 10.975021 | G13: =((B13-RIM_3Stage!$B$129)/RIM_3Stage!$B$128)*(0.16-0.04)/RIM_3Stage!$B$127+0.16 -> 0.51820069 | H13: =((B13-RIM_3Stage!$B$129)/RIM_3Stage!$B$128)*(0.12-0.04)/RIM_3Stage!$B$127+0.12 -> 0.35880046 | I13: =B13/Assumptions!$B$5-1 -> 0.38888889
A14: Piper Sandler | B14: 400 | C14: 2026-01-07 | D14: =B14/Consensus!$E$24 -> 1.5442823 | E14: =B14/Consensus!$F$24 -> 0.91336713 | F14: =B14/((Consensus!$D$18+Consensus!$E$18)/2) -> 3.5120067 | G14: =((B14-RIM_3Stage!$B$129)/RIM_3Stage!$B$128)*(0.16-0.04)/RIM_3Stage!$B$127+0.16 -> 0.19096186 | H14: =((B14-RIM_3Stage!$B$129)/RIM_3Stage!$B$128)*(0.12-0.04)/RIM_3Stage!$B$127+0.12 -> 0.14064124 | I14: =B14/Assumptions!$B$5-1 -> -0.55555556
A15: (Reference) 45-analyst average | B15: 1491.95 | C15: 2026-07-28 | D15: =B15/Consensus!$E$24 -> 5.7599799 | E15: =B15/Consensus!$F$24 -> 3.4067452 | F15: =B15/((Consensus!$D$18+Consensus!$E$18)/2) -> 13.099346 | G15: =((B15-RIM_3Stage!$B$129)/RIM_3Stage!$B$128)*(0.16-0.04)/RIM_3Stage!$B$127+0.16 -> 0.61134826 | H15: =((B15-RIM_3Stage!$B$129)/RIM_3Stage!$B$128)*(0.12-0.04)/RIM_3Stage!$B$127+0.12 -> 0.42089884 | I15: =B15/Assumptions!$B$5-1 -> 0.65772222
A17: Reference — historical and theoretical ceilings
A18: Five-year average P/B | D18: =HistoricalCycle!H16 -> 1.952 | E18: FY21-25 actual
A19: Five-year peak P/B | D19: =HistoricalCycle!F16 -> 2.53 | E19: FY2025
A20: BofA two-year-forward historical median | D20: 1.54 | E20: BofA report, May 29
A21: Target P/E cited by Goldman | D21: 9 | E21: Explicitly described as the average Micron upcycle multiple
A22: Top of the conservative terminal ROE band | D22: 0.3 | E22: User-set
A23: Five-year actual peak ROE | D23: =HistoricalCycle!C11 -> 0.1851 | E23: FY2022
A25: 2. Feasibility Factors — Six Tests
A26: Factor | B26: Detail | G26: Supporting figures | J26: Feasibility
A27: 1. Timing validity | B27: Nine of ten were published between May 27 and Jun 29, 2026, six of them between Jun 25 and 29 - right around the $1,255 peak on Jun 25. | G27: None reflect the July events - the CXMT listing, domestic Chinese DUV, the SK hynix miss, or KOSPI falling 44% | J27: Very low
A28: 2. Required P/B | B28: Every target requires an FY2028 P/B of 2.85-4.57x | G28: Above the five-year band of 1.26-2.53x, the 1.95x average and the BofA median of 1.54x - all of them | J28: Low
A29: 3. Required terminal ROE | B29: Requires 51.8-80.7% at a 16% discount rate, and still 35.9-55.1% at 12% | G29: Exceeds the 30% conservative band ceiling, the 18.5% historical peak and the 7.8% average | J29: Low
A30: 4. Robustness of the underlying estimates | B30: FY2028 rests on 12 BPS and 16 ROE estimates; FY2029 on 2 and 3 | G30: BPS estimates were revised up 2.6-3.2x within two months (BofA moved from 3.28x to 1.91x) | J30: Low
A31: 5. Structural lag in price targets | B31: Needham went from $500 to $1,550 on Jun 22 and to $1,650 three days later. UBS moved from $535 to $1,625, up 204%. | G31: A target is next-year EPS times a multiple, and EPS is a function of current DRAM prices - so it lags by definition | J31: Low
A32: 6. Dispersion | B32: The full range spans $400 to $2,000, a factor of five. Excluding Piper it is still $1,250 to $2,000, a factor of 1.6. | G32: Direction scores of 54-79 on the source screen - even directional accuracy is limited | J32: Low
A34: 3. Overall Verdict
A35: 1. These targets are less wrong than expired. Against the information set of late June they were internally coherent.
A36: 2. Even the lowest target, Wolfe at $1,250, requires an FY2028 P/B of 2.85x, above the five-year peak of 2.53x. Not a single target falls inside the historical band.
A37: 3. Translating into terminal ROE makes it starker. Even at a 12% discount rate - the Nomura bull assumption - $1,250 requires 35.9% and $2,000 requires 55.1% in perpetuity. Both exceed the agreed 20-30% conservative band.
A38: 4. Using these targets as support therefore requires separately defending terminal assumptions more optimistic than consensus. The targets do not do that work for you.
A39: 5. Practical conclusion: treat targets not as an answer to how high the stock goes, but as material for back-solving what would have to be true. Columns 7 and 8 above are that back-solve.
A40: 6. Piper Sandler at $400 dates from Jan 7, seven months ago. It should not be cited as the low, and by the same logic it can be set aside - a stale target is not information.
A42: Note: Targets and publication dates come from a screen supplied by the user, retrieved 2026-07-29. Overall, Direction and Price Scores are proprietary metrics of that service and their methodology has not been verified.

Sheet MixPath
A1: (12) Revenue Mix Path — From Wafer Allocation to Revenue Share
A2: Physical layer (wafer/bit) is anchored on TrendForce actuals. Price layer (ASP premium) is a [*] input lever. The 53/23/24 split is an FY2026 snapshot, not a constant.
A4: 1. Inputs — Physical Layer
A5: Item | B5: FY2026 | C5: FY2027 | D5: FY2028 | E5: FY2029 | F5: Source / Note
A6: HBM wafer input share (top 3 suppliers) | B6: 0.22 | C6: 0.3 | D6: 0.35 | E6: 0.38 | F6: FY26-27: TrendForce, Jun 2026 (18%/22%/30% for 2025/26/27). FY28-29: extrapolated [ESTIMATE]
A7: Trade ratio (wafer area per HBM bit vs commodity) | B7: 2.85 | C7: 2.87 | D7: 3 | E7: 3.1 | F7: FY26-27: back-solved from TrendForce wafer and bit shares. Reflects HBM3 3:1 to HBM4 4:1 trend [ESTIMATE]
A8: DRAM share of total revenue (vs NAND) | B8: 0.76 | C8: 0.78 | D8: 0.8 | E8: 0.8 | F8: FY2026: actual per handoff note (commodity 53% + HBM 23%). Later years assume widening DRAM share [ESTIMATE]
A10: 2. [*] ASP Premium — This Single Input Dominates the Result
A11: [*] Case selector (1/2/3) — applies from FY2027 onward | B11: 2 | F11: Three sources (TrendForce DRAM revenue, bit share, Micron HBM TAM) disagree, so this is left as a band
A12: 1 = Conservative — consistent with Micron HBM TAM guidance | B12: 0.56 | F12: HBM TAM $70B (2027 interpolated) / DRAM $903.3B = 7.8%; bit share 13% implies 0.56x
A13: 2 = Mid — partial contract price recovery | B13: 2 | F13: Assumes partial realization of TrendForce "HBM contract prices to surge multiples higher in 2027" [ESTIMATE]
A14: 3 = Status quo — back-solved from FY2026 actuals | B14: 4.39 | F14: Back-solved from Micron current mix: HBM 23% of revenue vs 9% of bits implies 4.39x
A15: Applied premium (by year) | B15: 4.39 | C15: =IF($B$11=3,$B$14,IF($B$11=2,$B$13,$B$12)) -> 2 | D15: =IF($B$11=3,$B$14,IF($B$11=2,$B$13,$B$12)) -> 2 | E15: =IF($B$11=3,$B$14,IF($B$11=2,$B$13,$B$12)) -> 2 | F15: FY2026 is fixed at the back-solved 4.39x so the actual 53/23/24 mix is always reproduced. The case selector applies from FY2027 onward.
A17: 3. Derived — Bit Share
A18: Item | B18: FY2026 | C18: FY2027 | D18: FY2028 | E18: FY2029
A19: HBM bit share = (w/k) / ((w/k) + (1-w)) | B19: =(B6/B7)/((B6/B7)+(1-B6)) -> 0.090053213 | C19: =(C6/C7)/((C6/C7)+(1-C6)) -> 0.12992638 | D19: =(D6/D7)/((D6/D7)+(1-D6)) -> 0.15217391 | E19: =(E6/E7)/((E6/E7)+(1-E6)) -> 0.16507385
A20: Check: TrendForce published bit share | B20: 0.09 | C20: 0.13 | D20: — | E20: —
A21: Difference | B21: =B19-B20 -> 5.3213262e-05 | C21: =C19-C20 -> -7.3624946e-05 | F21: Near zero means the physical-layer model reconciles with published data
A23: 4. Derived — Revenue Mix
A24: Item | B24: FY2026 | C24: FY2027 | D24: FY2028 | E24: FY2029
A25: HBM share of DRAM revenue | B25: =(B19*B15)/((B19*B15)+(1-B19)) -> 0.30287255 | C25: =(C19*C15)/((C19*C15)+(1-C19)) -> 0.22997317 | D25: =(D19*D15)/((D19*D15)+(1-D19)) -> 0.26415094 | E25: =(E19*E15)/((E19*E15)+(1-E19)) -> 0.28337062
A26: Commodity DRAM, % of total revenue | B26: =(1-B25)*B8 -> 0.52981686 | C26: =(1-C25)*C8 -> 0.60062093 | D26: =(1-D25)*D8 -> 0.58867925 | E26: =(1-E25)*E8 -> 0.5733035
A27: HBM, % of total revenue | B27: =B25*B8 -> 0.23018314 | C27: =C25*C8 -> 0.17937907 | D27: =D25*D8 -> 0.21132075 | E27: =E25*E8 -> 0.2266965
A28: NAND, % of total revenue | B28: =1-B8 -> 0.24 | C28: =1-C8 -> 0.22 | D28: =1-D8 -> 0.2 | E28: =1-E8 -> 0.2
A29: Sum check | B29: =B26+B27+B28 -> 1 | C29: =C26+C27+C28 -> 1 | D29: =D26+D27+D28 -> 1 | E29: =E26+E27+E28 -> 1
A31: 5. Check — Reconciliation to FY2026 Actual Mix (should match exactly under Case 3)
A32: Item | B32: Commodity DRAM | C32: HBM | D32: NAND
A33: FY2026 actual (handoff note, section 3.5) | B33: 0.53 | C33: 0.23 | D33: 0.24
A34: FY2026 derived (current case) | B34: =B26 -> 0.52981686 | C34: =B27 -> 0.23018314 | D34: =B28 -> 0.24
A35: Difference | B35: =B34-B33 -> -0.00018314099 | C35: =C34-C33 -> 0.00018314099 | D35: =D34-D33 -> 0 | F35: A zero difference under Case 3 (4.39x) confirms the back-solve is exact
A37: Note: The physical layer (rows 6-7) rests on TrendForce actuals and is relatively firm. The price layer (rows 11-15) is currently the most volatile variable in the industry.
A38: Note: Across a premium of 0.56x to 4.39x, HBM moves from roughly 8% to 35% of total revenue. That range is the model uncertainty.
A39: Note: Resolution point is the HBM4 annual contract price negotiation in Nov-Dec 2026. Entering the outcome in rows 11-14 recalculates every downstream tab.
A40: Sources: TrendForce press releases 2026-05-29 and 2026-06-02; Micron FY26 Q1 earnings call (Dec 2025). Not investment advice.
A41: Revision 2026-07-31: FY2026 premium fixed at 4.39x. The actual mix (53/23/24) must always be reproduced so the TTM shares on the ChinaRisk tab stay correct.

Sheet SegmentMargin
A1: (13) Segment Margins to Blended EBIT Margin [*] Cross-check 1
A2: Applies segment operating margins to the MixPath weights to derive a blended margin, then cross-checks it against consensus.
A4: 1. [*] Segment Operating Margins (OPM)
A5: Segment | B5: FY2026 | C5: FY2027 | D5: FY2028 | E5: FY2029 | F5: Basis / Note
A6: Commodity DRAM OPM | B6: =1-(1-$B$45)/B40 -> 0.8 | C6: =1-(1-$B$45)/C40 -> 0.8 | D6: =1-(1-$B$45)/D40 -> 0.77777778 | E6: =1-(1-$B$45)/E40 -> 0.67213115 | F6: Derived from (17) ASP Drivers; manual entry retired | G6: [*] Cycle path. FY26-27 is the cleanroom shortage peak (SK hynix company-wide OPM of 72% as reference). FY28 reflects new capacity landing (Micron Hiroshima, M15X, P4/P5, CXMT 600k). FY29 applies the consensus gross margin decline of -16.5%.
A7: HBM OPM | B7: =1-(1-$B$46)/B41 -> 0.5 | C7: =1-(1-$B$46)/C41 -> 0.65034965 | D7: =1-(1-$B$46)/D41 -> 0.75 | E7: =1-(1-$B$46)/E41 -> 0.72067039 | F7: Derived from (17) ASP Drivers; manual entry retired | G7: [*] Key lever. FY2026 sits below commodity due to contract lag (confirmed by Micron CEO). FY27-28 reflect contract repricing. FY29 is a modest step down.
A8: NAND OPM | B8: =1-(1-$B$47)/B42 -> 0.5 | C8: =1-(1-$B$47)/C42 -> 0.5 | D8: =1-(1-$B$47)/D42 -> 0.44444444 | E8: =1-(1-$B$47)/E42 -> 0.3902439 | F8: Derived from (17) ASP Drivers; manual entry retired | G8: TrendForce: NAND supply eases in 2027, so stepped down gradually [ESTIMATE]
A10: 2. Derived — Blended EBIT Margin
A11: Item | B11: FY2026 | C11: FY2027 | D11: FY2028 | E11: FY2029
A12: Commodity DRAM share (from MixPath) | B12: =MixPath!B26 -> 0.52981686 | C12: =MixPath!C26 -> 0.60062093 | D12: =MixPath!D26 -> 0.58867925 | E12: =MixPath!E26 -> 0.5733035
A13: HBM share (from MixPath) | B13: =MixPath!B27 -> 0.23018314 | C13: =MixPath!C27 -> 0.17937907 | D13: =MixPath!D27 -> 0.21132075 | E13: =MixPath!E27 -> 0.2266965
A14: NAND share (from MixPath) | B14: =MixPath!B28 -> 0.24 | C14: =MixPath!C28 -> 0.22 | D14: =MixPath!D28 -> 0.2 | E14: =MixPath!E28 -> 0.2
A15: Blended EBIT margin | B15: =B12*B6+B13*B7+B14*B8 -> 0.65894506 | C15: =C12*C6+C13*C7+C14*C8 -> 0.70715586 | D15: =D12*D6+D13*D7+D14*D8 -> 0.70524109 | E15: =E12*E6+E13*E7+E14*E8 -> 0.62675737
A17: 3. [*] Cross-check 1 — Consensus EBIT Margin
A18: Item | B18: FY2026 | C18: FY2027 | D18: FY2028 | E18: FY2029
A19: Consensus EBIT margin (median) | B19: =Consensus!D11 -> 0.7589 | C19: =Consensus!E11 -> 0.8233 | D19: =Consensus!F11 -> 0.7799 | E19: =Consensus!G11 -> 0.7021
A20: Derived EBIT margin | B20: =B15 -> 0.65894506 | C20: =C15 -> 0.70715586 | D20: =D15 -> 0.70524109 | E20: =E15 -> 0.62675737
A21: Implied achievement rate (derived / consensus) | B21: =IFERROR(B20/B19,"n/a") -> 0.86828971 | C21: =IFERROR(C20/C19,"n/a") -> 0.85892853 | D21: =IFERROR(D20/D19,"n/a") -> 0.90427118 | E21: =IFERROR(E20/E19,"n/a") -> 0.89268961 | F21: Feeding this into the ConsensusValuation achievement rate replaces an arbitrary haircut with a grounded one
A22: Gap (pp) | B22: =B20-B19 -> -0.099954942 | C22: =C20-C19 -> -0.11614414 | D22: =D20-D19 -> -0.07465891 | E22: =E20-E19 -> -0.075342625
A24: 4. Back-solve — What HBM OPM Would Consensus Require?
A25: Item | B25: FY2026 | C25: FY2027 | D25: FY2028 | E25: FY2029
A26: Required HBM OPM | B26: =IFERROR((B19-B12*B6-B14*B8)/B13,"n/a") -> 0.93424093 | C26: =IFERROR((C19-C12*C6-C14*C8)/C13,"n/a") -> 1.2978284 | D26: =IFERROR((D19-D12*D6-D14*D8)/D13,"n/a") -> 1.1032966 | E26: =IFERROR((E19-E12*E6-E14*E8)/E13,"n/a") -> 1.0530206
A27: Current HBM OPM input | B27: =B7 -> 0.5 | C27: =C7 -> 0.65034965 | D27: =D7 -> 0.75 | E27: =E7 -> 0.72067039
A28: Difference (pp) | B28: =IFERROR(B26-B27,"n/a") -> 0.43424093 | C28: =IFERROR(C26-C27,"n/a") -> 0.64747877 | D28: =IFERROR(D26-D27,"n/a") -> 0.35329663 | E28: =IFERROR(E26-E27,"n/a") -> 0.3323502
A30: Note: Row 26 exposes the hidden premise in consensus. The unstated assumption about how far HBM margins rise becomes visible here.
A31: Note: If the required HBM OPM exceeds 100%, or sits far above commodity OPM, consensus is not compatible with the current mix assumptions.
A32: Note: Resolution point is the HBM4 annual contract price negotiation in Nov-Dec 2026 (Goldman +44-50% vs consensus +34%).
A34: Warning: The row 26 back-solve implies an FY2027 commodity OPM above 99%. Either the consensus FY2027 EBIT margin of 82.3% is too high, or the HBM OPM assumption is too low.
A35: Note: Holding commodity OPM flat pushes the FY2029 achievement rate above 100%, making the model more optimistic than consensus. The cycle turn must be entered year by year.
A37: (17) ASP Drivers — Deriving OPM Instead of Entering It (added 2026-07-31)
A38: HBM OPM is no longer entered directly. When the HBM contract ASP rises, OPM rises with it. Under a fixed-cost structure unit cost is unchanged, so the ASP move flows straight into margin.
A39: Item | B39: FY2026 | C39: FY2027 | D39: FY2028 | E39: FY2029 | F39: Basis / Note
A40: [*] Commodity DRAM spot ASP index | B40: 1 | C40: 1 | D40: 0.9 | E40: 0.61 | F40: FY2026 = 1.0 base. FY28 reflects new capacity landing; FY29 is fitted to the consensus gross margin decline
A41: [*] HBM contract ASP index | B41: 1 | C41: 1.43 | D41: 2 | E41: 1.79 | F41: Per TrendForce, HBM contract prices surge multiples higher in 2027. FY2028 at 2.0x means double the FY2026 level [ESTIMATE]
A42: [*] NAND ASP index | B42: 1 | C42: 1 | D42: 0.9 | E42: 0.82 | F42: TrendForce: NAND supply eases in 2027 [ESTIMATE]
A44: Base OPM (at ASP index = 1.00, i.e. the FY2026 level)
A45: [*] Commodity DRAM base OPM | B45: 0.8 | F45: Stated in handoff note section 4.4 [UNVERIFIED]
A46: [*] HBM base OPM | B46: 0.5 | F46: Reflects the 2026 contract-lag state. Micron CEO confirmed DDR5 margins exceed HBM.
A47: [*] NAND base OPM | B47: 0.5 | F47: [ESTIMATE]
A49: Formula: OPM = 1 - (1 - base OPM) / ASP index. Rows 6-8 above read this result.
A50: Note: An ASP index below 1.0 pushes OPM below base. Once the index falls below (1 - base OPM), the segment swings to a loss.
A51: Note: Supply does not mechanically set HBM ASP. HBM has no spot market; prices are set in annual bilateral negotiations.
A52: Note: For that reason supply is not wired to ASP. Row 41 is where the negotiated outcome is entered; the Nov-Dec HBM4 contract price is the observation.

Sheet ROE_Build
A1: (14) ROE Build-up — Two-Factor DuPont [*] Cross-check 2
A2: ROE = net margin x equity turnover. Margin comes from SegmentMargin; equity comes from consensus BPS.
A4: 1. Inputs
A5: [*] Effective tax rate | B5: 0.145 | F5: Back-solved from consensus pretax vs net income for FY26-28 (14.9% / 15.2% / 13.7%), averaged
A6: Shares outstanding (millions) | B6: =Assumptions!B6 -> 1130
A7: Note: The net cash position generates interest income, which is conservatively ignored. Actual ROE will run slightly above the derived figure.
A9: 2. Derivation
A10: Item | B10: FY2026 | C10: FY2027 | D10: FY2028 | E10: FY2029
A11: Revenue ($m, consensus) | B11: =Consensus!D6 -> 129459 | C11: =Consensus!E6 -> 246699 | D11: =Consensus!F6 -> 285117 | E11: =Consensus!G6 -> 289549
A12: Blended EBIT margin (from SegmentMargin) | B12: =SegmentMargin!B15 -> 0.65894506 | C12: =SegmentMargin!C15 -> 0.70715586 | D12: =SegmentMargin!D15 -> 0.70524109 | E12: =SegmentMargin!E15 -> 0.62675737
A13: Derived net margin | B13: =B12*(1-$B$5) -> 0.56339802 | C13: =C12*(1-$B$5) -> 0.60461826 | D13: =D12*(1-$B$5) -> 0.60298113 | E13: =E12*(1-$B$5) -> 0.53587756
A14: Derived net income ($m) | B14: =B11*B13 -> 72936.945 | C14: =C11*C13 -> 149158.72 | D14: =D11*D13 -> 171920.17 | E14: =E11*E13 -> 155162.81
A15: Opening BPS | B15: =Consensus!C24 -> 48.4 | C15: =Consensus!D24 -> 118.72 | D15: =Consensus!E24 -> 259.02 | E15: =Consensus!F24 -> 437.94
A16: Closing BPS | B16: =Consensus!D24 -> 118.72 | C16: =Consensus!E24 -> 259.02 | D16: =Consensus!F24 -> 437.94 | E16: =Consensus!G24 -> 643.7
A17: Average equity ($m) | B17: =(B15+B16)/2*$B$6 -> 94422.8 | C17: =(C15+C16)/2*$B$6 -> 213423.1 | D17: =(D15+D16)/2*$B$6 -> 393782.4 | E17: =(E15+E16)/2*$B$6 -> 611126.6
A18: Derived ROE | B18: =IFERROR(B14/B17,"n/a") -> 0.77245056 | C18: =IFERROR(C14/C17,"n/a") -> 0.69888742 | D18: =IFERROR(D14/D17,"n/a") -> 0.43658673 | E18: =IFERROR(E14/E17,"n/a") -> 0.25389635
A20: 3. [*] Cross-check 2 — Consensus ROE
A21: Item | B21: FY2026 | C21: FY2027 | D21: FY2028 | E21: FY2029
A22: Consensus ROE (median) | B22: =Consensus!D27 -> 0.844 | C22: =Consensus!E27 -> 0.7384 | D22: =Consensus!F27 -> 0.4486 | E22: =Consensus!G27 -> 0.296
A23: Derived ROE | B23: =B18 -> 0.77245056 | C23: =C18 -> 0.69888742 | D23: =D18 -> 0.43658673 | E23: =E18 -> 0.25389635
A24: Gap (pp) | B24: =IFERROR(B23-B22,"n/a") -> -0.071549439 | C24: =IFERROR(C23-C22,"n/a") -> -0.039512579 | D24: =IFERROR(D23-D22,"n/a") -> -0.012013267 | E24: =IFERROR(E23-E22,"n/a") -> -0.042103655
A25: Consensus ROE, number of estimates | B25: 22 | C25: 21 | D25: 16 | E25: 3
A27: Note: Consensus ROE, EPS and BPS come from different analyst samples (for FY2028: ROE 16, EPS 31, BPS 12).
A28: Note: Consequently consensus net income divided by consensus average equity does not equal consensus ROE. Use this cross-check directionally, not for decimal agreement.
A29: Note: A large gap means one of two things - the segment margin assumptions are wrong, or the 12-estimate consensus BPS partially reflects buybacks.
A31: 4. [*] Buyback Adjustment — Correcting the Equity Balloon
A32: Consensus net debt (negative = net cash, $m) | B32: =Consensus!D31 -> -40902 | C32: =Consensus!E31 -> -143648 | D32: =Consensus!F31 -> -265525 | E32: =Consensus!G31 -> -318921 | G32: FY2029 net cash of $318.9B equals 110% of revenue, implying zero buybacks
A33: [*] Cumulative buyback spend ($m) | B33: 0 | C33: 0 | D33: 60000 | E33: 150000 | G33: [*] Assumes buybacks begin after the CHIPS restriction lifts on Dec 9. Estimates range from BofA $31.7B to UBS $380B; default sits in between
A34: Average buyback deduction | B34: =B33/2 -> 0 | C34: =(B33+C33)/2 -> 0 | D34: =(C33+D33)/2 -> 30000 | E34: =(D33+E33)/2 -> 105000
A35: Adjusted average equity ($m) | B35: =MAX(B17-B34,1) -> 94422.8 | C35: =MAX(C17-C34,1) -> 213423.1 | D35: =MAX(D17-D34,1) -> 363782.4 | E35: =MAX(E17-E34,1) -> 506126.6
A36: [*] Adjusted ROE | B36: =IFERROR(B14/B35,"n/a") -> 0.77245056 | C36: =IFERROR(C14/C35,"n/a") -> 0.69888742 | D36: =IFERROR(D14/D35,"n/a") -> 0.47259068 | E36: =IFERROR(E14/E35,"n/a") -> 0.30656917 | G36: The TerminalROE tab reads this row
A37: ROE before buybacks (reference) | B37: =B18 -> 0.77245056 | C37: =C18 -> 0.69888742 | D37: =D18 -> 0.43658673 | E37: =E18 -> 0.25389635
A38: Buyback effect (pp) | B38: =B36-B37 -> 0 | C38: =C36-C37 -> 0 | D38: =D36-D37 -> 0.036003946 | E38: =E36-E37 -> 0.052672822
A40: Note: The consensus BPS median (437.94) sits 5.9% above the mean (413.67). Some analysts already model buybacks and some do not.
A41: Note: Consensus BPS is therefore a blended figure. Leaving row 33 at zero is the extreme assumption that no buybacks occur at all.
A42: Note: Buybacks do not change net income, only the denominator, so they lift ROE directly. Resolution point: the CHIPS restriction announcement on 2026-12-09.

Sheet TerminalROE
A1: (15) Terminal ROE Build-up — Generating the RIM Input
A2: Terminal ROE is derived from mix and margins instead of being entered by hand. RIM_3Stage cell B10 reads B27 on this tab.
A4: 1. Anchor — FY2029 Derived Value (from ROE_Build)
A5: FY2029 derived ROE | B5: =ROE_Build!E36 -> 0.30656917 | G5: Buyback-adjusted ROE (ROE_Build row 36). Final year of the explicit forecast.
A6: FY2028 derived ROE (reference) | B6: =ROE_Build!D36 -> 0.47259068
A7: FY2029 HBM share of total revenue (from MixPath) | B7: =MixPath!E27 -> 0.2266965
A9: 2. Cycle Composition — Terminal Is a Through-Cycle Average, Not a Single Year
A10: [*] Weight on peak years | B10: 0.25 | G10: Assumes one peak year in a four-year cycle
A11: [*] Weight on mid years | B11: 0.5 | G11: Two transition years, rising and falling
A12: [*] Weight on trough years | B12: 0.25 | G12: One downturn year
A13: Sum check | B13: =B10+B11+B12 -> 1 | C13: =IF(ABS(B13-1)>0.001,"Warning: does not sum to 100%","OK") -> OK
A14: Base ROE (mid-cycle) = FY2029 derived | B14: =B5 -> 0.30656917
A15: [*] Peak multiple (vs base) | B15: 1.5 | G15: History: peak 18.5% / mid-year average 15.7% = 1.18x. Allowed up to 1.5x to stay conservative.
A16: Peak ROE | B16: =B14*B15 -> 0.45985375
A18: 3. [*] Trough ROE — Where HBM Contracts Provide Downside Support
A19: Spot-exposed share | B19: =1-B7 -> 0.7733035 | G19: Commodity DRAM plus NAND. Prices reprice immediately on spot.
A20: Contract-fixed share (= HBM revenue share) | B20: =B7 -> 0.2266965 | G20: MixPath FY2029 HBM share of total revenue
A21: [*] Trough ROE, spot-exposed portion | B21: -0.124 | G21: FY2023 actual of -12.4%. Revenue fell 49.5% and gross margin went to -9.1% on inventory write-downs.
A22: [*] Trough ROE, contract-fixed portion | B22: 0.15 | G22: [*] Critical assumption. Volume is locked but price rolls annually - can this stay profitable? Zero observations exist.
A23: Trough ROE | B23: =B19*B21+B20*B22 -> -0.06188516
A24: Reference: without contract support (prior regime) | B24: =B21 -> -0.124
A26: 4. [*] Result — The Cell RIM_3Stage Reads
A27: Derived terminal ROE | B27: =B10*B16+B11*B14+B12*B23 -> 0.25277673 | G27: peak weight x peak ROE + mid weight x base ROE + trough weight x trough ROE
A28: Conservative band (20-30%) test | B28: =IF(AND(B27>=0.2,B27<=0.3),"Inside band",IF(B27<0.2,"Below band","Above band")) -> Inside band
A29: Reference: terminal ROE without contract support | B29: =B10*B16+B11*B14+B12*B21 -> 0.23724802
A30: Contribution of the HBM contract structure (pp) | B30: =B27-B29 -> 0.01552871 | G30: This is the quantified size of the claim that contracts de-cyclicalize the business
A32: 5. Historical Check — Does This Method Reproduce the Record?
A33: FY2021 ROE | B33: =HistoricalCycle!B11 -> 0.1405
A34: FY2022 ROE (peak) | B34: =HistoricalCycle!C11 -> 0.1851
A35: FY2023 ROE (trough) | B35: =ROE_Build!E11 -> 289549
A36: FY2024 ROE | B36: =ROE_Build!E35 -> 506126.6
A37: FY2025 ROE | B37: =HistoricalCycle!F11 -> 0.1718
A38: Five-year simple average | B38: =HistoricalCycle!H11 -> 0.0782
A39: Average excluding FY2023 and FY2024 | B39: =(HistoricalCycle!B11+HistoricalCycle!C11+HistoricalCycle!F11)/3 -> 0.1658 | G39: Excluding those two years gives 16.6%. If the contract regime removes them, this is the anchor.
A40: This method applied to history (assuming zero contract share) | B40: =B10*HistoricalCycle!C11+B11*((HistoricalCycle!B11+HistoricalCycle!F11)/2)+B12*((HistoricalCycle!D11+HistoricalCycle!E11)/2) -> 0.11105 | G40: Comes out above the five-year simple average of 7.8% because downturn years were 40% of that window
A42: 6. Sensitivity — Terminal ROE (rows: contract trough ROE / columns: FY2029 HBM revenue share)
A43: Contract trough ROE \ HBM share | B43: 0.1 | C43: 0.2 | D43: 0.23 | E43: 0.3 | F43: 0.372 | G43: 0.45
A44: -0.124 | B44: =$B$10*$B$16+$B$11*$B$14+$B$12*((1-B$43)*$B$21+B$43*$A44) -> 0.23724802 | C44: =$B$10*$B$16+$B$11*$B$14+$B$12*((1-C$43)*$B$21+C$43*$A44) -> 0.23724802 | D44: =$B$10*$B$16+$B$11*$B$14+$B$12*((1-D$43)*$B$21+D$43*$A44) -> 0.23724802 | E44: =$B$10*$B$16+$B$11*$B$14+$B$12*((1-E$43)*$B$21+E$43*$A44) -> 0.23724802 | F44: =$B$10*$B$16+$B$11*$B$14+$B$12*((1-F$43)*$B$21+F$43*$A44) -> 0.23724802 | G44: =$B$10*$B$16+$B$11*$B$14+$B$12*((1-G$43)*$B$21+G$43*$A44) -> 0.23724802
A45: 0 | B45: =$B$10*$B$16+$B$11*$B$14+$B$12*((1-B$43)*$B$21+B$43*$A45) -> 0.24034802 | C45: =$B$10*$B$16+$B$11*$B$14+$B$12*((1-C$43)*$B$21+C$43*$A45) -> 0.24344802 | D45: =$B$10*$B$16+$B$11*$B$14+$B$12*((1-D$43)*$B$21+D$43*$A45) -> 0.24437802 | E45: =$B$10*$B$16+$B$11*$B$14+$B$12*((1-E$43)*$B$21+E$43*$A45) -> 0.24654802 | F45: =$B$10*$B$16+$B$11*$B$14+$B$12*((1-F$43)*$B$21+F$43*$A45) -> 0.24878002 | G45: =$B$10*$B$16+$B$11*$B$14+$B$12*((1-G$43)*$B$21+G$43*$A45) -> 0.25119802
A46: 0.1 | B46: =$B$10*$B$16+$B$11*$B$14+$B$12*((1-B$43)*$B$21+B$43*$A46) -> 0.24284802 | C46: =$B$10*$B$16+$B$11*$B$14+$B$12*((1-C$43)*$B$21+C$43*$A46) -> 0.24844802 | D46: =$B$10*$B$16+$B$11*$B$14+$B$12*((1-D$43)*$B$21+D$43*$A46) -> 0.25012802 | E46: =$B$10*$B$16+$B$11*$B$14+$B$12*((1-E$43)*$B$21+E$43*$A46) -> 0.25404802 | F46: =$B$10*$B$16+$B$11*$B$14+$B$12*((1-F$43)*$B$21+F$43*$A46) -> 0.25808002 | G46: =$B$10*$B$16+$B$11*$B$14+$B$12*((1-G$43)*$B$21+G$43*$A46) -> 0.26244802
A47: 0.15 | B47: =$B$10*$B$16+$B$11*$B$14+$B$12*((1-B$43)*$B$21+B$43*$A47) -> 0.24409802 | C47: =$B$10*$B$16+$B$11*$B$14+$B$12*((1-C$43)*$B$21+C$43*$A47) -> 0.25094802 | D47: =$B$10*$B$16+$B$11*$B$14+$B$12*((1-D$43)*$B$21+D$43*$A47) -> 0.25300302 | E47: =$B$10*$B$16+$B$11*$B$14+$B$12*((1-E$43)*$B$21+E$43*$A47) -> 0.25779802 | F47: =$B$10*$B$16+$B$11*$B$14+$B$12*((1-F$43)*$B$21+F$43*$A47) -> 0.26273002 | G47: =$B$10*$B$16+$B$11*$B$14+$B$12*((1-G$43)*$B$21+G$43*$A47) -> 0.26807302
A48: 0.25 | B48: =$B$10*$B$16+$B$11*$B$14+$B$12*((1-B$43)*$B$21+B$43*$A48) -> 0.24659802 | C48: =$B$10*$B$16+$B$11*$B$14+$B$12*((1-C$43)*$B$21+C$43*$A48) -> 0.25594802 | D48: =$B$10*$B$16+$B$11*$B$14+$B$12*((1-D$43)*$B$21+D$43*$A48) -> 0.25875302 | E48: =$B$10*$B$16+$B$11*$B$14+$B$12*((1-E$43)*$B$21+E$43*$A48) -> 0.26529802 | F48: =$B$10*$B$16+$B$11*$B$14+$B$12*((1-F$43)*$B$21+F$43*$A48) -> 0.27203002 | G48: =$B$10*$B$16+$B$11*$B$14+$B$12*((1-G$43)*$B$21+G$43*$A48) -> 0.27932302
A49: 0.35 | B49: =$B$10*$B$16+$B$11*$B$14+$B$12*((1-B$43)*$B$21+B$43*$A49) -> 0.24909802 | C49: =$B$10*$B$16+$B$11*$B$14+$B$12*((1-C$43)*$B$21+C$43*$A49) -> 0.26094802 | D49: =$B$10*$B$16+$B$11*$B$14+$B$12*((1-D$43)*$B$21+D$43*$A49) -> 0.26450302 | E49: =$B$10*$B$16+$B$11*$B$14+$B$12*((1-E$43)*$B$21+E$43*$A49) -> 0.27279802 | F49: =$B$10*$B$16+$B$11*$B$14+$B$12*((1-F$43)*$B$21+F$43*$A49) -> 0.28133002 | G49: =$B$10*$B$16+$B$11*$B$14+$B$12*((1-G$43)*$B$21+G$43*$A49) -> 0.29057302
A50: Current selection | B50: =B27 -> 0.25277673
A52: Note: Row 44 (contract trough at -12.4%) is the case where contracts do nothing. The gap between that row and the others is the value of the contract structure.
A53: Note: Moving toward the lower left is the bull case that contracts de-cyclicalize earnings. The upper right is not supported by observation.
A54: Note: The contract trough ROE is unverified. There has been no downturn since HBM became material in 2024, so there are zero observations.
A55: Note: Resolution point is disclosure of LTA terms around year-end. If a floor price exists, row 22 should sit at 15% or above; if not, 5% or below is the consistent setting.
A56: Sources: Historical ROE from the HistoricalCycle tab (FY2021-25 actuals). FY2023 revenue -49.5%, gross margin -9.1%.

Sheet PB_Bridge
A1: (18) P/B Bridge — Why the Market Assigns This Multiple
A2: P/B is an output of the RIM, not an input. Rather than adding adjustment factors, the multiple is split into three pieces to show where it comes from.
A4: 1. RIM Inputs (Section 11 Adopted Structure)
A5: B0 - FY2025 actual BPS | B5: =RIM_3Stage!B125 -> 48.4 | H5: Confirmed actual
A6: + PV of residual income, FY2026-28 | B6: =RIM_3Stage!B126 -> 271.17684 | H6: Explicit forecast window
A7: Terminal base equity (FY2028 BPS) | B7: =RIM_3Stage!B127 -> 437.94 | H7: 12 estimates
A8: Discount factor to FY2028 | B8: =RIM_3Stage!B128 -> 0.71173894
A9: Terminal ROE (derived on TerminalROE) | B9: =RIM_3Stage!B10 -> 0.25277673 | H9: Manual entry retired
A10: Terminal discount rate | B10: =RIM_3Stage!B9 -> 0.16000346 | H10: [*] The last battleground
A11: Terminal growth rate g | B11: =RIM_3Stage!B11 -> 0.04
A12: Stage 1 discount rate | B12: =RIM_3Stage!B7 -> 0.12002167
A14: 2. Multiple Bridge — Today’s Value Expressed Against FY2028 Book
A15: PV of terminal value | B15: =IFERROR((B9-B10)*B7/(B10-B11)*B8,0) -> 240.97083
A16: Intrinsic value V0 (today) | B16: =B5+B6+B15 -> 560.54768
A17: V0 compounded to FY2028 | B17: =B16*(1+B12)^3 -> 787.57483
A19: P/B bridge (forward multiple on FY2028 BPS)
A20: (a) Book value component (B0) | B20: =B5*(1+$B$12)^3/$B$7 -> 0.15527803 | H20: Equity already booked
A21: (b) Explicit residual income | B21: =B6*(1+$B$12)^3/$B$7 -> 0.869996 | H21: Excess earnings, FY2026-28
A22: (c) Terminal contribution | B22: =B15*(1+$B$12)^3/$B$7 -> 0.77308837 | H22: Everything from FY2029 onward
A23: Derived forward P/B | B23: =B20+B21+B22 -> 1.7983624 | H23: Total
A24: Terminal share of the multiple | B24: =IFERROR(B22/B23,"n/a") -> 0.42988464 | H24: A high value means the conclusion is dominated by terminal assumptions
A26: 3. Comparison With the Market Multiple
A27: Current share price | B27: =Assumptions!B5 -> 900
A28: FY2028 consensus BPS | B28: =Consensus!F24 -> 437.94 | H28: 12 estimates
A29: Market forward P/B (FY2028) | B29: =B27/B28 -> 2.055076 | H29: Current price / FY2028 BPS
A30: Derived forward P/B | B30: =B23 -> 1.7983624 | H30: Sum of (a), (b) and (c) above
A31: Gap | B31: =B29-B30 -> 0.25671363 | H31: Positive means the market values the shares above the model
A32: Gap (%) | B32: =IFERROR(B29/B30-1,"n/a") -> 0.14274855
A34: 4. Reference — Historical Multiple Band
A35: Five-year P/B band, low | B35: =HistoricalCycle!C16 -> 1.26 | H35: FY2022
A36: Five-year P/B average | B36: =HistoricalCycle!H16 -> 1.952 | H36: FY2021~25
A37: Five-year P/B band, high | B37: =HistoricalCycle!F16 -> 2.53 | H37: FY2025
A38: BofA two-year-forward historical median | B38: =1.54 -> 1.54 | H38: BofA report, 2026-05-29
A39: Note: The band above reflects realized multiples on then-current book value. Mind the timing difference when comparing directly with a forward P/B.
A41: 5. P/B Sensitivity (rows: terminal ROE / columns: terminal discount rate) — forward P/B on FY2028 BPS
A42: Terminal ROE \ Discount rate | B42: 0.1 | C42: 0.12 | D42: 0.14 | E42: 0.16 | F42: 0.18 | G42: 0.2
A43: 0.15 | B43: =IFERROR((($B$5+$B$6+($A43-B$42)*$B$7/(B$42-$B$11)*$B$8)*(1+$B$12)^3)/$B$7,"n/a") -> 1.8586074 | C43: =IFERROR((($B$5+$B$6+($A43-C$42)*$B$7/(C$42-$B$11)*$B$8)*(1+$B$12)^3)/$B$7,"n/a") -> 1.400274 | D43: =IFERROR((($B$5+$B$6+($A43-D$42)*$B$7/(D$42-$B$11)*$B$8)*(1+$B$12)^3)/$B$7,"n/a") -> 1.125274 | E43: =IFERROR((($B$5+$B$6+($A43-E$42)*$B$7/(E$42-$B$11)*$B$8)*(1+$B$12)^3)/$B$7,"n/a") -> 0.9419407 | F43: =IFERROR((($B$5+$B$6+($A43-F$42)*$B$7/(F$42-$B$11)*$B$8)*(1+$B$12)^3)/$B$7,"n/a") -> 0.81098832 | G43: =IFERROR((($B$5+$B$6+($A43-G$42)*$B$7/(G$42-$B$11)*$B$8)*(1+$B$12)^3)/$B$7,"n/a") -> 0.71277404
A44: 0.2 | B44: =IFERROR((($B$5+$B$6+($A44-B$42)*$B$7/(B$42-$B$11)*$B$8)*(1+$B$12)^3)/$B$7,"n/a") -> 2.6919407 | C44: =IFERROR((($B$5+$B$6+($A44-C$42)*$B$7/(C$42-$B$11)*$B$8)*(1+$B$12)^3)/$B$7,"n/a") -> 2.025274 | D44: =IFERROR((($B$5+$B$6+($A44-D$42)*$B$7/(D$42-$B$11)*$B$8)*(1+$B$12)^3)/$B$7,"n/a") -> 1.625274 | E44: =IFERROR((($B$5+$B$6+($A44-E$42)*$B$7/(E$42-$B$11)*$B$8)*(1+$B$12)^3)/$B$7,"n/a") -> 1.3586074 | F44: =IFERROR((($B$5+$B$6+($A44-F$42)*$B$7/(F$42-$B$11)*$B$8)*(1+$B$12)^3)/$B$7,"n/a") -> 1.1681312 | G44: =IFERROR((($B$5+$B$6+($A44-G$42)*$B$7/(G$42-$B$11)*$B$8)*(1+$B$12)^3)/$B$7,"n/a") -> 1.025274
A45: 0.25 | B45: =IFERROR((($B$5+$B$6+($A45-B$42)*$B$7/(B$42-$B$11)*$B$8)*(1+$B$12)^3)/$B$7,"n/a") -> 3.525274 | C45: =IFERROR((($B$5+$B$6+($A45-C$42)*$B$7/(C$42-$B$11)*$B$8)*(1+$B$12)^3)/$B$7,"n/a") -> 2.650274 | D45: =IFERROR((($B$5+$B$6+($A45-D$42)*$B$7/(D$42-$B$11)*$B$8)*(1+$B$12)^3)/$B$7,"n/a") -> 2.125274 | E45: =IFERROR((($B$5+$B$6+($A45-E$42)*$B$7/(E$42-$B$11)*$B$8)*(1+$B$12)^3)/$B$7,"n/a") -> 1.775274 | F45: =IFERROR((($B$5+$B$6+($A45-F$42)*$B$7/(F$42-$B$11)*$B$8)*(1+$B$12)^3)/$B$7,"n/a") -> 1.525274 | G45: =IFERROR((($B$5+$B$6+($A45-G$42)*$B$7/(G$42-$B$11)*$B$8)*(1+$B$12)^3)/$B$7,"n/a") -> 1.337774
A46: 0.3 | B46: =IFERROR((($B$5+$B$6+($A46-B$42)*$B$7/(B$42-$B$11)*$B$8)*(1+$B$12)^3)/$B$7,"n/a") -> 4.3586074 | C46: =IFERROR((($B$5+$B$6+($A46-C$42)*$B$7/(C$42-$B$11)*$B$8)*(1+$B$12)^3)/$B$7,"n/a") -> 3.275274 | D46: =IFERROR((($B$5+$B$6+($A46-D$42)*$B$7/(D$42-$B$11)*$B$8)*(1+$B$12)^3)/$B$7,"n/a") -> 2.625274 | E46: =IFERROR((($B$5+$B$6+($A46-E$42)*$B$7/(E$42-$B$11)*$B$8)*(1+$B$12)^3)/$B$7,"n/a") -> 2.1919407 | F46: =IFERROR((($B$5+$B$6+($A46-F$42)*$B$7/(F$42-$B$11)*$B$8)*(1+$B$12)^3)/$B$7,"n/a") -> 1.8824169 | G46: =IFERROR((($B$5+$B$6+($A46-G$42)*$B$7/(G$42-$B$11)*$B$8)*(1+$B$12)^3)/$B$7,"n/a") -> 1.650274
A47: 0.35 | B47: =IFERROR((($B$5+$B$6+($A47-B$42)*$B$7/(B$42-$B$11)*$B$8)*(1+$B$12)^3)/$B$7,"n/a") -> 5.1919407 | C47: =IFERROR((($B$5+$B$6+($A47-C$42)*$B$7/(C$42-$B$11)*$B$8)*(1+$B$12)^3)/$B$7,"n/a") -> 3.900274 | D47: =IFERROR((($B$5+$B$6+($A47-D$42)*$B$7/(D$42-$B$11)*$B$8)*(1+$B$12)^3)/$B$7,"n/a") -> 3.125274 | E47: =IFERROR((($B$5+$B$6+($A47-E$42)*$B$7/(E$42-$B$11)*$B$8)*(1+$B$12)^3)/$B$7,"n/a") -> 2.6086074 | F47: =IFERROR((($B$5+$B$6+($A47-F$42)*$B$7/(F$42-$B$11)*$B$8)*(1+$B$12)^3)/$B$7,"n/a") -> 2.2395598 | G47: =IFERROR((($B$5+$B$6+($A47-G$42)*$B$7/(G$42-$B$11)*$B$8)*(1+$B$12)^3)/$B$7,"n/a") -> 1.962774
A48: 0.4 | B48: =IFERROR((($B$5+$B$6+($A48-B$42)*$B$7/(B$42-$B$11)*$B$8)*(1+$B$12)^3)/$B$7,"n/a") -> 6.025274 | C48: =IFERROR((($B$5+$B$6+($A48-C$42)*$B$7/(C$42-$B$11)*$B$8)*(1+$B$12)^3)/$B$7,"n/a") -> 4.525274 | D48: =IFERROR((($B$5+$B$6+($A48-D$42)*$B$7/(D$42-$B$11)*$B$8)*(1+$B$12)^3)/$B$7,"n/a") -> 3.625274 | E48: =IFERROR((($B$5+$B$6+($A48-E$42)*$B$7/(E$42-$B$11)*$B$8)*(1+$B$12)^3)/$B$7,"n/a") -> 3.025274 | F48: =IFERROR((($B$5+$B$6+($A48-F$42)*$B$7/(F$42-$B$11)*$B$8)*(1+$B$12)^3)/$B$7,"n/a") -> 2.5967026 | G48: =IFERROR((($B$5+$B$6+($A48-G$42)*$B$7/(G$42-$B$11)*$B$8)*(1+$B$12)^3)/$B$7,"n/a") -> 2.275274
A50: Current combination | B50: =B23 -> 1.7983624
A51: Market forward P/B | B51: =B29 -> 2.055076
A52: Note: The cell matching the market multiple in B51 is the terminal ROE and discount rate combination the market implies.
A53: Note: Cells above the historical band high of 2.53x sit in territory that has never been realized.
A55: 6. [*] News Routing — Why No Adjustment Factor Is Applied to P/B
A56: Every news item routes through the table below into an existing input cell. Adjusting P/B directly would put the target multiple and the achievement rate on the optimistic side at the same time, violating update rule 5 in section 7 of the handoff note.
A57: News / Event | B57: Transmission path | C57: Cell to adjust | D57: P/B direction | E57: Resolution point
A58: HBM4 contract price rises (Goldman +44-50%) | B58: HBM ASP up, HBM OPM up, ROE up | C58: SegmentMargin B41:E41 | D58: Expands | E58: 2026-11~12
A59: HBM4 contract price undershoots consensus (+34%) | B59: HBM ASP down, HBM OPM down | C59: SegmentMargin B41:E41 | D59: Contracts | E59: 2026-11~12
A60: Commodity DRAM spot price collapses | B60: Commodity ASP down, commodity OPM down, ROE down | C60: SegmentMargin B40:E40 | D60: Contracts | E60: Ongoing
A61: Memory oversupply (CXMT and top-3 expansion) | B61: Commodity ASP down | C61: SegmentMargin B40:E40 | D61: Contracts | E61: 2027~28
A62: Hyperscaler AI capex slows | B62: HBM wafer share down and commodity ASP down | C62: MixPath B6:E6 and SegmentMargin row 40 | D62: Contracts | E62: Quarterly
A63: Large buyback announced on Dec 9 | B63: Equity down, turnover up, ROE up | C63: ROE_Build B33:E33 | D63: Expands | E63: 2026-12-09
A64: LTA floor price confirmed | B64: Contract trough ROE up, terminal ROE up | C64: TerminalROE B22 | D64: Expands | E64: Year-end to early next year
A65: Rates fall, liquidity improves | B65: Cost of equity down, terminal discount rate down | C65: RIM_3Stage B9 | D65: Expands | E65: Ongoing
A66: Re-rating out of the cyclical bucket (beta down) | B66: Cost of equity down | C66: RIM_3Stage B9 and Assumptions B14 | D66: Expands | E66: After LTA terms are disclosed
A67: CXMT accelerates into HBM | B67: Terminal ROE down, discount rate up | C67: TerminalROE B22 and RIM_3Stage B9 | D67: Contracts | E67: HBM3E in 2027
A68: Micron misses consensus | B68: Consensus EPS and BPS down, all tabs recalculate | C68: Consensus tab | D68: Contracts | E68: Late Sep to early Oct
A69: Apple adopts CXMT (Aug 21 Senate reply) | B69: Political shield disappears, discount rate up | C69: RIM_3Stage B9 | D69: Contracts | E69: 2026-08-21
A71: Note: There is deliberately no P/B premium factor cell here. With one, any conclusion could be manufactured.
A72: Note: The four factors raised in review (ROE premium, AI slowdown, oversupply, liquidity) map to rows 1, 5, 4 and 8 of the table above.
A73: Sources: Historical multiples from the HistoricalCycle tab. Resolution points are synchronized with the Tracker tab. Not investment advice.

Sheet DiscountRate
A1: (19) Discount Rate Build-up — Rf + Beta x ERP, With Beta Derived From Mix
A2: Converts the three-stage RIM discount rates from manual entry to a CAPM build-up. Beta is derived from the contract-fixed revenue share.
A4: 1. CAPM Components
A5: [*] Risk-free rate, US 10-year | B5: =Assumptions!B13 -> 0.043 | G5: Linked to Assumptions B13. Verify and update directly.
A6: [*] Equity risk premium (ERP) | B6: =Assumptions!B15 -> 0.05 | G6: Linked to Assumptions B15. Typically 4.5-5.5%.
A7: Observed beta (5Y) | B7: =Assumptions!B14 -> 2.14 | G7: Finviz 2026-07-28
A8: CAPM base cost of equity | B8: =B5+B7*B6 -> 0.15 | G8: Rf + beta x ERP, at the current mix
A10: 2. [*] Beta Decomposition — Does the Contract Structure Lower Beta?
A11: The observed beta of 2.14 already embeds a 23% HBM share. This splits it into spot and contract components.
A12: FY2026 HBM revenue share | B12: =MixPath!B27 -> 0.23018314 | G12: MixPath reproduces the actual 23.0%
A13: [*] Contract-portion beta | B13: 0.8 | G13: [*] Systematic risk of the five-year volume contracts and customer-qualified business. No observations exist [ESTIMATE]
A14: Implied spot-portion beta (back-solved) | B14: =IFERROR((B7-B12*B13)/(1-B12),"n/a") -> 2.5406738 | G14: (observed beta - HBM share x contract beta) / spot share
A16: 3. Derived Beta and Cost of Equity by Year
A17: Item | B17: FY2026 | C17: FY2027 | D17: FY2028 | E17: FY2029
A18: HBM revenue share (from MixPath) | B18: =MixPath!B27 -> 0.23018314 | C18: =MixPath!C27 -> 0.17937907 | D18: =MixPath!D27 -> 0.21132075 | E18: =MixPath!E27 -> 0.2266965
A19: Spot-exposed share | B19: =1-B18 -> 0.76981686 | C19: =1-C18 -> 0.82062093 | D19: =1-D18 -> 0.78867925 | E19: =1-E18 -> 0.7733035
A20: Derived beta | B20: =B19*$B$14+B18*$B$13 -> 2.14 | C20: =C19*$B$14+C18*$B$13 -> 2.2284333 | D20: =D19*$B$14+D18*$B$13 -> 2.1728333 | E20: =E19*$B$14+E18*$B$13 -> 2.1460691
A21: Derived cost of equity | B21: =$B$5+B20*$B$6 -> 0.15 | C21: =$B$5+C20*$B$6 -> 0.15442167 | D21: =$B$5+D20*$B$6 -> 0.15164166 | E21: =$B$5+E20*$B$6 -> 0.15030346 | G21: A larger contract share pulls beta and cost of equity down
A23: 4. Mapping to the Three Stages — Read by RIM_3Stage B7/B8/B9
A24: Each stage carries an explicit [*] adjustment. The adjustment is judgment, and it is shown in a cell rather than hidden.
A25: Stage | B25: Base cost of equity | C25: [*] Adjustment (pp) | D25: Applied discount rate | E25: Rationale
A26: Stage 1 (FY2026-28) | B26: =C21 -> 0.15442167 | C26: -0.0344 | D26: =B26+C26 -> 0.12002167 | E26: Near-term visibility is high given five-year HBM volume contracts and fab lead times. Based on the FY2027 cost of equity.
A27: Stage 2 (FY2029) | B27: =E21 -> 0.15030346 | C27: 0.0197 | D27: =B27+C27 -> 0.17000346 | E27: Period of CXMT reaching 600k wpm and domestic Chinese DUV spreading. New capacity landing raises uncertainty.
A28: Terminal | B28: =E21 -> 0.15030346 | C28: 0.0097 | D28: =B28+C28 -> 0.16000346 | E28: Perpetuity. Between 12-14% if the four-supplier oligopoly holds and 18-20% under commoditization.
A30: Note: The default adjustments are back-solved to reproduce the prior manual inputs of 12% / 17% / 16% exactly. Only the structure changed; the numbers did not.
A31: Note: Setting the adjustments to zero yields the pure CAPM values. Stage 1 rises to 15.4% and intrinsic value falls sharply.
A33: 5. Sensitivity — Terminal Discount Rate (rows: contract beta / columns: risk-free rate)
A34: Contract beta \ Rf | B34: 0.03 | C34: 0.035 | D34: 0.043 | E34: 0.05 | F34: 0.055
A35: 0.4 | B35: =B$34+((1-$E$18)*(($B$7-$B$12*$A35)/(1-$B$12))+$E$18*$A35)*$B$6+$C$28 -> 0.14709404 | C35: =C$34+((1-$E$18)*(($B$7-$B$12*$A35)/(1-$B$12))+$E$18*$A35)*$B$6+$C$28 -> 0.15209404 | D35: =D$34+((1-$E$18)*(($B$7-$B$12*$A35)/(1-$B$12))+$E$18*$A35)*$B$6+$C$28 -> 0.16009404 | E35: =E$34+((1-$E$18)*(($B$7-$B$12*$A35)/(1-$B$12))+$E$18*$A35)*$B$6+$C$28 -> 0.16709404 | F35: =F$34+((1-$E$18)*(($B$7-$B$12*$A35)/(1-$B$12))+$E$18*$A35)*$B$6+$C$28 -> 0.17209404
A36: 0.6 | B36: =B$34+((1-$E$18)*(($B$7-$B$12*$A36)/(1-$B$12))+$E$18*$A36)*$B$6+$C$28 -> 0.14704875 | C36: =C$34+((1-$E$18)*(($B$7-$B$12*$A36)/(1-$B$12))+$E$18*$A36)*$B$6+$C$28 -> 0.15204875 | D36: =D$34+((1-$E$18)*(($B$7-$B$12*$A36)/(1-$B$12))+$E$18*$A36)*$B$6+$C$28 -> 0.16004875 | E36: =E$34+((1-$E$18)*(($B$7-$B$12*$A36)/(1-$B$12))+$E$18*$A36)*$B$6+$C$28 -> 0.16704875 | F36: =F$34+((1-$E$18)*(($B$7-$B$12*$A36)/(1-$B$12))+$E$18*$A36)*$B$6+$C$28 -> 0.17204875
A37: 0.8 | B37: =B$34+((1-$E$18)*(($B$7-$B$12*$A37)/(1-$B$12))+$E$18*$A37)*$B$6+$C$28 -> 0.14700346 | C37: =C$34+((1-$E$18)*(($B$7-$B$12*$A37)/(1-$B$12))+$E$18*$A37)*$B$6+$C$28 -> 0.15200346 | D37: =D$34+((1-$E$18)*(($B$7-$B$12*$A37)/(1-$B$12))+$E$18*$A37)*$B$6+$C$28 -> 0.16000346 | E37: =E$34+((1-$E$18)*(($B$7-$B$12*$A37)/(1-$B$12))+$E$18*$A37)*$B$6+$C$28 -> 0.16700346 | F37: =F$34+((1-$E$18)*(($B$7-$B$12*$A37)/(1-$B$12))+$E$18*$A37)*$B$6+$C$28 -> 0.17200346
A38: 1 | B38: =B$34+((1-$E$18)*(($B$7-$B$12*$A38)/(1-$B$12))+$E$18*$A38)*$B$6+$C$28 -> 0.14695816 | C38: =C$34+((1-$E$18)*(($B$7-$B$12*$A38)/(1-$B$12))+$E$18*$A38)*$B$6+$C$28 -> 0.15195816 | D38: =D$34+((1-$E$18)*(($B$7-$B$12*$A38)/(1-$B$12))+$E$18*$A38)*$B$6+$C$28 -> 0.15995816 | E38: =E$34+((1-$E$18)*(($B$7-$B$12*$A38)/(1-$B$12))+$E$18*$A38)*$B$6+$C$28 -> 0.16695816 | F38: =F$34+((1-$E$18)*(($B$7-$B$12*$A38)/(1-$B$12))+$E$18*$A38)*$B$6+$C$28 -> 0.17195816
A39: 1.4 | B39: =B$34+((1-$E$18)*(($B$7-$B$12*$A39)/(1-$B$12))+$E$18*$A39)*$B$6+$C$28 -> 0.14686758 | C39: =C$34+((1-$E$18)*(($B$7-$B$12*$A39)/(1-$B$12))+$E$18*$A39)*$B$6+$C$28 -> 0.15186758 | D39: =D$34+((1-$E$18)*(($B$7-$B$12*$A39)/(1-$B$12))+$E$18*$A39)*$B$6+$C$28 -> 0.15986758 | E39: =E$34+((1-$E$18)*(($B$7-$B$12*$A39)/(1-$B$12))+$E$18*$A39)*$B$6+$C$28 -> 0.16686758 | F39: =F$34+((1-$E$18)*(($B$7-$B$12*$A39)/(1-$B$12))+$E$18*$A39)*$B$6+$C$28 -> 0.17186758
A40: 1.8 | B40: =B$34+((1-$E$18)*(($B$7-$B$12*$A40)/(1-$B$12))+$E$18*$A40)*$B$6+$C$28 -> 0.146777 | C40: =C$34+((1-$E$18)*(($B$7-$B$12*$A40)/(1-$B$12))+$E$18*$A40)*$B$6+$C$28 -> 0.151777 | D40: =D$34+((1-$E$18)*(($B$7-$B$12*$A40)/(1-$B$12))+$E$18*$A40)*$B$6+$C$28 -> 0.159777 | E40: =E$34+((1-$E$18)*(($B$7-$B$12*$A40)/(1-$B$12))+$E$18*$A40)*$B$6+$C$28 -> 0.166777 | F40: =F$34+((1-$E$18)*(($B$7-$B$12*$A40)/(1-$B$12))+$E$18*$A40)*$B$6+$C$28 -> 0.171777
A42: Current combination | B42: =D28 -> 0.16000346
A43: Note: Even with contract beta at 0.4 and the risk-free rate at 3.0%, the terminal discount rate stays in the low 12% range.
A44: Note: Contract structure plus falling rates alone will not reach the 10% Nomura argues for. The spot-portion beta itself would have to fall.
A45: Note: Resolution point is disclosure of LTA terms around year-end. A floor price would justify lowering row 13, the contract beta.

Sheet Sensitivity
A1: (20) One-Way Sensitivity (Tornado) — Which Assumption Dominates
A2: Each parameter is moved on its own to show the swing in intrinsic value V0. The ranking by swing is the update priority order.
A4: 1. Base Parameters (linked from other tabs — do not edit here)
A5: HBM wafer share (FY2029) | B5: =MixPath!E6 -> 0.38
A6: Trade ratio (FY2029) | B6: =MixPath!E7 -> 3.1
A7: ASP premium (FY2029) | B7: =MixPath!E15 -> 2
A8: DRAM revenue share (FY2029) | B8: =MixPath!E8 -> 0.8
A9: Commodity base OPM | B9: =SegmentMargin!B45 -> 0.8
A10: Commodity ASP index (FY2029) | B10: =SegmentMargin!E40 -> 0.61
A11: HBM base OPM | B11: =SegmentMargin!B46 -> 0.5
A12: HBM ASP index (FY2029) | B12: =SegmentMargin!E41 -> 1.79
A13: NAND base OPM | B13: =SegmentMargin!B47 -> 0.5
A14: NAND ASP index (FY2029) | B14: =SegmentMargin!E42 -> 0.82
A15: FY2029 revenue ($m) | B15: =ROE_Build!E11 -> 289549
A16: Effective tax rate | B16: =ROE_Build!B5 -> 0.145
A17: FY2029 average equity ($m) | B17: =ROE_Build!E17 -> 611126.6
A18: Average buyback deduction ($m) | B18: =ROE_Build!E34 -> 105000
A19: Spot trough ROE | B19: =TerminalROE!B21 -> -0.124
A20: Contract trough ROE | B20: =TerminalROE!B22 -> 0.15
A21: Peak multiple | B21: =TerminalROE!B15 -> 1.5
A22: Weight on peak years | B22: =TerminalROE!B10 -> 0.25
A23: Weight on mid years | B23: =TerminalROE!B11 -> 0.5
A24: Weight on trough years | B24: =TerminalROE!B12 -> 0.25
A25: Fixed component B0 + RI (RIM) | B25: =RIM_3Stage!B129 -> 319.57684
A26: FY2028 BPS (terminal equity) | B26: =RIM_3Stage!B127 -> 437.94
A27: FY2028 discount factor | B27: =RIM_3Stage!B128 -> 0.71173894
A28: Terminal discount rate | B28: =RIM_3Stage!B9 -> 0.16000346
A29: Terminal growth rate g | B29: =RIM_3Stage!B11 -> 0.04
A31: 2. Check — Does the Chain Reproduce the RIM Result?
A32: V0 reproduced by the chain | B32: =IFERROR($B$25+((($B$22*($B$15*(((1-(((($B$5/$B$6)/(($B$5/$B$6)+(1-$B$5)))*$B$7)/(((($B$5/$B$6)/(($B$5/$B$6)+(1-$B$5)))*$B$7)+(1-(($B$5/$B$6)/(($B$5/$B$6)+(1-$B$5)))))))*$B$8)*(1-(1-$B$9)/$B$10)+((((($B$5/$B$6)/(($B$5/$B$6)+(1-$B$5)))*$B$7)/(((($B$5/$B$6)/(($B$5/$B$6)+(1-$B$5)))*$B$7)+(1-(($B$5/$B$6)/(($B$5/$B$6)+(1-$B$5))))))*$B$8)*(1-(1-$B$11)/$B$12)+(1-$B$8)*(1-(1-$B$13)/$B$14))*(1-$B$16)/($B$17-$B$18))*$B$21+$B$23*($B$15*(((1-(((($B$5/$B$6)/(($B$5/$B$6)+(1-$B$5)))*$B$7)/(((($B$5/$B$6)/(($B$5/$B$6)+(1-$B$5)))*$B$7)+(1-(($B$5/$B$6)/(($B$5/$B$6)+(1-$B$5)))))))*$B$8)*(1-(1-$B$9)/$B$10)+((((($B$5/$B$6)/(($B$5/$B$6)+(1-$B$5)))*$B$7)/(((($B$5/$B$6)/(($B$5/$B$6)+(1-$B$5)))*$B$7)+(1-(($B$5/$B$6)/(($B$5/$B$6)+(1-$B$5))))))*$B$8)*(1-(1-$B$11)/$B$12)+(1-$B$8)*(1-(1-$B$13)/$B$14))*(1-$B$16)/($B$17-$B$18))+$B$24*((1-((((($B$5/$B$6)/(($B$5/$B$6)+(1-$B$5)))*$B$7)/(((($B$5/$B$6)/(($B$5/$B$6)+(1-$B$5)))*$B$7)+(1-(($B$5/$B$6)/(($B$5/$B$6)+(1-$B$5))))))*$B$8))*$B$19+((((($B$5/$B$6)/(($B$5/$B$6)+(1-$B$5)))*$B$7)/(((($B$5/$B$6)/(($B$5/$B$6)+(1-$B$5)))*$B$7)+(1-(($B$5/$B$6)/(($B$5/$B$6)+(1-$B$5))))))*$B$8)*$B$20))-$B$28)*$B$26/($B$28-$B$29))*$B$27,"n/a") -> 560.54768
A33: RIM section 11 computed directly | B33: =IFERROR(RIM_3Stage!B129+((RIM_3Stage!B10-RIM_3Stage!B9)*RIM_3Stage!B127/(RIM_3Stage!B9-RIM_3Stage!B11))*RIM_3Stage!B128,"n/a") -> 560.54768
A34: Difference | B34: =B32-B33 -> 0 | I34: Zero confirms the chain reproduces the RIM exactly
A36: 3. Tornado — V0 Swing by Parameter
A37: Parameter | B37: Base | C37: Down | D37: Up | E37: V0 (down) | F37: V0 (up) | G37: Swing ($) | H37: Swing (%) | I37: Basis for the range
A38: HBM wafer share (FY2029) | B38: =$B$5 -> 0.38 | C38: =$B$5-0.05 -> 0.33 | D38: =$B$5+0.05 -> 0.43 | E38: =IFERROR($B$25+((($B$22*($B$15*(((1-(((($C$38/$B$6)/(($C$38/$B$6)+(1-$C$38)))*$B$7)/(((($C$38/$B$6)/(($C$38/$B$6)+(1-$C$38)))*$B$7)+(1-(($C$38/$B$6)/(($C$38/$B$6)+(1-$C$38)))))))*$B$8)*(1-(1-$B$9)/$B$10)+((((($C$38/$B$6)/(($C$38/$B$6)+(1-$C$38)))*$B$7)/(((($C$38/$B$6)/(($C$38/$B$6)+(1-$C$38)))*$B$7)+(1-(($C$38/$B$6)/(($C$38/$B$6)+(1-$C$38))))))*$B$8)*(1-(1-$B$11)/$B$12)+(1-$B$8)*(1-(1-$B$13)/$B$14))*(1-$B$16)/($B$17-$B$18))*$B$21+$B$23*($B$15*(((1-(((($C$38/$B$6)/(($C$38/$B$6)+(1-$C$38)))*$B$7)/(((($C$38/$B$6)/(($C$38/$B$6)+(1-$C$38)))*$B$7)+(1-(($C$38/$B$6)/(($C$38/$B$6)+(1-$C$38)))))))*$B$8)*(1-(1-$B$9)/$B$10)+((((($C$38/$B$6)/(($C$38/$B$6)+(1-$C$38)))*$B$7)/(((($C$38/$B$6)/(($C$38/$B$6)+(1-$C$38)))*$B$7)+(1-(($C$38/$B$6)/(($C$38/$B$6)+(1-$C$38))))))*$B$8)*(1-(1-$B$11)/$B$12)+(1-$B$8)*(1-(1-$B$13)/$B$14))*(1-$B$16)/($B$17-$B$18))+$B$24*((1-((((($C$38/$B$6)/(($C$38/$B$6)+(1-$C$38)))*$B$7)/(((($C$38/$B$6)/(($C$38/$B$6)+(1-$C$38)))*$B$7)+(1-(($C$38/$B$6)/(($C$38/$B$6)+(1-$C$38))))))*$B$8))*$B$19+((((($C$38/$B$6)/(($C$38/$B$6)+(1-$C$38)))*$B$7)/(((($C$38/$B$6)/(($C$38/$B$6)+(1-$C$38)))*$B$7)+(1-(($C$38/$B$6)/(($C$38/$B$6)+(1-$C$38))))))*$B$8)*$B$20))-$B$28)*$B$26/($B$28-$B$29))*$B$27,"n/a") -> 552.71362 | F38: =IFERROR($B$25+((($B$22*($B$15*(((1-(((($D$38/$B$6)/(($D$38/$B$6)+(1-$D$38)))*$B$7)/(((($D$38/$B$6)/(($D$38/$B$6)+(1-$D$38)))*$B$7)+(1-(($D$38/$B$6)/(($D$38/$B$6)+(1-$D$38)))))))*$B$8)*(1-(1-$B$9)/$B$10)+((((($D$38/$B$6)/(($D$38/$B$6)+(1-$D$38)))*$B$7)/(((($D$38/$B$6)/(($D$38/$B$6)+(1-$D$38)))*$B$7)+(1-(($D$38/$B$6)/(($D$38/$B$6)+(1-$D$38))))))*$B$8)*(1-(1-$B$11)/$B$12)+(1-$B$8)*(1-(1-$B$13)/$B$14))*(1-$B$16)/($B$17-$B$18))*$B$21+$B$23*($B$15*(((1-(((($D$38/$B$6)/(($D$38/$B$6)+(1-$D$38)))*$B$7)/(((($D$38/$B$6)/(($D$38/$B$6)+(1-$D$38)))*$B$7)+(1-(($D$38/$B$6)/(($D$38/$B$6)+(1-$D$38)))))))*$B$8)*(1-(1-$B$9)/$B$10)+((((($D$38/$B$6)/(($D$38/$B$6)+(1-$D$38)))*$B$7)/(((($D$38/$B$6)/(($D$38/$B$6)+(1-$D$38)))*$B$7)+(1-(($D$38/$B$6)/(($D$38/$B$6)+(1-$D$38))))))*$B$8)*(1-(1-$B$11)/$B$12)+(1-$B$8)*(1-(1-$B$13)/$B$14))*(1-$B$16)/($B$17-$B$18))+$B$24*((1-((((($D$38/$B$6)/(($D$38/$B$6)+(1-$D$38)))*$B$7)/(((($D$38/$B$6)/(($D$38/$B$6)+(1-$D$38)))*$B$7)+(1-(($D$38/$B$6)/(($D$38/$B$6)+(1-$D$38))))))*$B$8))*$B$19+((((($D$38/$B$6)/(($D$38/$B$6)+(1-$D$38)))*$B$7)/(((($D$38/$B$6)/(($D$38/$B$6)+(1-$D$38)))*$B$7)+(1-(($D$38/$B$6)/(($D$38/$B$6)+(1-$D$38))))))*$B$8)*$B$20))-$B$28)*$B$26/($B$28-$B$29))*$B$27,"n/a") -> 568.70977 | G38: =IFERROR(ABS(F38-E38),"n/a") -> 15.996159 | H38: =IFERROR(G38/$B$32,"n/a") -> 0.028536661 | I38: +/-5pp — as suggested in review
A39: Trade ratio (FY2029) | B39: =$B$6 -> 3.1 | C39: =$B$6-0.3 -> 2.8 | D39: =$B$6+0.3 -> 3.4 | E39: =IFERROR($B$25+((($B$22*($B$15*(((1-(((($B$5/$C$39)/(($B$5/$C$39)+(1-$B$5)))*$B$7)/(((($B$5/$C$39)/(($B$5/$C$39)+(1-$B$5)))*$B$7)+(1-(($B$5/$C$39)/(($B$5/$C$39)+(1-$B$5)))))))*$B$8)*(1-(1-$B$9)/$B$10)+((((($B$5/$C$39)/(($B$5/$C$39)+(1-$B$5)))*$B$7)/(((($B$5/$C$39)/(($B$5/$C$39)+(1-$B$5)))*$B$7)+(1-(($B$5/$C$39)/(($B$5/$C$39)+(1-$B$5))))))*$B$8)*(1-(1-$B$11)/$B$12)+(1-$B$8)*(1-(1-$B$13)/$B$14))*(1-$B$16)/($B$17-$B$18))*$B$21+$B$23*($B$15*(((1-(((($B$5/$C$39)/(($B$5/$C$39)+(1-$B$5)))*$B$7)/(((($B$5/$C$39)/(($B$5/$C$39)+(1-$B$5)))*$B$7)+(1-(($B$5/$C$39)/(($B$5/$C$39)+(1-$B$5)))))))*$B$8)*(1-(1-$B$9)/$B$10)+((((($B$5/$C$39)/(($B$5/$C$39)+(1-$B$5)))*$B$7)/(((($B$5/$C$39)/(($B$5/$C$39)+(1-$B$5)))*$B$7)+(1-(($B$5/$C$39)/(($B$5/$C$39)+(1-$B$5))))))*$B$8)*(1-(1-$B$11)/$B$12)+(1-$B$8)*(1-(1-$B$13)/$B$14))*(1-$B$16)/($B$17-$B$18))+$B$24*((1-((((($B$5/$C$39)/(($B$5/$C$39)+(1-$B$5)))*$B$7)/(((($B$5/$C$39)/(($B$5/$C$39)+(1-$B$5)))*$B$7)+(1-(($B$5/$C$39)/(($B$5/$C$39)+(1-$B$5))))))*$B$8))*$B$19+((((($B$5/$C$39)/(($B$5/$C$39)+(1-$B$5)))*$B$7)/(((($B$5/$C$39)/(($B$5/$C$39)+(1-$B$5)))*$B$7)+(1-(($B$5/$C$39)/(($B$5/$C$39)+(1-$B$5))))))*$B$8)*$B$20))-$B$28)*$B$26/($B$28-$B$29))*$B$27,"n/a") -> 564.46494 | F39: =IFERROR($B$25+((($B$22*($B$15*(((1-(((($B$5/$D$39)/(($B$5/$D$39)+(1-$B$5)))*$B$7)/(((($B$5/$D$39)/(($B$5/$D$39)+(1-$B$5)))*$B$7)+(1-(($B$5/$D$39)/(($B$5/$D$39)+(1-$B$5)))))))*$B$8)*(1-(1-$B$9)/$B$10)+((((($B$5/$D$39)/(($B$5/$D$39)+(1-$B$5)))*$B$7)/(((($B$5/$D$39)/(($B$5/$D$39)+(1-$B$5)))*$B$7)+(1-(($B$5/$D$39)/(($B$5/$D$39)+(1-$B$5))))))*$B$8)*(1-(1-$B$11)/$B$12)+(1-$B$8)*(1-(1-$B$13)/$B$14))*(1-$B$16)/($B$17-$B$18))*$B$21+$B$23*($B$15*(((1-(((($B$5/$D$39)/(($B$5/$D$39)+(1-$B$5)))*$B$7)/(((($B$5/$D$39)/(($B$5/$D$39)+(1-$B$5)))*$B$7)+(1-(($B$5/$D$39)/(($B$5/$D$39)+(1-$B$5)))))))*$B$8)*(1-(1-$B$9)/$B$10)+((((($B$5/$D$39)/(($B$5/$D$39)+(1-$B$5)))*$B$7)/(((($B$5/$D$39)/(($B$5/$D$39)+(1-$B$5)))*$B$7)+(1-(($B$5/$D$39)/(($B$5/$D$39)+(1-$B$5))))))*$B$8)*(1-(1-$B$11)/$B$12)+(1-$B$8)*(1-(1-$B$13)/$B$14))*(1-$B$16)/($B$17-$B$18))+$B$24*((1-((((($B$5/$D$39)/(($B$5/$D$39)+(1-$B$5)))*$B$7)/(((($B$5/$D$39)/(($B$5/$D$39)+(1-$B$5)))*$B$7)+(1-(($B$5/$D$39)/(($B$5/$D$39)+(1-$B$5))))))*$B$8))*$B$19+((((($B$5/$D$39)/(($B$5/$D$39)+(1-$B$5)))*$B$7)/(((($B$5/$D$39)/(($B$5/$D$39)+(1-$B$5)))*$B$7)+(1-(($B$5/$D$39)/(($B$5/$D$39)+(1-$B$5))))))*$B$8)*$B$20))-$B$28)*$B$26/($B$28-$B$29))*$B$27,"n/a") -> 557.13852 | G39: =IFERROR(ABS(F39-E39),"n/a") -> 7.326418 | H39: =IFERROR(G39/$B$32,"n/a") -> 0.013070107 | I39: +/-0.30x — the HBM4 to HBM4E step
A40: ASP premium (FY2029) | B40: =$B$7 -> 2 | C40: =$B$7-1 -> 1 | D40: =$B$7+1 -> 3 | E40: =IFERROR($B$25+((($B$22*($B$15*(((1-(((($B$5/$B$6)/(($B$5/$B$6)+(1-$B$5)))*$C$40)/(((($B$5/$B$6)/(($B$5/$B$6)+(1-$B$5)))*$C$40)+(1-(($B$5/$B$6)/(($B$5/$B$6)+(1-$B$5)))))))*$B$8)*(1-(1-$B$9)/$B$10)+((((($B$5/$B$6)/(($B$5/$B$6)+(1-$B$5)))*$C$40)/(((($B$5/$B$6)/(($B$5/$B$6)+(1-$B$5)))*$C$40)+(1-(($B$5/$B$6)/(($B$5/$B$6)+(1-$B$5))))))*$B$8)*(1-(1-$B$11)/$B$12)+(1-$B$8)*(1-(1-$B$13)/$B$14))*(1-$B$16)/($B$17-$B$18))*$B$21+$B$23*($B$15*(((1-(((($B$5/$B$6)/(($B$5/$B$6)+(1-$B$5)))*$C$40)/(((($B$5/$B$6)/(($B$5/$B$6)+(1-$B$5)))*$C$40)+(1-(($B$5/$B$6)/(($B$5/$B$6)+(1-$B$5)))))))*$B$8)*(1-(1-$B$9)/$B$10)+((((($B$5/$B$6)/(($B$5/$B$6)+(1-$B$5)))*$C$40)/(((($B$5/$B$6)/(($B$5/$B$6)+(1-$B$5)))*$C$40)+(1-(($B$5/$B$6)/(($B$5/$B$6)+(1-$B$5))))))*$B$8)*(1-(1-$B$11)/$B$12)+(1-$B$8)*(1-(1-$B$13)/$B$14))*(1-$B$16)/($B$17-$B$18))+$B$24*((1-((((($B$5/$B$6)/(($B$5/$B$6)+(1-$B$5)))*$C$40)/(((($B$5/$B$6)/(($B$5/$B$6)+(1-$B$5)))*$C$40)+(1-(($B$5/$B$6)/(($B$5/$B$6)+(1-$B$5))))))*$B$8))*$B$19+((((($B$5/$B$6)/(($B$5/$B$6)+(1-$B$5)))*$C$40)/(((($B$5/$B$6)/(($B$5/$B$6)+(1-$B$5)))*$C$40)+(1-(($B$5/$B$6)/(($B$5/$B$6)+(1-$B$5))))))*$B$8)*$B$20))-$B$28)*$B$26/($B$28-$B$29))*$B$27,"n/a") -> 538.60287 | F40: =IFERROR($B$25+((($B$22*($B$15*(((1-(((($B$5/$B$6)/(($B$5/$B$6)+(1-$B$5)))*$D$40)/(((($B$5/$B$6)/(($B$5/$B$6)+(1-$B$5)))*$D$40)+(1-(($B$5/$B$6)/(($B$5/$B$6)+(1-$B$5)))))))*$B$8)*(1-(1-$B$9)/$B$10)+((((($B$5/$B$6)/(($B$5/$B$6)+(1-$B$5)))*$D$40)/(((($B$5/$B$6)/(($B$5/$B$6)+(1-$B$5)))*$D$40)+(1-(($B$5/$B$6)/(($B$5/$B$6)+(1-$B$5))))))*$B$8)*(1-(1-$B$11)/$B$12)+(1-$B$8)*(1-(1-$B$13)/$B$14))*(1-$B$16)/($B$17-$B$18))*$B$21+$B$23*($B$15*(((1-(((($B$5/$B$6)/(($B$5/$B$6)+(1-$B$5)))*$D$40)/(((($B$5/$B$6)/(($B$5/$B$6)+(1-$B$5)))*$D$40)+(1-(($B$5/$B$6)/(($B$5/$B$6)+(1-$B$5)))))))*$B$8)*(1-(1-$B$9)/$B$10)+((((($B$5/$B$6)/(($B$5/$B$6)+(1-$B$5)))*$D$40)/(((($B$5/$B$6)/(($B$5/$B$6)+(1-$B$5)))*$D$40)+(1-(($B$5/$B$6)/(($B$5/$B$6)+(1-$B$5))))))*$B$8)*(1-(1-$B$11)/$B$12)+(1-$B$8)*(1-(1-$B$13)/$B$14))*(1-$B$16)/($B$17-$B$18))+$B$24*((1-((((($B$5/$B$6)/(($B$5/$B$6)+(1-$B$5)))*$D$40)/(((($B$5/$B$6)/(($B$5/$B$6)+(1-$B$5)))*$D$40)+(1-(($B$5/$B$6)/(($B$5/$B$6)+(1-$B$5))))))*$B$8))*$B$19+((((($B$5/$B$6)/(($B$5/$B$6)+(1-$B$5)))*$D$40)/(((($B$5/$B$6)/(($B$5/$B$6)+(1-$B$5)))*$D$40)+(1-(($B$5/$B$6)/(($B$5/$B$6)+(1-$B$5))))))*$B$8)*$B$20))-$B$28)*$B$26/($B$28-$B$29))*$B$27,"n/a") -> 577.0457 | G40: =IFERROR(ABS(F40-E40),"n/a") -> 38.442831 | H40: =IFERROR(G40/$B$32,"n/a") -> 0.06858084 | I40: +/-1.00x — half the gap between cases 2 and 3
A41: Commodity base OPM | B41: =$B$9 -> 0.8 | C41: =$B$9-0.05 -> 0.75 | D41: =$B$9+0.05 -> 0.85 | E41: =IFERROR($B$25+((($B$22*($B$15*(((1-(((($B$5/$B$6)/(($B$5/$B$6)+(1-$B$5)))*$B$7)/(((($B$5/$B$6)/(($B$5/$B$6)+(1-$B$5)))*$B$7)+(1-(($B$5/$B$6)/(($B$5/$B$6)+(1-$B$5)))))))*$B$8)*(1-(1-$C$41)/$B$10)+((((($B$5/$B$6)/(($B$5/$B$6)+(1-$B$5)))*$B$7)/(((($B$5/$B$6)/(($B$5/$B$6)+(1-$B$5)))*$B$7)+(1-(($B$5/$B$6)/(($B$5/$B$6)+(1-$B$5))))))*$B$8)*(1-(1-$B$11)/$B$12)+(1-$B$8)*(1-(1-$B$13)/$B$14))*(1-$B$16)/($B$17-$B$18))*$B$21+$B$23*($B$15*(((1-(((($B$5/$B$6)/(($B$5/$B$6)+(1-$B$5)))*$B$7)/(((($B$5/$B$6)/(($B$5/$B$6)+(1-$B$5)))*$B$7)+(1-(($B$5/$B$6)/(($B$5/$B$6)+(1-$B$5)))))))*$B$8)*(1-(1-$C$41)/$B$10)+((((($B$5/$B$6)/(($B$5/$B$6)+(1-$B$5)))*$B$7)/(((($B$5/$B$6)/(($B$5/$B$6)+(1-$B$5)))*$B$7)+(1-(($B$5/$B$6)/(($B$5/$B$6)+(1-$B$5))))))*$B$8)*(1-(1-$B$11)/$B$12)+(1-$B$8)*(1-(1-$B$13)/$B$14))*(1-$B$16)/($B$17-$B$18))+$B$24*((1-((((($B$5/$B$6)/(($B$5/$B$6)+(1-$B$5)))*$B$7)/(((($B$5/$B$6)/(($B$5/$B$6)+(1-$B$5)))*$B$7)+(1-(($B$5/$B$6)/(($B$5/$B$6)+(1-$B$5))))))*$B$8))*$B$19+((((($B$5/$B$6)/(($B$5/$B$6)+(1-$B$5)))*$B$7)/(((($B$5/$B$6)/(($B$5/$B$6)+(1-$B$5)))*$B$7)+(1-(($B$5/$B$6)/(($B$5/$B$6)+(1-$B$5))))))*$B$8)*$B$20))-$B$28)*$B$26/($B$28-$B$29))*$B$27,"n/a") -> 508.30765 | F41: =IFERROR($B$25+((($B$22*($B$15*(((1-(((($B$5/$B$6)/(($B$5/$B$6)+(1-$B$5)))*$B$7)/(((($B$5/$B$6)/(($B$5/$B$6)+(1-$B$5)))*$B$7)+(1-(($B$5/$B$6)/(($B$5/$B$6)+(1-$B$5)))))))*$B$8)*(1-(1-$D$41)/$B$10)+((((($B$5/$B$6)/(($B$5/$B$6)+(1-$B$5)))*$B$7)/(((($B$5/$B$6)/(($B$5/$B$6)+(1-$B$5)))*$B$7)+(1-(($B$5/$B$6)/(($B$5/$B$6)+(1-$B$5))))))*$B$8)*(1-(1-$B$11)/$B$12)+(1-$B$8)*(1-(1-$B$13)/$B$14))*(1-$B$16)/($B$17-$B$18))*$B$21+$B$23*($B$15*(((1-(((($B$5/$B$6)/(($B$5/$B$6)+(1-$B$5)))*$B$7)/(((($B$5/$B$6)/(($B$5/$B$6)+(1-$B$5)))*$B$7)+(1-(($B$5/$B$6)/(($B$5/$B$6)+(1-$B$5)))))))*$B$8)*(1-(1-$D$41)/$B$10)+((((($B$5/$B$6)/(($B$5/$B$6)+(1-$B$5)))*$B$7)/(((($B$5/$B$6)/(($B$5/$B$6)+(1-$B$5)))*$B$7)+(1-(($B$5/$B$6)/(($B$5/$B$6)+(1-$B$5))))))*$B$8)*(1-(1-$B$11)/$B$12)+(1-$B$8)*(1-(1-$B$13)/$B$14))*(1-$B$16)/($B$17-$B$18))+$B$24*((1-((((($B$5/$B$6)/(($B$5/$B$6)+(1-$B$5)))*$B$7)/(((($B$5/$B$6)/(($B$5/$B$6)+(1-$B$5)))*$B$7)+(1-(($B$5/$B$6)/(($B$5/$B$6)+(1-$B$5))))))*$B$8))*$B$19+((((($B$5/$B$6)/(($B$5/$B$6)+(1-$B$5)))*$B$7)/(((($B$5/$B$6)/(($B$5/$B$6)+(1-$B$5)))*$B$7)+(1-(($B$5/$B$6)/(($B$5/$B$6)+(1-$B$5))))))*$B$8)*$B$20))-$B$28)*$B$26/($B$28-$B$29))*$B$27,"n/a") -> 612.78771 | G41: =IFERROR(ABS(F41-E41),"n/a") -> 104.48006 | H41: =IFERROR(G41/$B$32,"n/a") -> 0.18638925 | I41: +/-5pp — as suggested in review
A42: Commodity ASP index (FY2029) | B42: =$B$10 -> 0.61 | C42: =$B$10-0.1 -> 0.51 | D42: =$B$10+0.1 -> 0.71 | E42: =IFERROR($B$25+((($B$22*($B$15*(((1-(((($B$5/$B$6)/(($B$5/$B$6)+(1-$B$5)))*$B$7)/(((($B$5/$B$6)/(($B$5/$B$6)+(1-$B$5)))*$B$7)+(1-(($B$5/$B$6)/(($B$5/$B$6)+(1-$B$5)))))))*$B$8)*(1-(1-$B$9)/$C$42)+((((($B$5/$B$6)/(($B$5/$B$6)+(1-$B$5)))*$B$7)/(((($B$5/$B$6)/(($B$5/$B$6)+(1-$B$5)))*$B$7)+(1-(($B$5/$B$6)/(($B$5/$B$6)+(1-$B$5))))))*$B$8)*(1-(1-$B$11)/$B$12)+(1-$B$8)*(1-(1-$B$13)/$B$14))*(1-$B$16)/($B$17-$B$18))*$B$21+$B$23*($B$15*(((1-(((($B$5/$B$6)/(($B$5/$B$6)+(1-$B$5)))*$B$7)/(((($B$5/$B$6)/(($B$5/$B$6)+(1-$B$5)))*$B$7)+(1-(($B$5/$B$6)/(($B$5/$B$6)+(1-$B$5)))))))*$B$8)*(1-(1-$B$9)/$C$42)+((((($B$5/$B$6)/(($B$5/$B$6)+(1-$B$5)))*$B$7)/(((($B$5/$B$6)/(($B$5/$B$6)+(1-$B$5)))*$B$7)+(1-(($B$5/$B$6)/(($B$5/$B$6)+(1-$B$5))))))*$B$8)*(1-(1-$B$11)/$B$12)+(1-$B$8)*(1-(1-$B$13)/$B$14))*(1-$B$16)/($B$17-$B$18))+$B$24*((1-((((($B$5/$B$6)/(($B$5/$B$6)+(1-$B$5)))*$B$7)/(((($B$5/$B$6)/(($B$5/$B$6)+(1-$B$5)))*$B$7)+(1-(($B$5/$B$6)/(($B$5/$B$6)+(1-$B$5))))))*$B$8))*$B$19+((((($B$5/$B$6)/(($B$5/$B$6)+(1-$B$5)))*$B$7)/(((($B$5/$B$6)/(($B$5/$B$6)+(1-$B$5)))*$B$7)+(1-(($B$5/$B$6)/(($B$5/$B$6)+(1-$B$5))))))*$B$8)*$B$20))-$B$28)*$B$26/($B$28-$B$29))*$B$27,"n/a") -> 519.5751 | F42: =IFERROR($B$25+((($B$22*($B$15*(((1-(((($B$5/$B$6)/(($B$5/$B$6)+(1-$B$5)))*$B$7)/(((($B$5/$B$6)/(($B$5/$B$6)+(1-$B$5)))*$B$7)+(1-(($B$5/$B$6)/(($B$5/$B$6)+(1-$B$5)))))))*$B$8)*(1-(1-$B$9)/$D$42)+((((($B$5/$B$6)/(($B$5/$B$6)+(1-$B$5)))*$B$7)/(((($B$5/$B$6)/(($B$5/$B$6)+(1-$B$5)))*$B$7)+(1-(($B$5/$B$6)/(($B$5/$B$6)+(1-$B$5))))))*$B$8)*(1-(1-$B$11)/$B$12)+(1-$B$8)*(1-(1-$B$13)/$B$14))*(1-$B$16)/($B$17-$B$18))*$B$21+$B$23*($B$15*(((1-(((($B$5/$B$6)/(($B$5/$B$6)+(1-$B$5)))*$B$7)/(((($B$5/$B$6)/(($B$5/$B$6)+(1-$B$5)))*$B$7)+(1-(($B$5/$B$6)/(($B$5/$B$6)+(1-$B$5)))))))*$B$8)*(1-(1-$B$9)/$D$42)+((((($B$5/$B$6)/(($B$5/$B$6)+(1-$B$5)))*$B$7)/(((($B$5/$B$6)/(($B$5/$B$6)+(1-$B$5)))*$B$7)+(1-(($B$5/$B$6)/(($B$5/$B$6)+(1-$B$5))))))*$B$8)*(1-(1-$B$11)/$B$12)+(1-$B$8)*(1-(1-$B$13)/$B$14))*(1-$B$16)/($B$17-$B$18))+$B$24*((1-((((($B$5/$B$6)/(($B$5/$B$6)+(1-$B$5)))*$B$7)/(((($B$5/$B$6)/(($B$5/$B$6)+(1-$B$5)))*$B$7)+(1-(($B$5/$B$6)/(($B$5/$B$6)+(1-$B$5))))))*$B$8))*$B$19+((((($B$5/$B$6)/(($B$5/$B$6)+(1-$B$5)))*$B$7)/(((($B$5/$B$6)/(($B$5/$B$6)+(1-$B$5)))*$B$7)+(1-(($B$5/$B$6)/(($B$5/$B$6)+(1-$B$5))))))*$B$8)*$B$20))-$B$28)*$B$26/($B$28-$B$29))*$B$27,"n/a") -> 589.97868 | G42: =IFERROR(ABS(F42-E42),"n/a") -> 70.403578 | H42: =IFERROR(G42/$B$32,"n/a") -> 0.12559784 | I42: +/-10% — spot price movement
A43: HBM base OPM | B43: =$B$11 -> 0.5 | C43: =$B$11-0.05 -> 0.45 | D43: =$B$11+0.05 -> 0.55 | E43: =IFERROR($B$25+((($B$22*($B$15*(((1-(((($B$5/$B$6)/(($B$5/$B$6)+(1-$B$5)))*$B$7)/(((($B$5/$B$6)/(($B$5/$B$6)+(1-$B$5)))*$B$7)+(1-(($B$5/$B$6)/(($B$5/$B$6)+(1-$B$5)))))))*$B$8)*(1-(1-$B$9)/$B$10)+((((($B$5/$B$6)/(($B$5/$B$6)+(1-$B$5)))*$B$7)/(((($B$5/$B$6)/(($B$5/$B$6)+(1-$B$5)))*$B$7)+(1-(($B$5/$B$6)/(($B$5/$B$6)+(1-$B$5))))))*$B$8)*(1-(1-$C$43)/$B$12)+(1-$B$8)*(1-(1-$B$13)/$B$14))*(1-$B$16)/($B$17-$B$18))*$B$21+$B$23*($B$15*(((1-(((($B$5/$B$6)/(($B$5/$B$6)+(1-$B$5)))*$B$7)/(((($B$5/$B$6)/(($B$5/$B$6)+(1-$B$5)))*$B$7)+(1-(($B$5/$B$6)/(($B$5/$B$6)+(1-$B$5)))))))*$B$8)*(1-(1-$B$9)/$B$10)+((((($B$5/$B$6)/(($B$5/$B$6)+(1-$B$5)))*$B$7)/(((($B$5/$B$6)/(($B$5/$B$6)+(1-$B$5)))*$B$7)+(1-(($B$5/$B$6)/(($B$5/$B$6)+(1-$B$5))))))*$B$8)*(1-(1-$C$43)/$B$12)+(1-$B$8)*(1-(1-$B$13)/$B$14))*(1-$B$16)/($B$17-$B$18))+$B$24*((1-((((($B$5/$B$6)/(($B$5/$B$6)+(1-$B$5)))*$B$7)/(((($B$5/$B$6)/(($B$5/$B$6)+(1-$B$5)))*$B$7)+(1-(($B$5/$B$6)/(($B$5/$B$6)+(1-$B$5))))))*$B$8))*$B$19+((((($B$5/$B$6)/(($B$5/$B$6)+(1-$B$5)))*$B$7)/(((($B$5/$B$6)/(($B$5/$B$6)+(1-$B$5)))*$B$7)+(1-(($B$5/$B$6)/(($B$5/$B$6)+(1-$B$5))))))*$B$8)*$B$20))-$B$28)*$B$26/($B$28-$B$29))*$B$27,"n/a") -> 553.5082 | F43: =IFERROR($B$25+((($B$22*($B$15*(((1-(((($B$5/$B$6)/(($B$5/$B$6)+(1-$B$5)))*$B$7)/(((($B$5/$B$6)/(($B$5/$B$6)+(1-$B$5)))*$B$7)+(1-(($B$5/$B$6)/(($B$5/$B$6)+(1-$B$5)))))))*$B$8)*(1-(1-$B$9)/$B$10)+((((($B$5/$B$6)/(($B$5/$B$6)+(1-$B$5)))*$B$7)/(((($B$5/$B$6)/(($B$5/$B$6)+(1-$B$5)))*$B$7)+(1-(($B$5/$B$6)/(($B$5/$B$6)+(1-$B$5))))))*$B$8)*(1-(1-$D$43)/$B$12)+(1-$B$8)*(1-(1-$B$13)/$B$14))*(1-$B$16)/($B$17-$B$18))*$B$21+$B$23*($B$15*(((1-(((($B$5/$B$6)/(($B$5/$B$6)+(1-$B$5)))*$B$7)/(((($B$5/$B$6)/(($B$5/$B$6)+(1-$B$5)))*$B$7)+(1-(($B$5/$B$6)/(($B$5/$B$6)+(1-$B$5)))))))*$B$8)*(1-(1-$B$9)/$B$10)+((((($B$5/$B$6)/(($B$5/$B$6)+(1-$B$5)))*$B$7)/(((($B$5/$B$6)/(($B$5/$B$6)+(1-$B$5)))*$B$7)+(1-(($B$5/$B$6)/(($B$5/$B$6)+(1-$B$5))))))*$B$8)*(1-(1-$D$43)/$B$12)+(1-$B$8)*(1-(1-$B$13)/$B$14))*(1-$B$16)/($B$17-$B$18))+$B$24*((1-((((($B$5/$B$6)/(($B$5/$B$6)+(1-$B$5)))*$B$7)/(((($B$5/$B$6)/(($B$5/$B$6)+(1-$B$5)))*$B$7)+(1-(($B$5/$B$6)/(($B$5/$B$6)+(1-$B$5))))))*$B$8))*$B$19+((((($B$5/$B$6)/(($B$5/$B$6)+(1-$B$5)))*$B$7)/(((($B$5/$B$6)/(($B$5/$B$6)+(1-$B$5)))*$B$7)+(1-(($B$5/$B$6)/(($B$5/$B$6)+(1-$B$5))))))*$B$8)*$B$20))-$B$28)*$B$26/($B$28-$B$29))*$B$27,"n/a") -> 567.58716 | G43: =IFERROR(ABS(F43-E43),"n/a") -> 14.078956 | H43: =IFERROR(G43/$B$32,"n/a") -> 0.025116428 | I43: +/-5pp — as suggested in review
A44: HBM ASP index (FY2029) | B44: =$B$12 -> 1.79 | C44: =$B$12-0.2 -> 1.59 | D44: =$B$12+0.2 -> 1.99 | E44: =IFERROR($B$25+((($B$22*($B$15*(((1-(((($B$5/$B$6)/(($B$5/$B$6)+(1-$B$5)))*$B$7)/(((($B$5/$B$6)/(($B$5/$B$6)+(1-$B$5)))*$B$7)+(1-(($B$5/$B$6)/(($B$5/$B$6)+(1-$B$5)))))))*$B$8)*(1-(1-$B$9)/$B$10)+((((($B$5/$B$6)/(($B$5/$B$6)+(1-$B$5)))*$B$7)/(((($B$5/$B$6)/(($B$5/$B$6)+(1-$B$5)))*$B$7)+(1-(($B$5/$B$6)/(($B$5/$B$6)+(1-$B$5))))))*$B$8)*(1-(1-$B$11)/$C$44)+(1-$B$8)*(1-(1-$B$13)/$B$14))*(1-$B$16)/($B$17-$B$18))*$B$21+$B$23*($B$15*(((1-(((($B$5/$B$6)/(($B$5/$B$6)+(1-$B$5)))*$B$7)/(((($B$5/$B$6)/(($B$5/$B$6)+(1-$B$5)))*$B$7)+(1-(($B$5/$B$6)/(($B$5/$B$6)+(1-$B$5)))))))*$B$8)*(1-(1-$B$9)/$B$10)+((((($B$5/$B$6)/(($B$5/$B$6)+(1-$B$5)))*$B$7)/(((($B$5/$B$6)/(($B$5/$B$6)+(1-$B$5)))*$B$7)+(1-(($B$5/$B$6)/(($B$5/$B$6)+(1-$B$5))))))*$B$8)*(1-(1-$B$11)/$C$44)+(1-$B$8)*(1-(1-$B$13)/$B$14))*(1-$B$16)/($B$17-$B$18))+$B$24*((1-((((($B$5/$B$6)/(($B$5/$B$6)+(1-$B$5)))*$B$7)/(((($B$5/$B$6)/(($B$5/$B$6)+(1-$B$5)))*$B$7)+(1-(($B$5/$B$6)/(($B$5/$B$6)+(1-$B$5))))))*$B$8))*$B$19+((((($B$5/$B$6)/(($B$5/$B$6)+(1-$B$5)))*$B$7)/(((($B$5/$B$6)/(($B$5/$B$6)+(1-$B$5)))*$B$7)+(1-(($B$5/$B$6)/(($B$5/$B$6)+(1-$B$5))))))*$B$8)*$B$20))-$B$28)*$B$26/($B$28-$B$29))*$B$27,"n/a") -> 551.69299 | F44: =IFERROR($B$25+((($B$22*($B$15*(((1-(((($B$5/$B$6)/(($B$5/$B$6)+(1-$B$5)))*$B$7)/(((($B$5/$B$6)/(($B$5/$B$6)+(1-$B$5)))*$B$7)+(1-(($B$5/$B$6)/(($B$5/$B$6)+(1-$B$5)))))))*$B$8)*(1-(1-$B$9)/$B$10)+((((($B$5/$B$6)/(($B$5/$B$6)+(1-$B$5)))*$B$7)/(((($B$5/$B$6)/(($B$5/$B$6)+(1-$B$5)))*$B$7)+(1-(($B$5/$B$6)/(($B$5/$B$6)+(1-$B$5))))))*$B$8)*(1-(1-$B$11)/$D$44)+(1-$B$8)*(1-(1-$B$13)/$B$14))*(1-$B$16)/($B$17-$B$18))*$B$21+$B$23*($B$15*(((1-(((($B$5/$B$6)/(($B$5/$B$6)+(1-$B$5)))*$B$7)/(((($B$5/$B$6)/(($B$5/$B$6)+(1-$B$5)))*$B$7)+(1-(($B$5/$B$6)/(($B$5/$B$6)+(1-$B$5)))))))*$B$8)*(1-(1-$B$9)/$B$10)+((((($B$5/$B$6)/(($B$5/$B$6)+(1-$B$5)))*$B$7)/(((($B$5/$B$6)/(($B$5/$B$6)+(1-$B$5)))*$B$7)+(1-(($B$5/$B$6)/(($B$5/$B$6)+(1-$B$5))))))*$B$8)*(1-(1-$B$11)/$D$44)+(1-$B$8)*(1-(1-$B$13)/$B$14))*(1-$B$16)/($B$17-$B$18))+$B$24*((1-((((($B$5/$B$6)/(($B$5/$B$6)+(1-$B$5)))*$B$7)/(((($B$5/$B$6)/(($B$5/$B$6)+(1-$B$5)))*$B$7)+(1-(($B$5/$B$6)/(($B$5/$B$6)+(1-$B$5))))))*$B$8))*$B$19+((((($B$5/$B$6)/(($B$5/$B$6)+(1-$B$5)))*$B$7)/(((($B$5/$B$6)/(($B$5/$B$6)+(1-$B$5)))*$B$7)+(1-(($B$5/$B$6)/(($B$5/$B$6)+(1-$B$5))))))*$B$8)*$B$20))-$B$28)*$B$26/($B$28-$B$29))*$B$27,"n/a") -> 567.62253 | G44: =IFERROR(ABS(F44-E44),"n/a") -> 15.929541 | H44: =IFERROR(G44/$B$32,"n/a") -> 0.028417817 | I44: +/-20% — contract negotiation range
A45: Average buyback deduction ($m) | B45: =$B$18 -> 105000 | C45: =$B$18-50000 -> 55000 | D45: =$B$18+50000 -> 155000 | E45: =IFERROR($B$25+((($B$22*($B$15*(((1-(((($B$5/$B$6)/(($B$5/$B$6)+(1-$B$5)))*$B$7)/(((($B$5/$B$6)/(($B$5/$B$6)+(1-$B$5)))*$B$7)+(1-(($B$5/$B$6)/(($B$5/$B$6)+(1-$B$5)))))))*$B$8)*(1-(1-$B$9)/$B$10)+((((($B$5/$B$6)/(($B$5/$B$6)+(1-$B$5)))*$B$7)/(((($B$5/$B$6)/(($B$5/$B$6)+(1-$B$5)))*$B$7)+(1-(($B$5/$B$6)/(($B$5/$B$6)+(1-$B$5))))))*$B$8)*(1-(1-$B$11)/$B$12)+(1-$B$8)*(1-(1-$B$13)/$B$14))*(1-$B$16)/($B$17-$C$45))*$B$21+$B$23*($B$15*(((1-(((($B$5/$B$6)/(($B$5/$B$6)+(1-$B$5)))*$B$7)/(((($B$5/$B$6)/(($B$5/$B$6)+(1-$B$5)))*$B$7)+(1-(($B$5/$B$6)/(($B$5/$B$6)+(1-$B$5)))))))*$B$8)*(1-(1-$B$9)/$B$10)+((((($B$5/$B$6)/(($B$5/$B$6)+(1-$B$5)))*$B$7)/(((($B$5/$B$6)/(($B$5/$B$6)+(1-$B$5)))*$B$7)+(1-(($B$5/$B$6)/(($B$5/$B$6)+(1-$B$5))))))*$B$8)*(1-(1-$B$11)/$B$12)+(1-$B$8)*(1-(1-$B$13)/$B$14))*(1-$B$16)/($B$17-$C$45))+$B$24*((1-((((($B$5/$B$6)/(($B$5/$B$6)+(1-$B$5)))*$B$7)/(((($B$5/$B$6)/(($B$5/$B$6)+(1-$B$5)))*$B$7)+(1-(($B$5/$B$6)/(($B$5/$B$6)+(1-$B$5))))))*$B$8))*$B$19+((((($B$5/$B$6)/(($B$5/$B$6)+(1-$B$5)))*$B$7)/(((($B$5/$B$6)/(($B$5/$B$6)+(1-$B$5)))*$B$7)+(1-(($B$5/$B$6)/(($B$5/$B$6)+(1-$B$5))))))*$B$8)*$B$20))-$B$28)*$B$26/($B$28-$B$29))*$B$27,"n/a") -> 497.9044 | F45: =IFERROR($B$25+((($B$22*($B$15*(((1-(((($B$5/$B$6)/(($B$5/$B$6)+(1-$B$5)))*$B$7)/(((($B$5/$B$6)/(($B$5/$B$6)+(1-$B$5)))*$B$7)+(1-(($B$5/$B$6)/(($B$5/$B$6)+(1-$B$5)))))))*$B$8)*(1-(1-$B$9)/$B$10)+((((($B$5/$B$6)/(($B$5/$B$6)+(1-$B$5)))*$B$7)/(((($B$5/$B$6)/(($B$5/$B$6)+(1-$B$5)))*$B$7)+(1-(($B$5/$B$6)/(($B$5/$B$6)+(1-$B$5))))))*$B$8)*(1-(1-$B$11)/$B$12)+(1-$B$8)*(1-(1-$B$13)/$B$14))*(1-$B$16)/($B$17-$D$45))*$B$21+$B$23*($B$15*(((1-(((($B$5/$B$6)/(($B$5/$B$6)+(1-$B$5)))*$B$7)/(((($B$5/$B$6)/(($B$5/$B$6)+(1-$B$5)))*$B$7)+(1-(($B$5/$B$6)/(($B$5/$B$6)+(1-$B$5)))))))*$B$8)*(1-(1-$B$9)/$B$10)+((((($B$5/$B$6)/(($B$5/$B$6)+(1-$B$5)))*$B$7)/(((($B$5/$B$6)/(($B$5/$B$6)+(1-$B$5)))*$B$7)+(1-(($B$5/$B$6)/(($B$5/$B$6)+(1-$B$5))))))*$B$8)*(1-(1-$B$11)/$B$12)+(1-$B$8)*(1-(1-$B$13)/$B$14))*(1-$B$16)/($B$17-$D$45))+$B$24*((1-((((($B$5/$B$6)/(($B$5/$B$6)+(1-$B$5)))*$B$7)/(((($B$5/$B$6)/(($B$5/$B$6)+(1-$B$5)))*$B$7)+(1-(($B$5/$B$6)/(($B$5/$B$6)+(1-$B$5))))))*$B$8))*$B$19+((((($B$5/$B$6)/(($B$5/$B$6)+(1-$B$5)))*$B$7)/(((($B$5/$B$6)/(($B$5/$B$6)+(1-$B$5)))*$B$7)+(1-(($B$5/$B$6)/(($B$5/$B$6)+(1-$B$5))))))*$B$8)*$B$20))-$B$28)*$B$26/($B$28-$B$29))*$B$27,"n/a") -> 636.9247 | G45: =IFERROR(ABS(F45-E45),"n/a") -> 139.0203 | H45: =IFERROR(G45/$B$32,"n/a") -> 0.24800798 | I45: +/-$50B — within the BofA to UBS range
A46: Contract trough ROE | B46: =$B$20 -> 0.15 | C46: =$B$20-0.1 -> 0.05 | D46: =$B$20+0.1 -> 0.25 | E46: =IFERROR($B$25+((($B$22*($B$15*(((1-(((($B$5/$B$6)/(($B$5/$B$6)+(1-$B$5)))*$B$7)/(((($B$5/$B$6)/(($B$5/$B$6)+(1-$B$5)))*$B$7)+(1-(($B$5/$B$6)/(($B$5/$B$6)+(1-$B$5)))))))*$B$8)*(1-(1-$B$9)/$B$10)+((((($B$5/$B$6)/(($B$5/$B$6)+(1-$B$5)))*$B$7)/(((($B$5/$B$6)/(($B$5/$B$6)+(1-$B$5)))*$B$7)+(1-(($B$5/$B$6)/(($B$5/$B$6)+(1-$B$5))))))*$B$8)*(1-(1-$B$11)/$B$12)+(1-$B$8)*(1-(1-$B$13)/$B$14))*(1-$B$16)/($B$17-$B$18))*$B$21+$B$23*($B$15*(((1-(((($B$5/$B$6)/(($B$5/$B$6)+(1-$B$5)))*$B$7)/(((($B$5/$B$6)/(($B$5/$B$6)+(1-$B$5)))*$B$7)+(1-(($B$5/$B$6)/(($B$5/$B$6)+(1-$B$5)))))))*$B$8)*(1-(1-$B$9)/$B$10)+((((($B$5/$B$6)/(($B$5/$B$6)+(1-$B$5)))*$B$7)/(((($B$5/$B$6)/(($B$5/$B$6)+(1-$B$5)))*$B$7)+(1-(($B$5/$B$6)/(($B$5/$B$6)+(1-$B$5))))))*$B$8)*(1-(1-$B$11)/$B$12)+(1-$B$8)*(1-(1-$B$13)/$B$14))*(1-$B$16)/($B$17-$B$18))+$B$24*((1-((((($B$5/$B$6)/(($B$5/$B$6)+(1-$B$5)))*$B$7)/(((($B$5/$B$6)/(($B$5/$B$6)+(1-$B$5)))*$B$7)+(1-(($B$5/$B$6)/(($B$5/$B$6)+(1-$B$5))))))*$B$8))*$B$19+((((($B$5/$B$6)/(($B$5/$B$6)+(1-$B$5)))*$B$7)/(((($B$5/$B$6)/(($B$5/$B$6)+(1-$B$5)))*$B$7)+(1-(($B$5/$B$6)/(($B$5/$B$6)+(1-$B$5))))))*$B$8)*$C$46))-$B$28)*$B$26/($B$28-$B$29))*$B$27,"n/a") -> 545.82705 | F46: =IFERROR($B$25+((($B$22*($B$15*(((1-(((($B$5/$B$6)/(($B$5/$B$6)+(1-$B$5)))*$B$7)/(((($B$5/$B$6)/(($B$5/$B$6)+(1-$B$5)))*$B$7)+(1-(($B$5/$B$6)/(($B$5/$B$6)+(1-$B$5)))))))*$B$8)*(1-(1-$B$9)/$B$10)+((((($B$5/$B$6)/(($B$5/$B$6)+(1-$B$5)))*$B$7)/(((($B$5/$B$6)/(($B$5/$B$6)+(1-$B$5)))*$B$7)+(1-(($B$5/$B$6)/(($B$5/$B$6)+(1-$B$5))))))*$B$8)*(1-(1-$B$11)/$B$12)+(1-$B$8)*(1-(1-$B$13)/$B$14))*(1-$B$16)/($B$17-$B$18))*$B$21+$B$23*($B$15*(((1-(((($B$5/$B$6)/(($B$5/$B$6)+(1-$B$5)))*$B$7)/(((($B$5/$B$6)/(($B$5/$B$6)+(1-$B$5)))*$B$7)+(1-(($B$5/$B$6)/(($B$5/$B$6)+(1-$B$5)))))))*$B$8)*(1-(1-$B$9)/$B$10)+((((($B$5/$B$6)/(($B$5/$B$6)+(1-$B$5)))*$B$7)/(((($B$5/$B$6)/(($B$5/$B$6)+(1-$B$5)))*$B$7)+(1-(($B$5/$B$6)/(($B$5/$B$6)+(1-$B$5))))))*$B$8)*(1-(1-$B$11)/$B$12)+(1-$B$8)*(1-(1-$B$13)/$B$14))*(1-$B$16)/($B$17-$B$18))+$B$24*((1-((((($B$5/$B$6)/(($B$5/$B$6)+(1-$B$5)))*$B$7)/(((($B$5/$B$6)/(($B$5/$B$6)+(1-$B$5)))*$B$7)+(1-(($B$5/$B$6)/(($B$5/$B$6)+(1-$B$5))))))*$B$8))*$B$19+((((($B$5/$B$6)/(($B$5/$B$6)+(1-$B$5)))*$B$7)/(((($B$5/$B$6)/(($B$5/$B$6)+(1-$B$5)))*$B$7)+(1-(($B$5/$B$6)/(($B$5/$B$6)+(1-$B$5))))))*$B$8)*$D$46))-$B$28)*$B$26/($B$28-$B$29))*$B$27,"n/a") -> 575.26831 | G46: =IFERROR(ABS(F46-E46),"n/a") -> 29.441261 | H46: =IFERROR(G46/$B$32,"n/a") -> 0.052522313 | I46: +/-10pp — zero observations, so a wide range
A47: Peak multiple | B47: =$B$21 -> 1.5 | C47: =$B$21-0.25 -> 1.25 | D47: =$B$21+0.25 -> 1.75 | E47: =IFERROR($B$25+((($B$22*($B$15*(((1-(((($B$5/$B$6)/(($B$5/$B$6)+(1-$B$5)))*$B$7)/(((($B$5/$B$6)/(($B$5/$B$6)+(1-$B$5)))*$B$7)+(1-(($B$5/$B$6)/(($B$5/$B$6)+(1-$B$5)))))))*$B$8)*(1-(1-$B$9)/$B$10)+((((($B$5/$B$6)/(($B$5/$B$6)+(1-$B$5)))*$B$7)/(((($B$5/$B$6)/(($B$5/$B$6)+(1-$B$5)))*$B$7)+(1-(($B$5/$B$6)/(($B$5/$B$6)+(1-$B$5))))))*$B$8)*(1-(1-$B$11)/$B$12)+(1-$B$8)*(1-(1-$B$13)/$B$14))*(1-$B$16)/($B$17-$B$18))*$C$47+$B$23*($B$15*(((1-(((($B$5/$B$6)/(($B$5/$B$6)+(1-$B$5)))*$B$7)/(((($B$5/$B$6)/(($B$5/$B$6)+(1-$B$5)))*$B$7)+(1-(($B$5/$B$6)/(($B$5/$B$6)+(1-$B$5)))))))*$B$8)*(1-(1-$B$9)/$B$10)+((((($B$5/$B$6)/(($B$5/$B$6)+(1-$B$5)))*$B$7)/(((($B$5/$B$6)/(($B$5/$B$6)+(1-$B$5)))*$B$7)+(1-(($B$5/$B$6)/(($B$5/$B$6)+(1-$B$5))))))*$B$8)*(1-(1-$B$11)/$B$12)+(1-$B$8)*(1-(1-$B$13)/$B$14))*(1-$B$16)/($B$17-$B$18))+$B$24*((1-((((($B$5/$B$6)/(($B$5/$B$6)+(1-$B$5)))*$B$7)/(((($B$5/$B$6)/(($B$5/$B$6)+(1-$B$5)))*$B$7)+(1-(($B$5/$B$6)/(($B$5/$B$6)+(1-$B$5))))))*$B$8))*$B$19+((((($B$5/$B$6)/(($B$5/$B$6)+(1-$B$5)))*$B$7)/(((($B$5/$B$6)/(($B$5/$B$6)+(1-$B$5)))*$B$7)+(1-(($B$5/$B$6)/(($B$5/$B$6)+(1-$B$5))))))*$B$8)*$B$20))-$B$28)*$B$26/($B$28-$B$29))*$B$27,"n/a") -> 510.77969 | F47: =IFERROR($B$25+((($B$22*($B$15*(((1-(((($B$5/$B$6)/(($B$5/$B$6)+(1-$B$5)))*$B$7)/(((($B$5/$B$6)/(($B$5/$B$6)+(1-$B$5)))*$B$7)+(1-(($B$5/$B$6)/(($B$5/$B$6)+(1-$B$5)))))))*$B$8)*(1-(1-$B$9)/$B$10)+((((($B$5/$B$6)/(($B$5/$B$6)+(1-$B$5)))*$B$7)/(((($B$5/$B$6)/(($B$5/$B$6)+(1-$B$5)))*$B$7)+(1-(($B$5/$B$6)/(($B$5/$B$6)+(1-$B$5))))))*$B$8)*(1-(1-$B$11)/$B$12)+(1-$B$8)*(1-(1-$B$13)/$B$14))*(1-$B$16)/($B$17-$B$18))*$D$47+$B$23*($B$15*(((1-(((($B$5/$B$6)/(($B$5/$B$6)+(1-$B$5)))*$B$7)/(((($B$5/$B$6)/(($B$5/$B$6)+(1-$B$5)))*$B$7)+(1-(($B$5/$B$6)/(($B$5/$B$6)+(1-$B$5)))))))*$B$8)*(1-(1-$B$9)/$B$10)+((((($B$5/$B$6)/(($B$5/$B$6)+(1-$B$5)))*$B$7)/(((($B$5/$B$6)/(($B$5/$B$6)+(1-$B$5)))*$B$7)+(1-(($B$5/$B$6)/(($B$5/$B$6)+(1-$B$5))))))*$B$8)*(1-(1-$B$11)/$B$12)+(1-$B$8)*(1-(1-$B$13)/$B$14))*(1-$B$16)/($B$17-$B$18))+$B$24*((1-((((($B$5/$B$6)/(($B$5/$B$6)+(1-$B$5)))*$B$7)/(((($B$5/$B$6)/(($B$5/$B$6)+(1-$B$5)))*$B$7)+(1-(($B$5/$B$6)/(($B$5/$B$6)+(1-$B$5))))))*$B$8))*$B$19+((((($B$5/$B$6)/(($B$5/$B$6)+(1-$B$5)))*$B$7)/(((($B$5/$B$6)/(($B$5/$B$6)+(1-$B$5)))*$B$7)+(1-(($B$5/$B$6)/(($B$5/$B$6)+(1-$B$5))))))*$B$8)*$B$20))-$B$28)*$B$26/($B$28-$B$29))*$B$27,"n/a") -> 610.31567 | G47: =IFERROR(ABS(F47-E47),"n/a") -> 99.535976 | H47: =IFERROR(G47/$B$32,"n/a") -> 0.17756915 | I47: +/-0.25x
A48: FY2028 BPS (terminal equity) | B48: =$B$26 -> 437.94 | C48: =$B$26-24.27 -> 413.67 | D48: =$B$26+24.27 -> 462.21 | E48: =IFERROR($B$25+((($B$22*($B$15*(((1-(((($B$5/$B$6)/(($B$5/$B$6)+(1-$B$5)))*$B$7)/(((($B$5/$B$6)/(($B$5/$B$6)+(1-$B$5)))*$B$7)+(1-(($B$5/$B$6)/(($B$5/$B$6)+(1-$B$5)))))))*$B$8)*(1-(1-$B$9)/$B$10)+((((($B$5/$B$6)/(($B$5/$B$6)+(1-$B$5)))*$B$7)/(((($B$5/$B$6)/(($B$5/$B$6)+(1-$B$5)))*$B$7)+(1-(($B$5/$B$6)/(($B$5/$B$6)+(1-$B$5))))))*$B$8)*(1-(1-$B$11)/$B$12)+(1-$B$8)*(1-(1-$B$13)/$B$14))*(1-$B$16)/($B$17-$B$18))*$B$21+$B$23*($B$15*(((1-(((($B$5/$B$6)/(($B$5/$B$6)+(1-$B$5)))*$B$7)/(((($B$5/$B$6)/(($B$5/$B$6)+(1-$B$5)))*$B$7)+(1-(($B$5/$B$6)/(($B$5/$B$6)+(1-$B$5)))))))*$B$8)*(1-(1-$B$9)/$B$10)+((((($B$5/$B$6)/(($B$5/$B$6)+(1-$B$5)))*$B$7)/(((($B$5/$B$6)/(($B$5/$B$6)+(1-$B$5)))*$B$7)+(1-(($B$5/$B$6)/(($B$5/$B$6)+(1-$B$5))))))*$B$8)*(1-(1-$B$11)/$B$12)+(1-$B$8)*(1-(1-$B$13)/$B$14))*(1-$B$16)/($B$17-$B$18))+$B$24*((1-((((($B$5/$B$6)/(($B$5/$B$6)+(1-$B$5)))*$B$7)/(((($B$5/$B$6)/(($B$5/$B$6)+(1-$B$5)))*$B$7)+(1-(($B$5/$B$6)/(($B$5/$B$6)+(1-$B$5))))))*$B$8))*$B$19+((((($B$5/$B$6)/(($B$5/$B$6)+(1-$B$5)))*$B$7)/(((($B$5/$B$6)/(($B$5/$B$6)+(1-$B$5)))*$B$7)+(1-(($B$5/$B$6)/(($B$5/$B$6)+(1-$B$5))))))*$B$8)*$B$20))-$B$28)*$C$48/($B$28-$B$29))*$B$27,"n/a") -> 547.19342 | F48: =IFERROR($B$25+((($B$22*($B$15*(((1-(((($B$5/$B$6)/(($B$5/$B$6)+(1-$B$5)))*$B$7)/(((($B$5/$B$6)/(($B$5/$B$6)+(1-$B$5)))*$B$7)+(1-(($B$5/$B$6)/(($B$5/$B$6)+(1-$B$5)))))))*$B$8)*(1-(1-$B$9)/$B$10)+((((($B$5/$B$6)/(($B$5/$B$6)+(1-$B$5)))*$B$7)/(((($B$5/$B$6)/(($B$5/$B$6)+(1-$B$5)))*$B$7)+(1-(($B$5/$B$6)/(($B$5/$B$6)+(1-$B$5))))))*$B$8)*(1-(1-$B$11)/$B$12)+(1-$B$8)*(1-(1-$B$13)/$B$14))*(1-$B$16)/($B$17-$B$18))*$B$21+$B$23*($B$15*(((1-(((($B$5/$B$6)/(($B$5/$B$6)+(1-$B$5)))*$B$7)/(((($B$5/$B$6)/(($B$5/$B$6)+(1-$B$5)))*$B$7)+(1-(($B$5/$B$6)/(($B$5/$B$6)+(1-$B$5)))))))*$B$8)*(1-(1-$B$9)/$B$10)+((((($B$5/$B$6)/(($B$5/$B$6)+(1-$B$5)))*$B$7)/(((($B$5/$B$6)/(($B$5/$B$6)+(1-$B$5)))*$B$7)+(1-(($B$5/$B$6)/(($B$5/$B$6)+(1-$B$5))))))*$B$8)*(1-(1-$B$11)/$B$12)+(1-$B$8)*(1-(1-$B$13)/$B$14))*(1-$B$16)/($B$17-$B$18))+$B$24*((1-((((($B$5/$B$6)/(($B$5/$B$6)+(1-$B$5)))*$B$7)/(((($B$5/$B$6)/(($B$5/$B$6)+(1-$B$5)))*$B$7)+(1-(($B$5/$B$6)/(($B$5/$B$6)+(1-$B$5))))))*$B$8))*$B$19+((((($B$5/$B$6)/(($B$5/$B$6)+(1-$B$5)))*$B$7)/(((($B$5/$B$6)/(($B$5/$B$6)+(1-$B$5)))*$B$7)+(1-(($B$5/$B$6)/(($B$5/$B$6)+(1-$B$5))))))*$B$8)*$B$20))-$B$28)*$D$48/($B$28-$B$29))*$B$27,"n/a") -> 573.90193 | G48: =IFERROR(ABS(F48-E48),"n/a") -> 26.708509 | H48: =IFERROR(G48/$B$32,"n/a") -> 0.047647167 | I48: +/-$24.27 — the consensus median versus mean gap
A49: Terminal discount rate | B49: =$B$28 -> 0.16000346 | C49: =$B$28-0.01 -> 0.15000346 | D49: =$B$28+0.01 -> 0.17000346 | E49: =IFERROR($B$25+((($B$22*($B$15*(((1-(((($B$5/$B$6)/(($B$5/$B$6)+(1-$B$5)))*$B$7)/(((($B$5/$B$6)/(($B$5/$B$6)+(1-$B$5)))*$B$7)+(1-(($B$5/$B$6)/(($B$5/$B$6)+(1-$B$5)))))))*$B$8)*(1-(1-$B$9)/$B$10)+((((($B$5/$B$6)/(($B$5/$B$6)+(1-$B$5)))*$B$7)/(((($B$5/$B$6)/(($B$5/$B$6)+(1-$B$5)))*$B$7)+(1-(($B$5/$B$6)/(($B$5/$B$6)+(1-$B$5))))))*$B$8)*(1-(1-$B$11)/$B$12)+(1-$B$8)*(1-(1-$B$13)/$B$14))*(1-$B$16)/($B$17-$B$18))*$B$21+$B$23*($B$15*(((1-(((($B$5/$B$6)/(($B$5/$B$6)+(1-$B$5)))*$B$7)/(((($B$5/$B$6)/(($B$5/$B$6)+(1-$B$5)))*$B$7)+(1-(($B$5/$B$6)/(($B$5/$B$6)+(1-$B$5)))))))*$B$8)*(1-(1-$B$9)/$B$10)+((((($B$5/$B$6)/(($B$5/$B$6)+(1-$B$5)))*$B$7)/(((($B$5/$B$6)/(($B$5/$B$6)+(1-$B$5)))*$B$7)+(1-(($B$5/$B$6)/(($B$5/$B$6)+(1-$B$5))))))*$B$8)*(1-(1-$B$11)/$B$12)+(1-$B$8)*(1-(1-$B$13)/$B$14))*(1-$B$16)/($B$17-$B$18))+$B$24*((1-((((($B$5/$B$6)/(($B$5/$B$6)+(1-$B$5)))*$B$7)/(((($B$5/$B$6)/(($B$5/$B$6)+(1-$B$5)))*$B$7)+(1-(($B$5/$B$6)/(($B$5/$B$6)+(1-$B$5))))))*$B$8))*$B$19+((((($B$5/$B$6)/(($B$5/$B$6)+(1-$B$5)))*$B$7)/(((($B$5/$B$6)/(($B$5/$B$6)+(1-$B$5)))*$B$7)+(1-(($B$5/$B$6)/(($B$5/$B$6)+(1-$B$5))))))*$B$8)*$B$20))-$C$49)*$B$26/($C$49-$B$29))*$B$27,"n/a") -> 610.78881 | F49: =IFERROR($B$25+((($B$22*($B$15*(((1-(((($B$5/$B$6)/(($B$5/$B$6)+(1-$B$5)))*$B$7)/(((($B$5/$B$6)/(($B$5/$B$6)+(1-$B$5)))*$B$7)+(1-(($B$5/$B$6)/(($B$5/$B$6)+(1-$B$5)))))))*$B$8)*(1-(1-$B$9)/$B$10)+((((($B$5/$B$6)/(($B$5/$B$6)+(1-$B$5)))*$B$7)/(((($B$5/$B$6)/(($B$5/$B$6)+(1-$B$5)))*$B$7)+(1-(($B$5/$B$6)/(($B$5/$B$6)+(1-$B$5))))))*$B$8)*(1-(1-$B$11)/$B$12)+(1-$B$8)*(1-(1-$B$13)/$B$14))*(1-$B$16)/($B$17-$B$18))*$B$21+$B$23*($B$15*(((1-(((($B$5/$B$6)/(($B$5/$B$6)+(1-$B$5)))*$B$7)/(((($B$5/$B$6)/(($B$5/$B$6)+(1-$B$5)))*$B$7)+(1-(($B$5/$B$6)/(($B$5/$B$6)+(1-$B$5)))))))*$B$8)*(1-(1-$B$9)/$B$10)+((((($B$5/$B$6)/(($B$5/$B$6)+(1-$B$5)))*$B$7)/(((($B$5/$B$6)/(($B$5/$B$6)+(1-$B$5)))*$B$7)+(1-(($B$5/$B$6)/(($B$5/$B$6)+(1-$B$5))))))*$B$8)*(1-(1-$B$11)/$B$12)+(1-$B$8)*(1-(1-$B$13)/$B$14))*(1-$B$16)/($B$17-$B$18))+$B$24*((1-((((($B$5/$B$6)/(($B$5/$B$6)+(1-$B$5)))*$B$7)/(((($B$5/$B$6)/(($B$5/$B$6)+(1-$B$5)))*$B$7)+(1-(($B$5/$B$6)/(($B$5/$B$6)+(1-$B$5))))))*$B$8))*$B$19+((((($B$5/$B$6)/(($B$5/$B$6)+(1-$B$5)))*$B$7)/(((($B$5/$B$6)/(($B$5/$B$6)+(1-$B$5)))*$B$7)+(1-(($B$5/$B$6)/(($B$5/$B$6)+(1-$B$5))))))*$B$8)*$B$20))-$D$49)*$B$26/($D$49-$B$29))*$B$27,"n/a") -> 518.03575 | G49: =IFERROR(ABS(F49-E49),"n/a") -> 92.75306 | H49: =IFERROR(G49/$B$32,"n/a") -> 0.16546864 | I49: +/-1pp — as suggested in review
A50: Terminal growth rate g | B50: =$B$29 -> 0.04 | C50: =$B$29-0.005 -> 0.035 | D50: =$B$29+0.005 -> 0.045 | E50: =IFERROR($B$25+((($B$22*($B$15*(((1-(((($B$5/$B$6)/(($B$5/$B$6)+(1-$B$5)))*$B$7)/(((($B$5/$B$6)/(($B$5/$B$6)+(1-$B$5)))*$B$7)+(1-(($B$5/$B$6)/(($B$5/$B$6)+(1-$B$5)))))))*$B$8)*(1-(1-$B$9)/$B$10)+((((($B$5/$B$6)/(($B$5/$B$6)+(1-$B$5)))*$B$7)/(((($B$5/$B$6)/(($B$5/$B$6)+(1-$B$5)))*$B$7)+(1-(($B$5/$B$6)/(($B$5/$B$6)+(1-$B$5))))))*$B$8)*(1-(1-$B$11)/$B$12)+(1-$B$8)*(1-(1-$B$13)/$B$14))*(1-$B$16)/($B$17-$B$18))*$B$21+$B$23*($B$15*(((1-(((($B$5/$B$6)/(($B$5/$B$6)+(1-$B$5)))*$B$7)/(((($B$5/$B$6)/(($B$5/$B$6)+(1-$B$5)))*$B$7)+(1-(($B$5/$B$6)/(($B$5/$B$6)+(1-$B$5)))))))*$B$8)*(1-(1-$B$9)/$B$10)+((((($B$5/$B$6)/(($B$5/$B$6)+(1-$B$5)))*$B$7)/(((($B$5/$B$6)/(($B$5/$B$6)+(1-$B$5)))*$B$7)+(1-(($B$5/$B$6)/(($B$5/$B$6)+(1-$B$5))))))*$B$8)*(1-(1-$B$11)/$B$12)+(1-$B$8)*(1-(1-$B$13)/$B$14))*(1-$B$16)/($B$17-$B$18))+$B$24*((1-((((($B$5/$B$6)/(($B$5/$B$6)+(1-$B$5)))*$B$7)/(((($B$5/$B$6)/(($B$5/$B$6)+(1-$B$5)))*$B$7)+(1-(($B$5/$B$6)/(($B$5/$B$6)+(1-$B$5))))))*$B$8))*$B$19+((((($B$5/$B$6)/(($B$5/$B$6)+(1-$B$5)))*$B$7)/(((($B$5/$B$6)/(($B$5/$B$6)+(1-$B$5)))*$B$7)+(1-(($B$5/$B$6)/(($B$5/$B$6)+(1-$B$5))))))*$B$8)*$B$20))-$B$28)*$B$26/($B$28-$C$50))*$B$27,"n/a") -> 550.90911 | F50: =IFERROR($B$25+((($B$22*($B$15*(((1-(((($B$5/$B$6)/(($B$5/$B$6)+(1-$B$5)))*$B$7)/(((($B$5/$B$6)/(($B$5/$B$6)+(1-$B$5)))*$B$7)+(1-(($B$5/$B$6)/(($B$5/$B$6)+(1-$B$5)))))))*$B$8)*(1-(1-$B$9)/$B$10)+((((($B$5/$B$6)/(($B$5/$B$6)+(1-$B$5)))*$B$7)/(((($B$5/$B$6)/(($B$5/$B$6)+(1-$B$5)))*$B$7)+(1-(($B$5/$B$6)/(($B$5/$B$6)+(1-$B$5))))))*$B$8)*(1-(1-$B$11)/$B$12)+(1-$B$8)*(1-(1-$B$13)/$B$14))*(1-$B$16)/($B$17-$B$18))*$B$21+$B$23*($B$15*(((1-(((($B$5/$B$6)/(($B$5/$B$6)+(1-$B$5)))*$B$7)/(((($B$5/$B$6)/(($B$5/$B$6)+(1-$B$5)))*$B$7)+(1-(($B$5/$B$6)/(($B$5/$B$6)+(1-$B$5)))))))*$B$8)*(1-(1-$B$9)/$B$10)+((((($B$5/$B$6)/(($B$5/$B$6)+(1-$B$5)))*$B$7)/(((($B$5/$B$6)/(($B$5/$B$6)+(1-$B$5)))*$B$7)+(1-(($B$5/$B$6)/(($B$5/$B$6)+(1-$B$5))))))*$B$8)*(1-(1-$B$11)/$B$12)+(1-$B$8)*(1-(1-$B$13)/$B$14))*(1-$B$16)/($B$17-$B$18))+$B$24*((1-((((($B$5/$B$6)/(($B$5/$B$6)+(1-$B$5)))*$B$7)/(((($B$5/$B$6)/(($B$5/$B$6)+(1-$B$5)))*$B$7)+(1-(($B$5/$B$6)/(($B$5/$B$6)+(1-$B$5))))))*$B$8))*$B$19+((((($B$5/$B$6)/(($B$5/$B$6)+(1-$B$5)))*$B$7)/(((($B$5/$B$6)/(($B$5/$B$6)+(1-$B$5)))*$B$7)+(1-(($B$5/$B$6)/(($B$5/$B$6)+(1-$B$5))))))*$B$8)*$B$20))-$B$28)*$B$26/($B$28-$D$50))*$B$27,"n/a") -> 571.02436 | G50: =IFERROR(ABS(F50-E50),"n/a") -> 20.115245 | H50: =IFERROR(G50/$B$32,"n/a") -> 0.035884985 | I50: +/-0.5pp — as suggested in review
A52: Base V0 | B52: =B32 -> 560.54768
